Workbook
Name \G: #REF!
Name \P: #REF!
Name \Q: #REF!
Name \S: #REF!
Name ___CAR3: #REF!
Name ___CLS10: #REF!
Name ___CLS7: #REF!
Name ___CLS8: #REF!
Name ___CLS9: #REF!
Name ___NCL3: #REF!
Name ___PA7: #REF!
Name ___PA8: #REF!
Name ___PAL1: #REF!
Name ___PAL2: #REF!
Name ___PAL3: #REF!
Name ___PAL4: #REF!
Name ___PAL5: #REF!
Name ___PAL6: #REF!
Name ___PAL7: #REF!
Name ___PAL8: #REF!
Name ___PAL9: #REF!
Name ___PD1: #REF!
Name ___PE12: #REF!
Name ___PE13: #REF!
Name ___PE6: #REF!
Name ___PE7: #REF!
Name ___PE8: #REF!
Name ___PE9: #REF!
Name ___PH1: #REF!
Name ___PI1: #REF!
Name ___PK1: #REF!
Name ___PK3: #REF!
Name __bookmark_3: #REF!
Name __bookmark_4: #REF!
Name __bookmark_5: #REF!
Name __bookmark_6: #REF!
Name __bookmark_7: #REF!
Name __CAR3: #REF!
Name __CLS10: #REF!
Name __CLS7: #REF!
Name __CLS8: #REF!
Name __CLS9: #REF!
Name __NCL3: #REF!
Name __PA7: #REF!
Name __PA8: #REF!
Name __PAL1: #REF!
Name __PAL2: #REF!
Name __PAL3: #REF!
Name __PAL4: #REF!
Name __PAL5: #REF!
Name __PAL6: #REF!
Name __PAL7: #REF!
Name __PAL8: #REF!
Name __PAL9: #REF!
Name __PD1: #REF!
Name __PE12: #REF!
Name __PE13: #REF!
Name __PE6: #REF!
Name __PE7: #REF!
Name __PE8: #REF!

Sheet Portfolio Listing
B2: PORTFOLIO Listing
B3: 45657
I4: =#REF! -> #REF!
B5: Kingsway Investment Ltd | D5: Nature | I5: Invested Capital | M5: Realized Value | P5: Unrealized Value | R5: Fund Performance | W5: Expected Return | AB5: Fund Term
B6: No. | C6: Project | D6: Geography | E6: Sector | F6: Asset | G6: Nature | H6: Investment Date | I6: Committed | J6: Funded | K6: Unfunded (O/S) | M6: Distribution | N6: Syndication | P6: MTM Fair Value | R6: DPI (x) | S6: RVPI (x) | T6: TVPI/MOIC (x) | U6: IRR | W6: Upside | X6: Total | Y6: MoIC | Z6: IRR | AB6: Inception | AC6: Expiry | AD6: Entity | AE6: Fee % | AF6: Carry % | AG6: Q3 CAS | AH6: Q3 Investment Report | AI6: Q3 Financial Statements | AJ6: Contributed | AK6: Distributed/ Realised | AL6: Deal expense | AM6: MTM/Unrealised
B7: =ROW()-6 -> 1 | C7: BOYU Capital Fund I | D7: China | E7: Diversified | F7: PE - VC / Growth | G7: Private | H7: 40695 | I7: ='BOYU Capital Fund I'!E10*10^6 -> 30000000 | J7: =-'BOYU Capital Fund I CF'!M2 -> 29454452 | K7: =IF(J7-I7>0,"0",J7-I7) -> -545547.98 | L7: =-K7/I7 -> 0.018184933 | M7: ='BOYU Capital Fund I CF'!M3 -> 92038826 | N7: 0 | P7: ='BOYU Capital Fund I CF'!M4 -> 51248 | R7: =M7/J7 -> 3.1247849 | S7: =P7/J7 -> 0.0017399068 | T7: ='BOYU Capital Fund I'!E18 -> 3.1265248 | U7: ='BOYU Capital Fund I'!E19 -> 0.3363551 | W7: {=SUM(VLOOKUP($C7,'Portfolio Summary'!$C$6:$AO$28,{28,29,30,31,32,33,34},FALSE))} -> 16900319 | X7: =VLOOKUP(C7,'Portfolio Summary'!$C$6:$T$27,14,0) -> 0 | Y7: =VLOOKUP(C7,'Portfolio Summary'!$C$6:$AN$26,3,0) -> 3.1042404 | Z7: =VLOOKUP(C7,'Portfolio Summary'!$C$6:$AN$26,2,0) -> 0.34753879 | AB7: ='BOYU Capital Fund I'!B3 -> 40705 | AC7: 44358 | AD7: CCGBVI | AE7: 2 | AF7: 20 | AG7: Y | AH7: Y | AI7: Y | AJ7: =-J7 -> -29454452 | AK7: =M7 -> 92038826 | AM7: =P7 -> 51248 | AO7: BOYU Capital Fund I, L.P.
B8: =B7+1 -> 2 | C8: Ascendent Fund | D8: China | E8: Diversified | F8: PE - Buyout | G8: Private | H8: 40878 | I8: ='Ascendent CP I'!E10*10^6 -> 10000000 | J8: =-'Ascendant CP I CF'!N2 -> 8570276.4 | K8: =IF(J8-I8>0,"0",J8-I8) -> -1429723.6 | L8: =-K8/I8 -> 0.14297236 | M8: ='Ascendant CP I CF'!N3 -> 20207464 | N8: 0 | P8: ='Ascendant CP I CF'!N4 -> 249627 | R8: =M8/J8 -> 2.3578545 | S8: =P8/J8 -> 0.029127065 | T8: ='Ascendent CP I'!E18 -> 2.3869815 | U8: ='Ascendent CP I'!E19 -> 0.22429716 | W8: {=SUM(VLOOKUP($C8,'Portfolio Summary'!$C$6:$AO$28,{28,29,30,31,32,33,34},FALSE))} -> 8917875.7 | X8: =VLOOKUP(C8,'Portfolio Summary'!$C$6:$T$27,14,0) -> 0 | Y8: =VLOOKUP(C8,'Portfolio Summary'!$C$6:$AN$26,3,0) -> 2.3365704 | Z8: =VLOOKUP(C8,'Portfolio Summary'!$C$6:$AN$26,2,0) -> 0.2338096 | AB8: ='Ascendent CP I'!B3 -> 40651 | AC8: =AB8+365*10 -> 44301 | AD8: CCGBVI | AE8: 2 | AF8: 20 | AG8: Y | AH8: Y | AI8: N | AO8: Ascendent Capital Partners I, L.P.
B9: =B8+1 -> 3 | C9: BOYU Capital Offshore Fund | D9: China | E9: Diversified | F9: HF | G9: PIPP | H9: 42614 | I9: 10000000 | J9: =-'BOYU Offshore CF'!D5 -> 10000000 | K9: =IF(J9-I9>0,"0",J9-I9) -> 0 | L9: =-K9/I9 -> 0 | M9: ='BOYU Offshore CF'!D65 -> 20196163 | N9: 0 | P9: ='BOYU Offshore CF'!D60 -> 793271.37 | R9: =M9/J9 -> 2.0196163 | S9: =P9/J9 -> 0.079327137 | T9: ='BOYU Offshore CF'!D67 -> 2.0989434 | U9: ='BOYU Offshore CF'!D68 -> 0.16955446 | W9: {=SUM(VLOOKUP($C9,'Portfolio Summary'!$C$6:$AO$28,{28,29,30,31,32,33,34},FALSE))} -> 20506163 | X9: =VLOOKUP(C9,'Portfolio Summary'!$C$6:$T$27,14,0) -> 0 | Y9: =VLOOKUP(C9,'Portfolio Summary'!$C$6:$AN$26,3,0) -> 2.0506163 | Z9: =VLOOKUP(C9,'Portfolio Summary'!$C$6:$AN$26,2,0) -> 0.16178617 | AB9: 42618 | AC9: Nil | AD9: CCGBVI | AE9: 2 | AF9: 20 | AG9: N/A | AH9: N/A | AI9: N/A | AJ9: =-J9 -> -10000000 | AK9: =M9 -> 20196163 | AM9: =P9 -> 793271.37 | AO9: BOYU Capital Offshore Fund
B10: =B9+1 -> 4 | C10: E15 Fund I | D10: US | E10: Technology | F10: PE - VC / Growth | G10: VC | H10: 42894 | I10: ='E15 Fund I'!E10*10^6 -> 6000000 | J10: =-'E15 Fund I (CF) '!I2 -> 6000000 | K10: =IF(J10-I10>0,"0",J10-I10) -> 0 | L10: =-K10/I10 -> 0 | M10: ='E15 Fund I (CF) '!I3 -> 4158210.8 | N10: 0 | P10: ='E15 Fund I (CF) '!I4 -> 569305 | R10: =M10/J10 -> 0.69303513 | S10: =P10/J10 -> 0.094884167 | T10: ='E15 Fund I'!E18 -> 0.7879193 | U10: ='E15 Fund I'!E19 -> -0.084686515 | W10: {=SUM(VLOOKUP($C10,'Portfolio Summary'!$C$6:$AO$28,{28,29,30,31,32,33,34},FALSE))} -> 875897.13 | X10: =VLOOKUP(C10,'Portfolio Summary'!$C$6:$T$27,14,0) -> 0 | Y10: =VLOOKUP(C10,'Portfolio Summary'!$C$6:$AN$26,3,0) -> 0.8097018 | Z10: =VLOOKUP(C10,'Portfolio Summary'!$C$6:$AN$26,2,0) -> -0.066498433 | AB10: ='E15 Fund I'!B3 -> 42892 | AC10: 46874 | AD10: Fortune Wheel | AE10: 2 | AF10: 20 | AO10: E15 Fund I, LP
B11: =B10+1 -> 5 | C11: West Street Capital Partners VII | D11: Global | E11: Diversified | F11: PE - Buyout | G11: Private | H11: 43344 | I11: ='West Street VII'!E10*10^6 -> 25000000 | J11: =-'West Street VII (CF)'!N2 -> 20996048 | K11: =IF(J11-I11>0,"0",J11-I11) -> -4003952 | L11: =-K11/I11 -> 0.16015808 | M11: ='West Street VII (CF)'!N3 -> 14856555 | N11: 0 | P11: ='West Street VII (CF)'!N4 -> 14507335 | R11: =M11/J11 -> 0.70758816 | S11: =P11/J11 -> 0.69095551 | T11: ='West Street VII'!E18 -> 1.3985437 | U11: ='West Street VII'!E19 -> 0.14580788 | W11: {=SUM(VLOOKUP($C11,'Portfolio Summary'!$C$6:$AO$28,{28,29,30,31,32,33,34},FALSE))} -> 3037854.7 | X11: =VLOOKUP(C11,'Portfolio Summary'!$C$6:$T$27,14,0) -> 0 | Y11: =VLOOKUP(C11,'Portfolio Summary'!$C$6:$AN$26,3,0) -> 2 | Z11: =VLOOKUP(C11,'Portfolio Summary'!$C$6:$AN$26,2,0) -> 0.18804665 | AB11: ='West Street VII'!B4 -> 43313 | AC11: 46966 | AD11: VMG Ltd | AE11: 1 | AF11: 20 | AG11: Y | AH11: N | AI11: Y | AO11: West Street Capital Partners VII
B12: =B11+1 -> 6 | C12: C Ventures Fund II | D12: China | E12: Technology | F12: PE - VC / Growth | G12: Private | H12: 43373 | I12: ='C Ventures II'!E10*10^6 -> 20000000 | J12: =-'C Ventures II CF '!K2 -> 19929372 | K12: =IF(J12-I12>0,"0",J12-I12) -> -70627.64 | L12: =-K12/I12 -> 0.003531382 | M12: ='C Ventures II CF '!K3 -> 5324899 | N12: 0 | P12: ='C Ventures II CF '!K4 -> 16039005 | R12: =M12/J12 -> 0.26718849 | S12: =P12/J12 -> 0.80479226 | T12: ='C Ventures II'!E18 -> 1.0719808 | U12: ='C Ventures II'!E19 -> 0.017202333 | W12: {=SUM(VLOOKUP($C12,'Portfolio Summary'!$C$6:$AO$28,{28,29,30,31,32,33,34},FALSE))} -> 6046681.3 | X12: =VLOOKUP(C12,'Portfolio Summary'!$C$6:$T$27,14,0) -> 0 | Y12: =VLOOKUP(C12,'Portfolio Summary'!$C$6:$AN$26,3,0) -> 1.4331243 | Z12: =VLOOKUP(C12,'Portfolio Summary'!$C$6:$AN$26,2,0) -> 0.069602423 | AB12: ='C Ventures II'!B3 -> 43373 | AC12: =AB12+365*8 -> 46293 | AD12: CCGBVI | AE12: 2 | AF12: 20 | AG12: Y | AH12: N | AI12: Y | AO12: C Ventures Fund II, L.P.
B13: =B12+1 -> 7 | C13: DCP Capital Partners | D13: China | E13: Diversified | F13: PE - Buyout | G13: Private | H13: 43445 | I13: ='DCP I'!E10*10^6 -> 50000000 | J13: =-'DCP I (CF)'!M2 -> 59725670 | K13: =IF(J13-I13>0,"0",J13-I13) -> 0 | L13: =-K13/I13 -> 0 | M13: ='DCP I (CF)'!M3 -> 28599371 | N13: 0 | P13: ='DCP I (CF)'!M4 -> 41287985 | R13: =M13/J13 -> 0.47884554 | S13: =P13/J13 -> 0.69129379 | T13: ='DCP I'!E18 -> 1.1701393 | U13: ='DCP I'!E19 -> 0.061443415 | W13: {=SUM(VLOOKUP($C13,'Portfolio Summary'!$C$6:$AO$28,{28,29,30,31,32,33,34},FALSE))} -> -4903893.3 | X13: =VLOOKUP(C13,'Portfolio Summary'!$C$6:$T$27,14,0) -> 0 | Y13: =VLOOKUP(C13,'Portfolio Summary'!$C$6:$AN$26,3,0) -> 1.4123037 | Z13: =VLOOKUP(C13,'Portfolio Summary'!$C$6:$AN$26,2,0) -> 0.08650031 | AB13: ='DCP I'!B3 -> 43080 | AC13: =AB13+365*11 -> 47095 | AD13: CCGBVI | AE13: 2 | AF13: 20 | AG13: Y | AH13: Y | AI13: N | AO13: DCP Capital Partners, L.P.
B14: =B13+1 -> 8 | C14: E15 Fund 1.5 | D14: US | E14: Technology | F14: PE - VC / Growth | G14: FinTech | H14: 43466 | I14: ='E15 Fund 1.5 (liquidating)'!E10*10^6 -> 6000000 | J14: =-'E15 Fund 1.5(CF) '!M2 -> 4500000 | K14: =IF(J14-I14>0,"0",J14-I14) -> -1500000 | L14: =-K14/I14 -> 0.25 | M14: ='E15 Fund 1.5(CF) '!M3 -> 3034269.1 | N14: 0 | P14: ='E15 Fund 1.5(CF) '!M4 -> 42858 | R14: =M14/J14 -> 0.67428203 | S14: =P14/J14 -> 0.009524 | T14: ='E15 Fund 1.5 (liquidating)'!E18 -> 0.68380603 | U14: ='E15 Fund 1.5 (liquidating)'!E19 -> -0.38429492 | W14: {=SUM(VLOOKUP($C14,'Portfolio Summary'!$C$6:$AO$28,{28,29,30,31,32,33,34},FALSE))} -> 121480.17 | X14: =VLOOKUP(C14,'Portfolio Summary'!$C$6:$T$27,14,0) -> 0 | Y14: =VLOOKUP(C14,'Portfolio Summary'!$C$6:$AN$26,3,0) -> 0.65096887 | Z14: =VLOOKUP(C14,'Portfolio Summary'!$C$6:$AN$26,2,0) -> -0.92820831 | AB14: 43466 | AC14: 47484 | AD14: Fortune Wheel | AE14: 2 | AF14: 10 | AO14: E15 Fund 1.5, LP
B15: =B14+1 -> 9 | C15: Skycus China Fund | D15: China | E15: Diversified | F15: PE - VC / Growth | G15: Private | H15: 43632 | I15: ='Skycus China Fund'!E10*10^6 -> 30000000 | J15: =-'Skycus China CF'!M2 -> 30000000 | K15: =IF(J15-I15>0,"0",J15-I15) -> 0 | L15: =-K15/I15 -> 0 | M15: ='Skycus China CF'!M3 -> 5327911.5 | N15: 0 | P15: ='Skycus China CF'!M4 -> 39396376 | R15: =M15/J15 -> 0.17759705 | S15: =P15/J15 -> 1.3132125 | T15: ='Skycus China Fund'!E18 -> 1.4908096 | U15: ='Skycus China Fund'!E19 -> 0.072061196 | W15: {=SUM(VLOOKUP($C15,'Portfolio Summary'!$C$6:$AO$28,{28,29,30,31,32,33,34},FALSE))} -> 19951941 | X15: =VLOOKUP(C15,'Portfolio Summary'!$C$6:$T$27,14,0) -> 0 | Y15: =VLOOKUP(C15,'Portfolio Summary'!$C$6:$AN$26,3,0) -> 1.8 | Z15: =VLOOKUP(C15,'Portfolio Summary'!$C$6:$AN$26,2,0) -> 0.08682356 | AB15: ='Skycus China Fund'!B3 -> 43024 | AC15: 46172 | AD15: CCGBVI | AE15: 2 | AF15: 20 | AG15: Y | AH15: Y | AI15: Y | AO15: Skycus China Fund, L.P.
B16: =B15+1 -> 10 | C16: Hongshan Capital Venture Partners Fund VIII (AKA "Sequoia Capital China Venture Partners VIII") | D16: China | E16: Diversified | F16: PE - VC / Growth | G16: Private | H16: 44075 | I16: ='HSG Growth VIII'!E10*10^6 -> 4500000 | J16: =-'HSG Growth VIII (CF)'!L2 -> 4500000 | K16: =IF(J16-I16>0,"0",J16-I16) -> 0 | L16: =-K16/I16 -> 0 | M16: ='HSG Growth VIII (CF)'!L3 -> 0 | N16: 0 | P16: ='HSG Growth VIII (CF)'!L4 -> 4623800 | R16: =M16/J16 -> 0 | S16: =P16/J16 -> 1.0275111 | T16: ='HSG Growth VIII'!E18 -> 1.0275111 | U16: ='HSG Growth VIII'!E19 -> 0.0080131024 | W16: {=SUM(VLOOKUP($C16,'Portfolio Summary'!$C$6:$AO$28,{27,28,29,30,31,32,33,34,35,36,37,38,39},FALSE))} -> 8100000 | X16: =VLOOKUP(C16,'Portfolio Summary'!$C$6:$T$27,14,0) -> 0 | Y16: =VLOOKUP(C16,'Portfolio Summary'!$C$6:$AN$26,3,0) -> 2.8 | Z16: =VLOOKUP(C16,'Portfolio Summary'!$C$6:$AN$26,2,0) -> 0.17868194 | AB16: 44075 | AC16: Nil | AD16: CCGBVI | AE16: Nil | AF16: 15 | AG16: Y | AH16: N | AI16: N | AJ16: =-J16 -> -4500000 | AK16: =M16 -> 0 | AM16: =P16 -> 4623800 | AO16: HongShan Capital Venture Partners Fund VIII, L.P.
B17: =B16+1 -> 11 | C17: HongShan Capital Growth Partners Fund VI (AKA "Sequoia Capital China Growth Partners VI") | D17: China | E17: Diversified | F17: PE - VC / Growth | G17: Private | H17: 44075 | I17: ='HSG Growth VI'!E10*10^6 -> 15750000 | J17: =-'HSG Growth VI (CF) '!L2 -> 15750000 | K17: =IF(J17-I17>0,"0",J17-I17) -> 0 | L17: =-K17/I17 -> 0 | M17: ='HSG Growth VI (CF) '!L3 -> 121791 | N17: 0 | P17: ='HSG Growth VI (CF) '!L4 -> 18019138 | R17: =M17/J17 -> 0.0077327619 | S17: =P17/J17 -> 1.1440723 | T17: ='HSG Growth VI'!E18 -> 1.151805 | U17: ='HSG Growth VI'!E19 -> 0.040418962 | W17: {=SUM(VLOOKUP($C17,'Portfolio Summary'!$C$6:$AO$28,{27,28,29,30,31,32,33,34,35,36,37,38,39},FALSE))} -> 15706709 | X17: =VLOOKUP(C17,'Portfolio Summary'!$C$6:$T$27,14,0) -> 0 | Y17: =VLOOKUP(C17,'Portfolio Summary'!$C$6:$AN$26,3,0) -> 1.9945178 | Z17: =VLOOKUP(C17,'Portfolio Summary'!$C$6:$AN$26,2,0) -> 0.11862699 | AB17: 44075 | AC17: Nil | AD17: CCGBVI | AE17: Nil | AF17: 15 | AG17: Y | AH17: N | AI17: N | AJ17: =-J17 -> -15750000 | AK17: =M17 -> 121791 | AM17: =P17 -> 18019138 | AO17: HongShan Capital Growth Partners Fund VI, L.P.
B18: =B17+1 -> 12 | C18: West Street Capital Partners VIII | D18: Global | E18: Diversified | F18: PE - Buyout | G18: Private | H18: 44136 | I18: ='West Street VIII'!E10*10^6 -> 50000000 | J18: =-'West Street VIII (CF)'!N2 -> 33100000 | K18: =IF(J18-I18>0,"0",J18-I18) -> -16900000 | L18: =-K18/I18 -> 0.338 | M18: ='West Street VIII (CF)'!N3 -> 650000 | N18: 0 | P18: ='West Street VIII (CF)'!N4 -> 38945352 | R18: =M18/J18 -> 0.019637462 | S18: =P18/J18 -> 1.1765967 | T18: ='West Street VIII'!E18 -> 1.1962342 | U18: ='West Street VIII'!E19 -> 0.085717693 | W18: {=SUM(VLOOKUP($C18,'Portfolio Summary'!$C$6:$AO$28,{27,28,29,30,31,32,33,34,35,36,37,38,39},FALSE))} -> 50000000 | X18: =VLOOKUP(C18,'Portfolio Summary'!$C$6:$T$27,14,0) -> 0 | Y18: =VLOOKUP(C18,'Portfolio Summary'!$C$6:$AN$26,3,0) -> 2 | Z18: =VLOOKUP(C18,'Portfolio Summary'!$C$6:$AN$26,2,0) -> 0.16302718 | AB18: ='West Street VIII'!B3 -> 44136 | AC18: ='West Street VIII'!B4 -> 44774 | AD18: VMG Ltd | AE18: 1.5 | AF18: 20 | AG18: Y | AH18: N | AI18: Y | AO18: West Street Capital Partners VIII
B19: =B18+1 -> 13 | C19: DCP Capital Partners II | D19: China | E19: Diversified | F19: PE - Buyout | G19: Private | H19: 44166 | I19: ='DCP II'!E10*10^6 -> 100000000 | J19: =-'DCP II (CF) '!M2 -> 37438527 | K19: =IF(J19-I19>0,"0",J19-I19) -> -62561473 | L19: =-K19/I19 -> 0.62561473 | M19: ='DCP II (CF) '!M3 -> 2676323.4 | N19: 0 | P19: ='DCP II (CF) '!M4 -> 25000583 | R19: =M19/J19 -> 0.07148581 | S19: =P19/J19 -> 0.66777688 | T19: ='DCP II'!E18 -> 0.73926269 | U19: ='DCP II'!E19 -> -0.18608239 | W19: {=SUM(VLOOKUP($C19,'Portfolio Summary'!$C$6:$AO$28,{27,28,29,30,31,32,33,34,35,36,37,38,39},FALSE))} -> 55024118 | X19: =VLOOKUP(C19,'Portfolio Summary'!$C$6:$T$27,14,0) -> 0 | Y19: =VLOOKUP(C19,'Portfolio Summary'!$C$6:$AN$26,3,0) -> 1.8 | Z19: =VLOOKUP(C19,'Portfolio Summary'!$C$6:$AN$26,2,0) -> 0.16096521 | AB19: ='DCP II'!B3 -> 44478 | AC19: 48122 | AD19: CCGBVI | AE19: 2 | AF19: 20 | AG19: Y | AH19: Y | AI19: N | AO19: DCP Capital Partners II, L.P.
B20: =B19+1 -> 14 | C20: Skycus USD Fund II (AKA “Lionet Fund LP”) | D20: China | E20: Diversified | F20: PE - VC / Growth | G20: Private | H20: 44166 | I20: ='Lionet Fund'!E10*10^6 -> 15000000 | J20: =-'Lionet Fund CF'!M2 -> 15728508 | K20: =IF(J20-I20>0,"0",J20-I20) -> 0 | L20: =-K20/I20 -> 0 | M20: ='Lionet Fund CF'!M3 -> 2197607.1 | N20: 0 | P20: ='Lionet Fund CF'!M4 -> 11059809 | R20: =M20/J20 -> 0.13972127 | S20: =P20/J20 -> 0.70316959 | T20: ='Lionet Fund'!E18 -> 0.84289086 | U20: ='Lionet Fund'!E19 -> -0.046108851 | W20: {=SUM(VLOOKUP($C20,'Portfolio Summary'!$C$6:$AO$28,{27,28,29,30,31,32,33,34,35,36,37,38,39},FALSE))} -> 6771491.7 | X20: =VLOOKUP(C20,'Portfolio Summary'!$C$6:$T$27,14,0) -> 0 | Y20: =VLOOKUP(C20,'Portfolio Summary'!$C$6:$AN$26,3,0) -> 1.4305235 | Z20: =VLOOKUP(C20,'Portfolio Summary'!$C$6:$AN$26,2,0) -> 0.060594109 | AB20: ='Lionet Fund'!B3 -> 44013 | AC20: =AB20+365*9 -> 47298 | AD20: CCGBVI | AE20: 2 | AF20: 20 | AG20: Y | AH20: N | AI20: N | AJ20: =-J20 -> -15728508 | AK20: =M20 -> 2197607.1 | AM20: =P20 -> 11059809 | AO20: Skycus USD Fund II ("Lionet Fund")
B21: =B20+1 -> 15 | C21: BOYU Real Estate Fund I | D21: China | E21: Logistic/ Data Center | F21: PE - Real Estate | G21: Property | H21: 44197 | I21: ='Boyu Real Estate'!E10*10^6 -> 30000000 | J21: =-'Boyu Real Estate CF'!M2 -> 19364197 | K21: =IF(J21-I21>0,"0",J21-I21) -> -10635803 | L21: =-K21/I21 -> 0.35452677 | M21: ='Boyu Real Estate CF'!M3 -> 995489.23 | N21: 0 | P21: ='Boyu Real Estate CF'!M4 -> 15342150 | R21: =M21/J21 -> 0.051408754 | S21: =P21/J21 -> 0.79229468 | T21: ='Boyu Real Estate'!E18 -> 0.84370343 | U21: ='Boyu Real Estate'!E19 -> -0.095536217 | W21: {=SUM(VLOOKUP($C21,'Portfolio Summary'!$C$6:$AO$28,{27,28,29,30,31,32,33,34,35,36,37,38,39},FALSE))} -> 39000000 | X21: =VLOOKUP(C21,'Portfolio Summary'!$C$6:$T$27,14,0) -> 0 | Y21: =VLOOKUP(C21,'Portfolio Summary'!$C$6:$AN$26,3,0) -> 2.3 | Z21: =VLOOKUP(C21,'Portfolio Summary'!$C$6:$AN$26,2,0) -> 0.22333994 | AB21: 44197 | AC21: =AB21+365*10 -> 47847 | AD21: CCGBVI | AE21: 1.75 | AF21: 20 | AG21: Y | AH21: Y | AI21: Y | AJ21: =-J21 -> -19364197 | AK21: =M21 -> 995489.23 | AM21: =P21 -> 15342150 | AO21: Boyu Real Estate Fund I, LP
B22: =B21+1 -> 16 | C22: E15 Fund II | D22: Global | E22: Technology | F22: PE - VC / Growth | G22: VC | H22: 44197 | I22: ='E15 Fund II'!E10*10^6 -> 10000000 | J22: =-'E15 Fund II CF'!L2 -> 6595876.3 | K22: =IF(J22-I22>0,"0",J22-I22) -> -3404123.7 | L22: =-K22/I22 -> 0.34041237 | M22: ='E15 Fund II CF'!L3 -> 24622248 | N22: 0 | P22: ='E15 Fund II CF'!L4 -> 2681000 | R22: =M22/J22 -> 3.732976 | S22: =P22/J22 -> 0.40646608 | T22: ='E15 Fund II'!E18 -> 4.1394421 | U22: ='E15 Fund II'!E19 -> 4.4740932 | W22: {=SUM(VLOOKUP($C22,'Portfolio Summary'!$C$6:$AO$28,{28,29,30,31,32,33,34},FALSE))} -> 17791489 | X22: =VLOOKUP(C22,'Portfolio Summary'!$C$6:$T$27,14,0) -> 0 | Y22: =VLOOKUP(C22,'Portfolio Summary'!$C$6:$AN$26,3,0) -> 3.9922991 | Z22: =VLOOKUP(C22,'Portfolio Summary'!$C$6:$AN$26,2,0) -> 3.7867348 | AB22: 44197 | AC22: 47849 | AD22: Fortune Wheel | AE22: 2 | AF22: 20 | AG22: N | AH22: Y | AI22: N | AJ22: =-J22 -> -6595876.3 | AK22: =M22 -> 24622248 | AM22: =P22 -> 2681000 | AO22: E15 Fund II, LP
B23: =B22+1 -> 17 | C23: Cottonwood | D23: US | E23: Real Estate | F23: PE - Special Situations | G23: Private | H23: 45393 | I23: =Cottonwood!E10*10^6 -> 12500000 | J23: =-'Cottonwood (CF)'!N2 -> 3150647.5 | K23: =IF(J23-I23>0,"0",J23-I23) -> -9349352.5 | L23: =-K23/I23 -> 0.7479482 | M23: ='Cottonwood (CF)'!N3 -> 0 | N23: 0 | P23: ='Cottonwood (CF)'!N4 -> 3779467 | R23: =M23/J23 -> 0 | S23: =P23/J23 -> 1.1995842 | T23: =Cottonwood!E18 -> 1.1995842 | U23: =Cottonwood!E19 -> 0.44407232 | W23: {=SUM(VLOOKUP($C23,'Portfolio Summary'!$C$6:$AO$28,{27,28,29,30,31,32,33,34,35,36,37,38,39},FALSE))} -> 18875000 | X23: =VLOOKUP(C23,'Portfolio Summary'!$C$6:$T$27,14,0) -> 0 | Y23: =VLOOKUP(C23,'Portfolio Summary'!$C$6:$AN$26,3,0) -> 2.51 | Z23: =VLOOKUP(C23,'Portfolio Summary'!$C$6:$AN$26,2,0) -> 0.28061346 | AB23: 45383 | AC23: 2030 | AD23: CCGBVI | AE23: 1.5 | AF23: 20 | AO23: Cottonwood-WTT Real Estate Special Situations Fund, LP
B24: =B23+1 -> 18 | C24: Genedant Ventures I | D24: Global | E24: Diversified | F24: PE - VC / Growth | G24: VC | H24: 45518 | I24: ='Genedant Ventures'!E10*10^6 -> 37600000 | J24: =-'Genedent Ventures (CF)'!M2 -> 2954733 | K24: =IF(J24-I24>0,"0",J24-I24) -> -34645267 | L24: =-K24/I24 -> 0.92141668 | M24: 0 | N24: 0 | P24: ='Genedent Ventures (CF)'!L14 -> 2186280 | R24: =M24/J24 -> 0 | S24: =P24/J24 -> 0.73992472 | T24: ='Genedant Ventures'!E18 -> 0.73992472 | U24: ='Genedant Ventures'!E19 -> -0.67657796 | W24: {=SUM(VLOOKUP($C24,'Portfolio Summary'!$C$6:$AO$28,{27,28,29,30,31,32,33,34,35,36,37,38,39},FALSE))} -> 2216049.8 | X24: =VLOOKUP(C24,'Portfolio Summary'!$C$6:$T$27,14,0) -> 0 | Y24: =VLOOKUP(C24,'Portfolio Summary'!$C$6:$AN$26,3,0) -> 3.5 | Z24: =VLOOKUP(C24,'Portfolio Summary'!$C$6:$AN$26,2,0) -> 0.18861382 | AB24: 45413 | AC24: 49065 | AD24: BII | AE24: 2 | AF24: 20 | AO24: Genedant Ventures I
B25: =B24+1 -> 19 | C25: GTCR XIV Access Offshore LP | D25: US | E25: Diversified | F25: PE - Buyout | G25: Buyout | H25: 45261 | I25: 16940000 | J25: =-'GTCR (CF)'!M2 -> 1756064.1 | K25: =J25-I25 -> -15183936 | L25: =-K25/I25 -> 0.89633624 | M25: 0 | N25: 0 | P25: ='GTCR (CF)'!L14 -> 2093389 | R25: =M25/J25 -> 0 | S25: =P25/J25 -> 1.1920915 | T25: =(P25+M25)/J25 -> 1.1920915 | U25: ='GTCR (CF)'!M5 -> 1.5680467 | W25: {=SUM(VLOOKUP($C25,'Portfolio Summary'!$C$6:$AO$28,{27,28,29,30,31,32,33,34,35,36,37,38,39},FALSE))} -> 8470000 | X25: =VLOOKUP(C25,'Portfolio Summary'!$C$6:$T$27,14,0) -> 0 | Y25: =VLOOKUP(C25,'Portfolio Summary'!$C$6:$AN$26,3,0) -> 2.5 | Z25: =VLOOKUP(C25,'Portfolio Summary'!$C$6:$AN$26,2,0) -> 0.22347825 | AB25: 45292 | AC25: 48945 | AD25: VMG Ltd | AE25: 2 | AF25: 20 | AO25: GTCR XIV Access Offshore LP
C27: Total_PE Fund | I27: =SUM(I7:I26) -> 479290000 | J27: =SUM(J7:J26) -> 3.2951437e+08 | K27: =SUM(K7:K26) -> -1.6022981e+08 | M27: =SUM(M7:M26) -> 2.2500713e+08 | N27: =SUM(N7:N26) -> 0 | P27: =SUM(P7:P26) -> 2.3666798e+08 | Q27: d | R27: =M27/J27 -> 0.68284465 | T27: =(P27+M27)/J27 -> 1.4010773 | W27: =SUM(W7:W26) -> 2.9340918e+08 | X27: =SUM(X7:X26) -> 0 | Y27: ='Portfolio Summary'!E26 -> 1.4469843 | Z27: ='Portfolio Summary'!D26 -> 0.19990547
B35: 4 | C35: Ark Pacific Special Oppor Fund I | G35: Private | H35: 42887 | I35: 5000000 | J35: 3413271.4 | K35: -1586728.6 | M35: 3636000 | N35: 0 | P35: 488000 | R35: 1.0652537 | S35: 0.14297134 | T35: 1.208225 | U35: 0.037474552 | W35: #N/A | X35: #N/A | Y35: #N/A | Z35: #N/A | AB35: 42181 | AC35: 44738 | AD35: VPP | AE35: 2 | AF35: 15 | AG35: Y | AH35: Y | AI35: N

Sheet Portfolio Summary
B2: Kingsway Investment - PE Fund Investment Summary
D3: Forecast | F3: Up to date | H3: Nature | M3: Capital Investment | Q3: Realized Value | U3: 40908 | V3: =+EOMONTH(U3,12) -> 41274 | W3: =+EOMONTH(V3,12) -> 41639 | X3: =+EOMONTH(W3,12) -> 42004 | Y3: =+EOMONTH(X3,12) -> 42369 | Z3: =+EOMONTH(Y3,12) -> 42735 | AA3: =+EOMONTH(Z3,12) -> 43100 | AB3: =+EOMONTH(AA3,12) -> 43465 | AC3: =+EOMONTH(AB3,12) -> 43830 | ... AX3: =+EOMONTH(AW3,12) -> 51501
B4: No. | C4: PE Fund | D4: IRR | E4: MoIC | F4: IRR | G4: MoIC | H4: Geography | I4: Sector | J4: Asset | K4: Nature | L4: Investment Date | M4: Committed | N4: Funded | O4: O/S | Q4: Distribution | R4: Syndicated to Genedant | S4: MTM Value | T4: Total | U4: 0 | V4: =U4+1 -> 1 | W4: =V4+1 -> 2 | X4: =W4+1 -> 3 | Y4: =X4+1 -> 4 | Z4: =Y4+1 -> 5 | AA4: =Z4+1 -> 6 | AB4: =AA4+1 -> 7 | AC4: =AB4+1 -> 8 | ... AX4: =AW4+1 -> 29
B5: Net Cash Flow
B6: 1 | C6: BOYU Capital Fund I | D6: =IRR(U6:AX6) -> 0.34753879 | E6: =T65/-T41 -> 3.1042404 | F6: =+INDEX('Portfolio Listing'!$U$7:$U$28,MATCH(C6,'Portfolio Listing'!$C$7:$C$28,0)) -> 0.3363551 | G6: ='Portfolio Listing'!T7 -> 3.1265248 | H6: =VLOOKUP($C6,'Portfolio Listing'!$C$7:$AF$28,2,FALSE) -> China | I6: =VLOOKUP($C6,'Portfolio Listing'!$C$7:$AF$28,3,FALSE) -> Diversified | J6: =VLOOKUP($C6,'Portfolio Listing'!$C$7:$AF$28,4,FALSE) -> PE - VC / Growth | K6: Private | L6: ='Portfolio Listing'!H7 -> 40695 | M6: =VLOOKUP(C6,'Portfolio Listing'!$C$7:$AF$28,7,FALSE) -> 30000000 | N6: =VLOOKUP(C6,'Portfolio Listing'!$C$7:$AF$28,8,FALSE) -> 29454452 | O6: =IF(N6-M6>0,0,N6-M6) -> -545547.98 | Q6: =VLOOKUP(C6,'Portfolio Listing'!$C$7:$AF$28,11,FALSE) -> 92038826 | R6: =VLOOKUP(C6,'Portfolio Listing'!$C$7:$AF$28,12,FALSE) -> 0 | S6: =VLOOKUP(C6,'Portfolio Listing'!$C$7:$AF$28,14,FALSE) -> 51248 | T6: =SUM(U6:AX6) -> 62584374 | U6: =U41+U65 -> -2738663.8 | V6: =V41+V65 -> -12024167 | W6: =W41+W65 -> -892468.02 | X6: =X41+X65 -> -4209772.1 | Y6: =Y41+Y65 -> 15963275 | Z6: =Z41+Z65 -> 12562086 | AA6: =AA41+AA65 -> 22614615 | AB6: =AB41+AB65 -> 6209234.1 | ... AX6: =AX41+AX65 -> 0 | AZ6: =+INDEX('Portfolio Listing'!$AO$7:$AO$28,MATCH('Portfolio Summary'!$C6,'Portfolio Listing'!$C$7:$C$28,0)) -> BOYU Capital Fund I, L.P.
B7: =B6+1 -> 2 | C7: Ascendent Fund | D7: =IRR(U7:AX7) -> 0.2338096 | E7: =T66/-T42 -> 2.3365704 | F7: =+INDEX('Portfolio Listing'!$U$7:$U$28,MATCH(C7,'Portfolio Listing'!$C$7:$C$28,0)) -> 0.22429716 | G7: ='Portfolio Listing'!T8 -> 2.3869815 | H7: =VLOOKUP($C7,'Portfolio Listing'!$C$7:$AF$28,2,FALSE) -> China | I7: =VLOOKUP($C7,'Portfolio Listing'!$C$7:$AF$28,3,FALSE) -> Diversified | J7: =VLOOKUP($C7,'Portfolio Listing'!$C$7:$AF$28,4,FALSE) -> PE - Buyout | K7: Private | L7: ='Portfolio Listing'!H8 -> 40878 | M7: =VLOOKUP(C7,'Portfolio Listing'!$C$7:$AF$28,7,FALSE) -> 10000000 | N7: =VLOOKUP(C7,'Portfolio Listing'!$C$7:$AF$28,8,FALSE) -> 8570276.4 | O7: =IF(N7-M7>0,0,N7-M7) -> -1429723.6 | Q7: =VLOOKUP(C7,'Portfolio Listing'!$C$7:$AF$28,11,FALSE) -> 20207464 | R7: =VLOOKUP(C7,'Portfolio Listing'!$C$7:$AF$28,12,FALSE) -> 0 | S7: =VLOOKUP(C7,'Portfolio Listing'!$C$7:$AF$28,14,FALSE) -> 249627 | T7: =SUM(U7:AX7) -> 12237188 | U7: =U42+U66 -> 0 | V7: =V42+V66 -> -2337283.7 | W7: =W42+W66 -> -2121566.2 | X7: =X42+X66 -> -118164.22 | Y7: =Y42+Y66 -> -309527.97 | Z7: =Z42+Z66 -> 2864132.1 | AA7: =AA42+AA66 -> 3478488.3 | AB7: =AB42+AB66 -> 1917146.6 | ... AX7: =AX42+AX66 -> 0 | AZ7: =+INDEX('Portfolio Listing'!$AO$7:$AO$28,MATCH('Portfolio Summary'!$C7,'Portfolio Listing'!$C$7:$C$28,0)) -> Ascendent Capital Partners I, L.P.
B8: =B7+1 -> 3 | C8: BOYU Capital Offshore Fund | D8: =IRR(U8:AX8) -> 0.16178617 | E8: =T67/-T43 -> 2.0506163 | F8: =+INDEX('Portfolio Listing'!$U$7:$U$28,MATCH(C8,'Portfolio Listing'!$C$7:$C$28,0)) -> 0.16955446 | G8: ='Portfolio Listing'!T9 -> 2.0989434 | H8: =VLOOKUP($C8,'Portfolio Listing'!$C$7:$AF$28,2,FALSE) -> China | I8: =VLOOKUP($C8,'Portfolio Listing'!$C$7:$AF$28,3,FALSE) -> Diversified | J8: =VLOOKUP($C8,'Portfolio Listing'!$C$7:$AF$28,4,FALSE) -> HF | K8: PIPP | L8: ='Portfolio Listing'!H9 -> 42614 | M8: =VLOOKUP(C8,'Portfolio Listing'!$C$7:$AF$28,7,FALSE) -> 10000000 | N8: =VLOOKUP(C8,'Portfolio Listing'!$C$7:$AF$28,8,FALSE) -> 10000000 | O8: =IF(N8-M8>0,0,N8-M8) -> 0 | Q8: =VLOOKUP(C8,'Portfolio Listing'!$C$7:$AF$28,11,FALSE) -> 20196163 | R8: =VLOOKUP(C8,'Portfolio Listing'!$C$7:$AF$28,12,FALSE) -> 0 | S8: =VLOOKUP(C8,'Portfolio Listing'!$C$7:$AF$28,14,FALSE) -> 793271.37 | T8: =SUM(U8:AX8) -> 10506163 | U8: =U43+U67 -> 0 | V8: =V43+V67 -> 0 | W8: =W43+W67 -> 0 | X8: =X43+X67 -> 0 | Y8: =Y43+Y67 -> 0 | Z8: =Z43+Z67 -> -10000000 | AA8: =AA43+AA67 -> 0 | AB8: =AB43+AB67 -> 0 | ... AX8: =AX43+AX67 -> 0 | AZ8: =+INDEX('Portfolio Listing'!$AO$7:$AO$28,MATCH('Portfolio Summary'!$C8,'Portfolio Listing'!$C$7:$C$28,0)) -> BOYU Capital Offshore Fund
B9: =B8+1 -> 4 | C9: E15 Fund I | D9: =IRR(U9:AX9) -> -0.066498433 | E9: =T69/-T45 -> 0.8097018 | F9: =+INDEX('Portfolio Listing'!$U$7:$U$28,MATCH(C9,'Portfolio Listing'!$C$7:$C$28,0)) -> -0.084686515 | G9: ='Portfolio Listing'!T10 -> 0.7879193 | H9: =VLOOKUP($C9,'Portfolio Listing'!$C$7:$AF$28,2,FALSE) -> US | I9: =VLOOKUP($C9,'Portfolio Listing'!$C$7:$AF$28,3,FALSE) -> Technology | J9: =VLOOKUP($C9,'Portfolio Listing'!$C$7:$AF$28,4,FALSE) -> PE - VC / Growth | K9: VC | L9: ='Portfolio Listing'!H10 -> 42894 | M9: =VLOOKUP(C9,'Portfolio Listing'!$C$7:$AF$28,7,FALSE) -> 6000000 | N9: =VLOOKUP(C9,'Portfolio Listing'!$C$7:$AF$28,8,FALSE) -> 6000000 | O9: =IF(N9-M9>0,0,N9-M9) -> 0 | Q9: =VLOOKUP(C9,'Portfolio Listing'!$C$7:$AF$28,11,FALSE) -> 4158210.8 | R9: =VLOOKUP(C9,'Portfolio Listing'!$C$7:$AF$28,12,FALSE) -> 0 | S9: =VLOOKUP(C9,'Portfolio Listing'!$C$7:$AF$28,14,FALSE) -> 569305 | T9: =SUM(U9:AX9) -> -1141789.2 | U9: =U45+U69 -> 0 | V9: =V45+V69 -> 0 | W9: =W45+W69 -> 0 | X9: =X45+X69 -> 0 | Y9: =Y45+Y69 -> 0 | Z9: =Z45+Z69 -> 0 | AA9: =AA45+AA69 -> -6000000 | AB9: =AB45+AB69 -> 0 | ... AX9: =AX45+AX69 -> 0 | AZ9: =+INDEX('Portfolio Listing'!$AO$7:$AO$28,MATCH('Portfolio Summary'!$C9,'Portfolio Listing'!$C$7:$C$28,0)) -> E15 Fund I, LP
B10: =B9+1 -> 5 | C10: West Street Capital Partners VII | D10: =IRR(U10:AX10) -> 0.18804665 | E10: =T70/-T46 -> 2 | F10: =+INDEX('Portfolio Listing'!$U$7:$U$28,MATCH(C10,'Portfolio Listing'!$C$7:$C$28,0)) -> 0.14580788 | G10: ='Portfolio Listing'!T11 -> 1.3985437 | H10: =VLOOKUP($C10,'Portfolio Listing'!$C$7:$AF$28,2,FALSE) -> Global | I10: =VLOOKUP($C10,'Portfolio Listing'!$C$7:$AF$28,3,FALSE) -> Diversified | J10: =VLOOKUP($C10,'Portfolio Listing'!$C$7:$AF$28,4,FALSE) -> PE - Buyout | K10: Private | L10: ='Portfolio Listing'!H11 -> 43344 | M10: =VLOOKUP(C10,'Portfolio Listing'!$C$7:$AF$28,7,FALSE) -> 25000000 | N10: =VLOOKUP(C10,'Portfolio Listing'!$C$7:$AF$28,8,FALSE) -> 20996048 | O10: =IF(N10-M10>0,0,N10-M10) -> -4003952 | Q10: =VLOOKUP(C10,'Portfolio Listing'!$C$7:$AF$28,11,FALSE) -> 14856555 | R10: =VLOOKUP(C10,'Portfolio Listing'!$C$7:$AF$28,12,FALSE) -> 0 | S10: =VLOOKUP(C10,'Portfolio Listing'!$C$7:$AF$28,14,FALSE) -> 14507335 | T10: =SUM(U10:AX10) -> 25000000 | U10: =U46+U70 -> 0 | V10: =V46+V70 -> 0 | W10: =W46+W70 -> 0 | X10: =X46+X70 -> 0 | Y10: =Y46+Y70 -> 0 | Z10: =Z46+Z70 -> 0 | AA10: =AA46+AA70 -> 0 | AB10: =AB46+AB70 -> 0 | ... AX10: =AX46+AX70 -> 0 | AZ10: =+INDEX('Portfolio Listing'!$AO$7:$AO$28,MATCH('Portfolio Summary'!$C10,'Portfolio Listing'!$C$7:$C$28,0)) -> West Street Capital Partners VII
B11: =B10+1 -> 6 | C11: C Ventures Fund II | D11: =IRR(U11:AX11) -> 0.069602423 | E11: =T71/-T47 -> 1.4331243 | F11: =+INDEX('Portfolio Listing'!$U$7:$U$28,MATCH(C11,'Portfolio Listing'!$C$7:$C$28,0)) -> 0.017202333 | G11: ='Portfolio Listing'!T12 -> 1.0719808 | H11: =VLOOKUP($C11,'Portfolio Listing'!$C$7:$AF$28,2,FALSE) -> China | I11: =VLOOKUP($C11,'Portfolio Listing'!$C$7:$AF$28,3,FALSE) -> Technology | J11: =VLOOKUP($C11,'Portfolio Listing'!$C$7:$AF$28,4,FALSE) -> PE - VC / Growth | K11: Private | L11: ='Portfolio Listing'!H12 -> 43373 | M11: =VLOOKUP(C11,'Portfolio Listing'!$C$7:$AF$28,7,FALSE) -> 20000000 | N11: =VLOOKUP(C11,'Portfolio Listing'!$C$7:$AF$28,8,FALSE) -> 19929372 | O11: =IF(N11-M11>0,0,N11-M11) -> -70627.64 | Q11: =VLOOKUP(C11,'Portfolio Listing'!$C$7:$AF$28,11,FALSE) -> 5324899 | R11: =VLOOKUP(C11,'Portfolio Listing'!$C$7:$AF$28,12,FALSE) -> 0 | S11: =VLOOKUP(C11,'Portfolio Listing'!$C$7:$AF$28,14,FALSE) -> 16039005 | T11: =SUM(U11:AX11) -> 9066713.9 | U11: =U47+U71 -> 0 | V11: =V47+V71 -> 0 | W11: =W47+W71 -> 0 | X11: =X47+X71 -> 0 | Y11: =Y47+Y71 -> 0 | Z11: =Z47+Z71 -> 0 | AA11: =AA47+AA71 -> 0 | AB11: =AB47+AB71 -> -2000000 | ... AX11: =AX47+AX71 -> 0 | AZ11: =+INDEX('Portfolio Listing'!$AO$7:$AO$28,MATCH('Portfolio Summary'!$C11,'Portfolio Listing'!$C$7:$C$28,0)) -> C Ventures Fund II, L.P.
B12: =B11+1 -> 7 | C12: DCP Capital Partners | D12: =IRR(U12:AX12) -> 0.08650031 | E12: =T72/-T48 -> 1.4123037 | F12: =+INDEX('Portfolio Listing'!$U$7:$U$28,MATCH(C12,'Portfolio Listing'!$C$7:$C$28,0)) -> 0.061443415 | G12: ='Portfolio Listing'!T13 -> 1.1701393 | H12: =VLOOKUP($C12,'Portfolio Listing'!$C$7:$AF$28,2,FALSE) -> China | I12: =VLOOKUP($C12,'Portfolio Listing'!$C$7:$AF$28,3,FALSE) -> Diversified | J12: =VLOOKUP($C12,'Portfolio Listing'!$C$7:$AF$28,4,FALSE) -> PE - Buyout | K12: Private | L12: ='Portfolio Listing'!H13 -> 43445 | M12: =VLOOKUP(C12,'Portfolio Listing'!$C$7:$AF$28,7,FALSE) -> 50000000 | N12: =VLOOKUP(C12,'Portfolio Listing'!$C$7:$AF$28,8,FALSE) -> 59725670 | O12: =IF(N12-M12>0,0,N12-M12) -> 0 | Q12: =VLOOKUP(C12,'Portfolio Listing'!$C$7:$AF$28,11,FALSE) -> 28599371 | R12: =VLOOKUP(C12,'Portfolio Listing'!$C$7:$AF$28,12,FALSE) -> 0 | S12: =VLOOKUP(C12,'Portfolio Listing'!$C$7:$AF$28,14,FALSE) -> 41287985 | T12: =SUM(U12:AX12) -> 26274330 | U12: =U48+U72 -> 0 | V12: =V48+V72 -> 0 | W12: =W48+W72 -> 0 | X12: =X48+X72 -> 0 | Y12: =Y48+Y72 -> 0 | Z12: =Z48+Z72 -> 0 | AA12: =AA48+AA72 -> 0 | AB12: =AB48+AB72 -> 0 | ... AX12: =AX48+AX72 -> 0 | AZ12: =+INDEX('Portfolio Listing'!$AO$7:$AO$28,MATCH('Portfolio Summary'!$C12,'Portfolio Listing'!$C$7:$C$28,0)) -> DCP Capital Partners, L.P.
B13: =B12+1 -> 8 | C13: E15 Fund 1.5 | D13: =IRR(U13:AX13) -> -0.92820831 | E13: =T73/-T49 -> 0.65096887 | F13: =+INDEX('Portfolio Listing'!$U$7:$U$28,MATCH(C13,'Portfolio Listing'!$C$7:$C$28,0)) -> -0.38429492 | G13: ='Portfolio Listing'!T14 -> 0.68380603 | H13: =VLOOKUP($C13,'Portfolio Listing'!$C$7:$AF$28,2,FALSE) -> US | I13: =VLOOKUP($C13,'Portfolio Listing'!$C$7:$AF$28,3,FALSE) -> Technology | J13: =VLOOKUP($C13,'Portfolio Listing'!$C$7:$AF$28,4,FALSE) -> PE - VC / Growth | K13: FinTech | L13: ='Portfolio Listing'!H14 -> 43466 | M13: =VLOOKUP(C13,'Portfolio Listing'!$C$7:$AF$28,7,FALSE) -> 6000000 | N13: =VLOOKUP(C13,'Portfolio Listing'!$C$7:$AF$28,8,FALSE) -> 4500000 | O13: =IF(N13-M13>0,0,N13-M13) -> -1500000 | Q13: =VLOOKUP(C13,'Portfolio Listing'!$C$7:$AF$28,11,FALSE) -> 3034269.1 | R13: =VLOOKUP(C13,'Portfolio Listing'!$C$7:$AF$28,12,FALSE) -> 0 | S13: =VLOOKUP(C13,'Portfolio Listing'!$C$7:$AF$28,14,FALSE) -> 42858 | T13: =SUM(U13:AX13) -> -1570640.1 | U13: =U49+U73 -> 0 | V13: =V49+V73 -> 0 | W13: =W49+W73 -> 0 | X13: =X49+X73 -> 0 | Y13: =Y49+Y73 -> 0 | Z13: =Z49+Z73 -> 0 | AA13: =AA49+AA73 -> 0 | AB13: =AB49+AB73 -> 0 | ... AX13: =AX49+AX73 -> 0 | AZ13: =+INDEX('Portfolio Listing'!$AO$7:$AO$28,MATCH('Portfolio Summary'!$C13,'Portfolio Listing'!$C$7:$C$28,0)) -> E15 Fund 1.5, LP
B14: =B13+1 -> 9 | C14: Skycus China Fund | D14: =IRR(U14:AX14) -> 0.08682356 | E14: =T74/-T50 -> 1.8 | F14: =+INDEX('Portfolio Listing'!$U$7:$U$28,MATCH(C14,'Portfolio Listing'!$C$7:$C$28,0)) -> 0.072061196 | G14: ='Portfolio Listing'!T15 -> 1.4908096 | H14: =VLOOKUP($C14,'Portfolio Listing'!$C$7:$AF$28,2,FALSE) -> China | I14: =VLOOKUP($C14,'Portfolio Listing'!$C$7:$AF$28,3,FALSE) -> Diversified | J14: =VLOOKUP($C14,'Portfolio Listing'!$C$7:$AF$28,4,FALSE) -> PE - VC / Growth | K14: Private | L14: ='Portfolio Listing'!H15 -> 43632 | M14: =VLOOKUP(C14,'Portfolio Listing'!$C$7:$AF$28,7,FALSE) -> 30000000 | N14: =VLOOKUP(C14,'Portfolio Listing'!$C$7:$AF$28,8,FALSE) -> 30000000 | O14: =IF(N14-M14>0,0,N14-M14) -> 0 | Q14: =VLOOKUP(C14,'Portfolio Listing'!$C$7:$AF$28,11,FALSE) -> 5327911.5 | R14: =VLOOKUP(C14,'Portfolio Listing'!$C$7:$AF$28,12,FALSE) -> 0 | S14: =VLOOKUP(C14,'Portfolio Listing'!$C$7:$AF$28,14,FALSE) -> 39396376 | T14: =SUM(U14:AX14) -> 24000000 | U14: =U50+U74 -> 0 | V14: =V50+V74 -> 0 | W14: =W50+W74 -> 0 | X14: =X50+X74 -> 0 | Y14: =Y50+Y74 -> 0 | Z14: =Z50+Z74 -> 0 | AA14: =AA50+AA74 -> 0 | AB14: =AB50+AB74 -> -18000000 | ... AX14: =AX50+AX74 -> 0 | AZ14: =+INDEX('Portfolio Listing'!$AO$7:$AO$28,MATCH('Portfolio Summary'!$C14,'Portfolio Listing'!$C$7:$C$28,0)) -> Skycus China Fund, L.P.
B15: =B14+1 -> 10 | C15: Hongshan Capital Venture Partners Fund VIII (AKA "Sequoia Capital China Venture Partners VIII") | D15: =IRR(U15:AX15) -> 0.17868194 | E15: =T75/-T51 -> 2.8 | F15: =+INDEX('Portfolio Listing'!$U$7:$U$28,MATCH(C15,'Portfolio Listing'!$C$7:$C$28,0)) -> 0.0080131024 | G15: ='Portfolio Listing'!T16 -> 1.0275111 | H15: =VLOOKUP($C15,'Portfolio Listing'!$C$7:$AF$28,2,FALSE) -> China | I15: =VLOOKUP($C15,'Portfolio Listing'!$C$7:$AF$28,3,FALSE) -> Diversified | J15: =VLOOKUP($C15,'Portfolio Listing'!$C$7:$AF$28,4,FALSE) -> PE - VC / Growth | K15: Private | L15: ='Portfolio Listing'!H16 -> 44075 | M15: =VLOOKUP(C15,'Portfolio Listing'!$C$7:$AF$28,7,FALSE) -> 4500000 | N15: =VLOOKUP(C15,'Portfolio Listing'!$C$7:$AF$28,8,FALSE) -> 4500000 | O15: =IF(N15-M15>0,0,N15-M15) -> 0 | Q15: =VLOOKUP(C15,'Portfolio Listing'!$C$7:$AF$28,11,FALSE) -> 0 | R15: =VLOOKUP(C15,'Portfolio Listing'!$C$7:$AF$28,12,FALSE) -> 0 | S15: =VLOOKUP(C15,'Portfolio Listing'!$C$7:$AF$28,14,FALSE) -> 4623800 | T15: =SUM(U15:AX15) -> 8100000 | U15: =U51+U75 -> 0 | V15: =V51+V75 -> 0 | W15: =W51+W75 -> 0 | X15: =X51+X75 -> 0 | Y15: =Y51+Y75 -> 0 | Z15: =Z51+Z75 -> 0 | AA15: =AA51+AA75 -> 0 | AB15: =AB51+AB75 -> 0 | ... AX15: =AX51+AX75 -> 0 | AZ15: =+INDEX('Portfolio Listing'!$AO$7:$AO$28,MATCH('Portfolio Summary'!$C15,'Portfolio Listing'!$C$7:$C$28,0)) -> HongShan Capital Venture Partners Fund VIII, L.P.
B16: =B15+1 -> 11 | C16: HongShan Capital Growth Partners Fund VI (AKA "Sequoia Capital China Growth Partners VI") | D16: =IRR(U16:AX16) -> 0.11862699 | E16: =T76/-T52 -> 1.9945178 | F16: =+INDEX('Portfolio Listing'!$U$7:$U$28,MATCH(C16,'Portfolio Listing'!$C$7:$C$28,0)) -> 0.040418962 | G16: ='Portfolio Listing'!T17 -> 1.151805 | H16: =VLOOKUP($C16,'Portfolio Listing'!$C$7:$AF$28,2,FALSE) -> China | I16: =VLOOKUP($C16,'Portfolio Listing'!$C$7:$AF$28,3,FALSE) -> Diversified | J16: =VLOOKUP($C16,'Portfolio Listing'!$C$7:$AF$28,4,FALSE) -> PE - VC / Growth | K16: Private | L16: ='Portfolio Listing'!H17 -> 44075 | M16: =VLOOKUP(C16,'Portfolio Listing'!$C$7:$AF$28,7,FALSE) -> 15750000 | N16: =VLOOKUP(C16,'Portfolio Listing'!$C$7:$AF$28,8,FALSE) -> 15750000 | O16: =IF(N16-M16>0,0,N16-M16) -> 0 | Q16: =VLOOKUP(C16,'Portfolio Listing'!$C$7:$AF$28,11,FALSE) -> 121791 | R16: =VLOOKUP(C16,'Portfolio Listing'!$C$7:$AF$28,12,FALSE) -> 0 | S16: =VLOOKUP(C16,'Portfolio Listing'!$C$7:$AF$28,14,FALSE) -> 18019138 | T16: =SUM(U16:AX16) -> 15706709 | U16: =U52+U76 -> 0 | V16: =V52+V76 -> 0 | W16: =W52+W76 -> 0 | X16: =X52+X76 -> 0 | Y16: =Y52+Y76 -> 0 | Z16: =Z52+Z76 -> 0 | AA16: =AA52+AA76 -> 0 | AB16: =AB52+AB76 -> 0 | ... AX16: =AX52+AX76 -> 0 | AZ16: =+INDEX('Portfolio Listing'!$AO$7:$AO$28,MATCH('Portfolio Summary'!$C16,'Portfolio Listing'!$C$7:$C$28,0)) -> HongShan Capital Growth Partners Fund VI, L.P.
B17: =B16+1 -> 12 | C17: West Street Capital Partners VIII | D17: =IRR(U17:AX17) -> 0.16302718 | E17: =T77/-T53 -> 2 | F17: =+INDEX('Portfolio Listing'!$U$7:$U$28,MATCH(C17,'Portfolio Listing'!$C$7:$C$28,0)) -> 0.085717693 | G17: ='Portfolio Listing'!T18 -> 1.1962342 | H17: =VLOOKUP($C17,'Portfolio Listing'!$C$7:$AF$28,2,FALSE) -> Global | I17: =VLOOKUP($C17,'Portfolio Listing'!$C$7:$AF$28,3,FALSE) -> Diversified | J17: =VLOOKUP($C17,'Portfolio Listing'!$C$7:$AF$28,4,FALSE) -> PE - Buyout | K17: Private | L17: ='Portfolio Listing'!H18 -> 44136 | M17: =VLOOKUP(C17,'Portfolio Listing'!$C$7:$AF$28,7,FALSE) -> 50000000 | N17: =VLOOKUP(C17,'Portfolio Listing'!$C$7:$AF$28,8,FALSE) -> 33100000 | O17: =IF(N17-M17>0,0,N17-M17) -> -16900000 | Q17: =VLOOKUP(C17,'Portfolio Listing'!$C$7:$AF$28,11,FALSE) -> 650000 | R17: =VLOOKUP(C17,'Portfolio Listing'!$C$7:$AF$28,12,FALSE) -> 0 | S17: =VLOOKUP(C17,'Portfolio Listing'!$C$7:$AF$28,14,FALSE) -> 38945352 | T17: =SUM(U17:AX17) -> 50000000 | U17: =U53+U77 -> 0 | V17: =V53+V77 -> 0 | W17: =W53+W77 -> 0 | X17: =X53+X77 -> 0 | Y17: =Y53+Y77 -> 0 | Z17: =Z53+Z77 -> 0 | AA17: =AA53+AA77 -> 0 | AB17: =AB53+AB77 -> 0 | ... AX17: =AX53+AX77 -> 0 | AZ17: =+INDEX('Portfolio Listing'!$AO$7:$AO$28,MATCH('Portfolio Summary'!$C17,'Portfolio Listing'!$C$7:$C$28,0)) -> West Street Capital Partners VIII
B18: =B17+1 -> 13 | C18: DCP Capital Partners II | D18: =IRR(U18:AX18) -> 0.16096521 | E18: =T78/-T54 -> 1.8 | F18: =+INDEX('Portfolio Listing'!$U$7:$U$28,MATCH(C18,'Portfolio Listing'!$C$7:$C$28,0)) -> -0.18608239 | G18: ='Portfolio Listing'!T19 -> 0.73926269 | H18: =VLOOKUP($C18,'Portfolio Listing'!$C$7:$AF$28,2,FALSE) -> China | I18: =VLOOKUP($C18,'Portfolio Listing'!$C$7:$AF$28,3,FALSE) -> Diversified | J18: =VLOOKUP($C18,'Portfolio Listing'!$C$7:$AF$28,4,FALSE) -> PE - Buyout | K18: Private | L18: ='Portfolio Listing'!H19 -> 44166 | M18: =VLOOKUP(C18,'Portfolio Listing'!$C$7:$AF$28,7,FALSE) -> 100000000 | N18: =VLOOKUP(C18,'Portfolio Listing'!$C$7:$AF$28,8,FALSE) -> 37438527 | O18: =IF(N18-M18>0,0,N18-M18) -> -62561473 | Q18: =VLOOKUP(C18,'Portfolio Listing'!$C$7:$AF$28,11,FALSE) -> 2676323.4 | R18: =VLOOKUP(C18,'Portfolio Listing'!$C$7:$AF$28,12,FALSE) -> 0 | S18: =VLOOKUP(C18,'Portfolio Listing'!$C$7:$AF$28,14,FALSE) -> 25000583 | T18: =SUM(U18:AX18) -> 80000000 | U18: =U54+U78 -> 0 | V18: =V54+V78 -> 0 | W18: =W54+W78 -> 0 | X18: =X54+X78 -> 0 | Y18: =Y54+Y78 -> 0 | Z18: =Z54+Z78 -> 0 | AA18: =AA54+AA78 -> 0 | AB18: =AB54+AB78 -> 0 | ... AX18: =AX54+AX78 -> 0 | AZ18: =+INDEX('Portfolio Listing'!$AO$7:$AO$28,MATCH('Portfolio Summary'!$C18,'Portfolio Listing'!$C$7:$C$28,0)) -> DCP Capital Partners II, L.P.
B19: =B18+1 -> 14 | C19: Skycus USD Fund II (AKA “Lionet Fund LP”) | D19: =IRR(U19:AX19) -> 0.060594109 | E19: =T79/-T55 -> 1.4305235 | F19: =+INDEX('Portfolio Listing'!$U$7:$U$28,MATCH(C19,'Portfolio Listing'!$C$7:$C$28,0)) -> -0.046108851 | G19: ='Portfolio Listing'!T20 -> 0.84289086 | H19: =VLOOKUP($C19,'Portfolio Listing'!$C$7:$AF$28,2,FALSE) -> China | I19: =VLOOKUP($C19,'Portfolio Listing'!$C$7:$AF$28,3,FALSE) -> Diversified | J19: =VLOOKUP($C19,'Portfolio Listing'!$C$7:$AF$28,4,FALSE) -> PE - VC / Growth | K19: Private | L19: ='Portfolio Listing'!H20 -> 44166 | M19: =VLOOKUP(C19,'Portfolio Listing'!$C$7:$AF$28,7,FALSE) -> 15000000 | N19: =VLOOKUP(C19,'Portfolio Listing'!$C$7:$AF$28,8,FALSE) -> 15728508 | O19: =IF(N19-M19>0,0,N19-M19) -> 0 | Q19: =VLOOKUP(C19,'Portfolio Listing'!$C$7:$AF$28,11,FALSE) -> 2197607.1 | R19: =VLOOKUP(C19,'Portfolio Listing'!$C$7:$AF$28,12,FALSE) -> 0 | S19: =VLOOKUP(C19,'Portfolio Listing'!$C$7:$AF$28,14,FALSE) -> 11059809 | T19: =SUM(U19:AX19) -> 6771491.7 | U19: =U55+U79 -> 0 | V19: =V55+V79 -> 0 | W19: =W55+W79 -> 0 | X19: =X55+X79 -> 0 | Y19: =Y55+Y79 -> 0 | Z19: =Z55+Z79 -> 0 | AA19: =AA55+AA79 -> 0 | AB19: =AB55+AB79 -> 0 | ... AX19: =AX55+AX79 -> 0 | AZ19: =+INDEX('Portfolio Listing'!$AO$7:$AO$28,MATCH('Portfolio Summary'!$C19,'Portfolio Listing'!$C$7:$C$28,0)) -> Skycus USD Fund II ("Lionet Fund")
B20: =B19+1 -> 15 | C20: BOYU Real Estate Fund I | D20: =IRR(U20:AX20) -> 0.22333994 | E20: =T80/-T56 -> 2.3 | F20: =+INDEX('Portfolio Listing'!$U$7:$U$28,MATCH(C20,'Portfolio Listing'!$C$7:$C$28,0)) -> -0.095536217 | G20: ='Portfolio Listing'!T21 -> 0.84370343 | H20: =VLOOKUP($C20,'Portfolio Listing'!$C$7:$AF$28,2,FALSE) -> China | I20: =VLOOKUP($C20,'Portfolio Listing'!$C$7:$AF$28,3,FALSE) -> Logistic/ Data Center | J20: =VLOOKUP($C20,'Portfolio Listing'!$C$7:$AF$28,4,FALSE) -> PE - Real Estate | K20: Property | L20: ='Portfolio Listing'!H21 -> 44197 | M20: =VLOOKUP(C20,'Portfolio Listing'!$C$7:$AF$28,7,FALSE) -> 30000000 | N20: =VLOOKUP(C20,'Portfolio Listing'!$C$7:$AF$28,8,FALSE) -> 19364197 | O20: =IF(N20-M20>0,0,N20-M20) -> -10635803 | Q20: =VLOOKUP(C20,'Portfolio Listing'!$C$7:$AF$28,11,FALSE) -> 995489.23 | R20: =VLOOKUP(C20,'Portfolio Listing'!$C$7:$AF$28,12,FALSE) -> 0 | S20: =VLOOKUP(C20,'Portfolio Listing'!$C$7:$AF$28,14,FALSE) -> 15342150 | T20: =SUM(U20:AX20) -> 39000000 | U20: =U56+U80 -> 0 | V20: =V56+V80 -> 0 | W20: =W56+W80 -> 0 | X20: =X56+X80 -> 0 | Y20: =Y56+Y80 -> 0 | Z20: =Z56+Z80 -> 0 | AA20: =AA56+AA80 -> 0 | AB20: =AB56+AB80 -> 0 | ... AX20: =AX56+AX80 -> 0 | AZ20: =+INDEX('Portfolio Listing'!$AO$7:$AO$28,MATCH('Portfolio Summary'!$C20,'Portfolio Listing'!$C$7:$C$28,0)) -> Boyu Real Estate Fund I, LP
... B22: =B21+1 -> 17 | C22: Cottonwood | D22: =IRR(U22:AX22) -> 0.28061346 | E22: =T82/-T58 -> 2.51 | F22: =+INDEX('Portfolio Listing'!$U$7:$U$28,MATCH(C22,'Portfolio Listing'!$C$7:$C$28,0)) -> 0.44407232 | G22: ='Portfolio Listing'!T23 -> 1.1995842 | H22: =VLOOKUP($C22,'Portfolio Listing'!$C$7:$AF$28,2,FALSE) -> US | I22: =VLOOKUP($C22,'Portfolio Listing'!$C$7:$AF$28,3,FALSE) -> Real Estate | J22: =VLOOKUP($C22,'Portfolio Listing'!$C$7:$AF$28,4,FALSE) -> PE - Special Situations | K22: Private | L22: ='Portfolio Listing'!H23 -> 45393 | M22: =VLOOKUP(C22,'Portfolio Listing'!$C$7:$AF$28,7,FALSE) -> 12500000 | N22: =VLOOKUP(C22,'Portfolio Listing'!$C$7:$AF$28,8,FALSE) -> 3150647.5 | O22: =IF(N22-M22>0,0,N22-M22) -> -9349352.5 | Q22: =VLOOKUP(C22,'Portfolio Listing'!$C$7:$AF$28,11,FALSE) -> 0 | R22: =VLOOKUP(C22,'Portfolio Listing'!$C$7:$AF$28,12,FALSE) -> 0 | S22: =VLOOKUP(C22,'Portfolio Listing'!$C$7:$AF$28,14,FALSE) -> 3779467 | T22: =SUM(U22:AX22) -> 18875000 | U22: =U58+U82 -> 0 | V22: =V58+V82 -> 0 | W22: =W58+W82 -> 0 | X22: =X58+X82 -> 0 | Y22: =Y58+Y82 -> 0 | Z22: =Z58+Z82 -> 0 | AA22: =AA58+AA82 -> 0 | AB22: =AB58+AB82 -> 0 | ... AX22: =AX58+AX82 -> 0 | AZ22: =+INDEX('Portfolio Listing'!$AO$7:$AO$28,MATCH('Portfolio Summary'!$C22,'Portfolio Listing'!$C$7:$C$28,0)) -> Cottonwood-WTT Real Estate Special Situations Fund, LP
B23: =B22+1 -> 18 | C23: Genedant Ventures I | D23: =IRR(U23:AX23) -> 0.18861382 | E23: =T83/-T59 -> 3.5 | F23: =+INDEX('Portfolio Listing'!$U$7:$U$28,MATCH(C23,'Portfolio Listing'!$C$7:$C$28,0)) -> -0.67657796 | G23: ='Portfolio Listing'!T24 -> 0.73992472 | H23: =VLOOKUP($C23,'Portfolio Listing'!$C$7:$AF$28,2,FALSE) -> Global | I23: =VLOOKUP($C23,'Portfolio Listing'!$C$7:$AF$28,3,FALSE) -> Diversified | J23: =VLOOKUP($C23,'Portfolio Listing'!$C$7:$AF$28,4,FALSE) -> PE - VC / Growth | K23: VC | L23: 45518 | M23: =VLOOKUP(C23,'Portfolio Listing'!$C$7:$AF$28,7,FALSE) -> 37600000 | N23: =VLOOKUP(C23,'Portfolio Listing'!$C$7:$AF$28,8,FALSE) -> 2954733 | O23: =IF(N23-M23>0,0,N23-M23) -> -34645267 | Q23: =VLOOKUP(C23,'Portfolio Listing'!$C$7:$AF$28,11,FALSE) -> 0 | R23: =VLOOKUP(C23,'Portfolio Listing'!$C$7:$AF$28,12,FALSE) -> 0 | S23: =VLOOKUP(C23,'Portfolio Listing'!$C$7:$AF$28,14,FALSE) -> 2186280 | T23: =SUM(U23:AX23) -> 7386832.5 | U23: =U59+U83 -> 0 | V23: =V59+V83 -> 0 | W23: =W59+W83 -> 0 | X23: =X59+X83 -> 0 | Y23: =Y59+Y83 -> 0 | Z23: =Z59+Z83 -> 0 | AA23: =AA59+AA83 -> 0 | AB23: =AB59+AB83 -> 0 | ... AX23: =AX59+AX83 -> 0 | AZ23: =+INDEX('Portfolio Listing'!$AO$7:$AO$28,MATCH('Portfolio Summary'!$C23,'Portfolio Listing'!$C$7:$C$28,0)) -> Genedant Ventures I
B24: =B23+1 -> 19 | C24: GTCR XIV Access Offshore LP | D24: =IRR(U24:AX24) -> 0.22347825 | E24: =T84/-T60 -> 2.5 | F24: =+INDEX('Portfolio Listing'!$U$7:$U$28,MATCH(C24,'Portfolio Listing'!$C$7:$C$28,0)) -> 1.5680467 | G24: ='Portfolio Listing'!T25 -> 1.1920915 | H24: =VLOOKUP($C24,'Portfolio Listing'!$C$7:$AF$28,2,FALSE) -> US | I24: =VLOOKUP($C24,'Portfolio Listing'!$C$7:$AF$28,3,FALSE) -> Diversified | J24: =VLOOKUP($C24,'Portfolio Listing'!$C$7:$AF$28,4,FALSE) -> PE - Buyout | K24: VC | L24: 45261 | M24: =VLOOKUP(C24,'Portfolio Listing'!$C$7:$AF$28,7,FALSE) -> 16940000 | N24: =VLOOKUP(C24,'Portfolio Listing'!$C$7:$AF$28,8,FALSE) -> 1756064.1 | O24: =IF(N24-M24>0,0,N24-M24) -> -15183936 | Q24: =VLOOKUP(C24,'Portfolio Listing'!$C$7:$AF$28,11,FALSE) -> 0 | R24: =VLOOKUP(C24,'Portfolio Listing'!$C$7:$AF$28,12,FALSE) -> 0 | S24: =VLOOKUP(C24,'Portfolio Listing'!$C$7:$AF$28,14,FALSE) -> 2093389 | T24: =SUM(U24:AX24) -> 25410000 | U24: =U60+U84 -> 0 | V24: =V60+V84 -> 0 | W24: =W60+W84 -> 0 | X24: =X60+X84 -> 0 | Y24: =Y60+Y84 -> 0 | Z24: =Z60+Z84 -> 0 | AA24: =AA60+AA84 -> 0 | AB24: =AB60+AB84 -> 0 | ... AX24: =AX60+AX84 -> 0 | AZ24: =+INDEX('Portfolio Listing'!$AO$7:$AO$28,MATCH('Portfolio Summary'!$C24,'Portfolio Listing'!$C$7:$C$28,0)) -> GTCR XIV Access Offshore LP
D26: =IRR(U26:AR26) -> 0.19990547 | E26: =(Q26+R26+S26)/(M26+O26) -> 1.4469843 | M26: =SUM(M6:M25) -> 479290000 | N26: =SUM(N6:N25) -> 3.2951437e+08 | O26: =SUM(O6:O25) -> -1.6022981e+08 | Q26: =SUM(Q6:Q25) -> 2.2500713e+08 | R26: =SUM(R6:R25) -> 0 | S26: =SUM(S6:S25) -> 2.3666798e+08 | T26: =SUM(T6:T25) -> 4.3864604e+08 | U26: =SUM(U6:U25) -> -2738663.8 | V26: =SUM(V6:V25) -> -14361451 | W26: =SUM(W6:W25) -> -3014034.2 | X26: =SUM(X6:X25) -> -4327936.3 | ... AX26: =SUM(AX6:AX25) -> 0
U27: =+SUM($U$26:U26) -> -2738663.8 | V27: =+SUM($U$26:V26) -> -17100115 | W27: =+SUM($U$26:W26) -> -20114149 | X27: =+SUM($U$26:X26) -> -24442085 | Y27: =+SUM($U$26:Y26) -> -8788338 | Z27: =+SUM($U$26:Z26) -> -3362120.2 | AA27: =+SUM($U$26:AA26) -> 16730983 | AB27: =+SUM($U$26:AB26) -> 4857364 | ... AR27: =+SUM($U$26:AR26) -> 4.3864604e+08
B29: NOTES:
C30: 1. IRR is calculated based on forecast / expected future cashflow of the project / fund throughout the lifecycle
C31: 2. MoIC is calculated based on existing capital funding, distribution / sales proceeds and MTM Value
C32: 3. MTM Value is based on the the latest fund / project NAV report which may or may not reflect the potential capital upside of each fund / project
C33: 4. Some PE Projects will be managed by managed by Genedant after granting of RFM licence
C34: 5. Exited funds / projects are shaded in grey
C35: 6. O/S commitment to be funded in 5 to 10 years. Actual contribution may be less based on previous experience due to accelerated fund distribution and fund leverage
C36: *. Taikang Insurance is excluded from calculation of total as it has been syndicated out. The above shown is carried interest accrued.
B38: Kingsway Investment Ltd | M38: Capital Investment | Q38: Realized Value | S38: Unrealized Value | U38: 2011 | V38: =U38+1 -> 2012 | W38: =V38+1 -> 2013 | X38: =W38+1 -> 2014 | Y38: =X38+1 -> 2015 | Z38: =Y38+1 -> 2016 | AA38: =Z38+1 -> 2017 | AB38: =AA38+1 -> 2018 | AC38: =AB38+1 -> 2019 | ... AX38: =AW38+1 -> 2040
B39: No. | C39: PE Funds | K39: Nature | L39: Investment Date | M39: Committed | N39: Funded | O39: Unfunded (O/S) | Q39: Distribution | R39: Syndicated to Genedant | S39: MTM Value | T39: Total | U39: 0 | V39: =U39+1 -> 1 | W39: =V39+1 -> 2 | X39: =W39+1 -> 3 | Y39: =X39+1 -> 4 | Z39: =Y39+1 -> 5 | AA39: =Z39+1 -> 6 | AB39: =AA39+1 -> 7 | AC39: =AB39+1 -> 8 | ... AX39: =AW39+1 -> 29
B40: Cash Outflow
B41: 1 | C41: BOYU Capital Fund I | M41: =M6 -> 30000000 | T41: =SUM(U41:AX41) -> -29742026 | U41: ='BOYU Capital Fund I CF'!L10 -> -3026238.1 | V41: ='BOYU Capital Fund I CF'!L12+'BOYU Capital Fund I CF'!L14+'BOYU Capital Fund I CF'!L15+'BOYU Capital Fund I CF'!L16+'BOYU Capital Fund I CF'!L18 -> -13434435 | W41: ='BOYU Capital Fund I CF'!L20+'BOYU Capital Fund I CF'!L21+'BOYU Capital Fund I CF'!L23 -> -2311707 | X41: ='BOYU Capital Fund I CF'!L26+'BOYU Capital Fund I CF'!L27+'BOYU Capital Fund I CF'!L29+'BOYU Capital Fund I CF'!L30+'BOYU Capital Fund I CF'!L31+'BOYU Capital Fund I CF'!L34 -> -6199025.8 | Y41: ='BOYU Capital Fund I CF'!L36+'BOYU Capital Fund I CF'!L37+'BOYU Capital Fund I CF'!L40+'BOYU Capital Fund I CF'!L43+'BOYU Capital Fund I CF'!L46 -> -3309202 | Z41: ='BOYU Capital Fund I CF'!L49+'BOYU Capital Fund I CF'!L51+'BOYU Capital Fund I CF'!L52 -> -488498.82 | AA41: ='BOYU Capital Fund I CF'!L56+'BOYU Capital Fund I CF'!L60+'BOYU Capital Fund I CF'!L65 -> -273132.09 | AB41: ='BOYU Capital Fund I CF'!L66+'BOYU Capital Fund I CF'!L70 -> -182878.86 | AC41: ='BOYU Capital Fund I CF'!L72+'BOYU Capital Fund I CF'!L74+'BOYU Capital Fund I CF'!L77 -> -157424.58 | AD41: ='BOYU Capital Fund I CF'!L82+'BOYU Capital Fund I CF'!L85 -> -120277.23 | AE41: ='BOYU Capital Fund I CF'!L87+'BOYU Capital Fund I CF'!L90 -> -72816.23 | AF41: ='BOYU Capital Fund I CF'!L92+'BOYU Capital Fund I CF'!L94 -> -57293.78 | AG41: ='BOYU Capital Fund I CF'!L95+'BOYU Capital Fund I CF'!L96 -> -109097.3 | AH41: 0 | AI41: 0 | AJ41: 0 | AK41: 0 | AL41: 0 | AM41: 0 | AN41: 0 | AY41: Updated based on capital call estimate in 2025 from Boyu, expect no more further capital call.
B42: =B41+1 -> 2 | C42: Ascendent Fund | M42: =M7 -> 10000000 | T42: =SUM(U42:AX42) -> -9155663.4 | U42: 0 | V42: ='Ascendant CP I CF'!L11+'Ascendant CP I CF'!L12+'Ascendant CP I CF'!L13+'Ascendant CP I CF'!L15 -> -2938196.1 | W42: ='Ascendant CP I CF'!L17+'Ascendant CP I CF'!L18+'Ascendant CP I CF'!L19+'Ascendant CP I CF'!L20+'Ascendant CP I CF'!L21 -> -2121566.2 | X42: ='Ascendant CP I CF'!L22+'Ascendant CP I CF'!L24+'Ascendant CP I CF'!L25+'Ascendant CP I CF'!L26+'Ascendant CP I CF'!L31 -> -2214175.8 | Y42: ='Ascendant CP I CF'!L34+'Ascendant CP I CF'!L37 -> -1275365.5 | Z42: ='Ascendant CP I CF'!L38+'Ascendant CP I CF'!L40 -> -225358.24 | AA42: ='Ascendant CP I CF'!L42 -> -126777 | AB42: ='Ascendant CP I CF'!L45+'Ascendant CP I CF'!L46+'Ascendant CP I CF'!L47+'Ascendant CP I CF'!L49 -> -109918.94 | AC42: ='Ascendant CP I CF'!L51+'Ascendant CP I CF'!L52 -> -53912.04 | AD42: ='Ascendant CP I CF'!L53+'Ascendant CP I CF'!L54 -> -58314.38 | AE42: ='Ascendant CP I CF'!L56+'Ascendant CP I CF'!L58 -> -26929.11 | AF42: ='Ascendant CP I CF'!L61 -> -4396.94 | AG42: ='Ascendant CP I CF'!L63 -> -753.07 | AH42: 0 | AI42: 0 | AJ42: 0 | AK42: 0 | AL42: 0 | AM42: 0 | AN42: 0 | AY42: Commitment amount has been fully called
B43: =B42+1 -> 3 | C43: BOYU Capital Offshore Fund | M43: =M8 -> 10000000 | T43: =SUM(U43:AX43) -> -10000000 | U43: 0 | V43: 0 | W43: 0 | X43: 0 | Y43: 0 | Z43: -10000000 | AA43: 0 | AB43: 0 | AC43: 0 | AD43: 0 | AE43: 0 | AF43: 0 | AG43: 0 | AH43: 0 | AI43: 0 | AJ43: 0 | AK43: 0 | AL43: 0 | AM43: 0 | AN43: 0 | AY43: Commitment amount has been fully called
B44: =B43+1 -> 4 | C44: Ark Pacific Special Oppor Fund I | T44: =SUM(U44:AX44) -> -3413271.4 | U44: 0 | V44: 0 | W44: 0 | X44: 0 | Y44: -1973271.4 | Z44: 0 | AA44: -1440000 | AB44: 0 | AC44: 0 | AD44: 0 | AE44: 0 | AF44: 0 | AG44: 0 | AH44: 0 | AI44: 0 | AJ44: 0 | AK44: 0 | AL44: 0 | AM44: 0 | AN44: 0 | AY44: Commitment amount has been fully called
B45: =B44+1 -> 5 | C45: E15 Fund I | M45: =M9 -> 6000000 | T45: =SUM(U45:AX45) -> -6000000 | U45: 0 | V45: 0 | W45: 0 | X45: 0 | Y45: 0 | Z45: 0 | AA45: ='E15 Fund I (CF) '!J10+'E15 Fund I (CF) '!J11 -> -6000000 | AB45: 0 | AC45: 0 | AD45: 0 | AE45: 0 | AF45: 0 | AG45: 0 | AH45: 0 | AI45: 0 | AJ45: 0 | AK45: 0 | AL45: 0 | AM45: 0 | AN45: 0 | AY45: Commitment amount has been fully called
B46: =B45+1 -> 6 | C46: West Street Capital Partners VII | M46: =M10 -> 25000000 | T46: =SUM(U46:AX46) -> -25000000 | U46: 0 | V46: 0 | W46: 0 | X46: 0 | Y46: 0 | Z46: 0 | AA46: 0 | AB46: 0 | AC46: 0 | AD46: ='West Street VII (CF)'!L11 -> -17882500 | AE46: ='West Street VII (CF)'!L12+'West Street VII (CF)'!L13+'West Street VII (CF)'!L15 -> -2050000 | AF46: ='West Street VII (CF)'!L20 -> -250000 | AG46: ='West Street VII (CF)'!L27 -> -163548 | AH46: ='West Street VII (CF)'!L29 -> -650000 | AI46: =[4]Cashflow!$P$38 -> 0 | AJ46: =(M10+SUM(AD46:AI46))*-1 -> -4003952 | AK46: 0 | AL46: 0 | AM46: 0 | AN46: 0 | AY46: 2025 is based on West Street estimate. Remainder is expected to be called in 2026.
B47: =B46+1 -> 7 | C47: C Capital Fund II | M47: =M11 -> 20000000 | T47: =SUM(U47:AX47) -> -20933286 | U47: 0 | V47: 0 | W47: 0 | X47: 0 | Y47: 0 | Z47: 0 | AA47: 0 | AB47: ='C Ventures II CF '!K11 -> -2000000 | AC47: ='C Ventures II CF '!K12+'C Ventures II CF '!K13+'C Ventures II CF '!K14 -> -5850861.1 | AD47: ='C Ventures II CF '!K15+'C Ventures II CF '!K16+'C Ventures II CF '!K17 -> -3629119.4 | AE47: ='C Ventures II CF '!K19+'C Ventures II CF '!K20+'C Ventures II CF '!K21+'C Ventures II CF '!K22+'C Ventures II CF '!K23+'C Ventures II CF '!K24+'C Ventures II CF '!K28+'C Ventures II CF '!K29 -> -7942857.1 | AF47: ='C Ventures II CF '!K30+'C Ventures II CF '!K31 -> -561208.62 | AG47: ='C Ventures II CF '!K35+'C Ventures II CF '!K37 -> -297854.99 | AH47: ='C Ventures II CF '!K39+'C Ventures II CF '!K40 -> -580784.89 | AI47: =[4]Cashflow!$P$34 -> -70600 | AJ47: 0 | AK47: 0 | AL47: 0 | AM47: 0 | AN47: 0 | AY47: 2025 is based on C Capital estimate. Commitment amount has been fully called.
B48: =B47+1 -> 8 | C48: DCP Capital Partners | M48: =M12 -> 50000000 | T48: =SUM(U48:AX48) -> -63725670 | U48: 0 | V48: 0 | W48: 0 | X48: 0 | Y48: 0 | Z48: 0 | AA48: 0 | AB48: 0 | AC48: ='DCP I (CF)'!L28+'DCP I (CF)'!L29+'DCP I (CF)'!L31 -> -11384334 | AD48: ='DCP I (CF)'!L32 -> -4860719.2 | AE48: ='DCP I (CF)'!L37+'DCP I (CF)'!L39+'DCP I (CF)'!L40+'DCP I (CF)'!L41+'DCP I (CF)'!L43+'DCP I (CF)'!L34 -> -22147615 | AF48: ='DCP I (CF)'!L46+'DCP I (CF)'!L49+'DCP I (CF)'!L52 -> -7096172 | AG48: ='DCP I (CF)'!L55+'DCP I (CF)'!L58+'DCP I (CF)'!L61+'DCP I (CF)'!L64+'DCP I (CF)'!L67 -> -11184831 | AH48: =SUM('DCP I (CF)'!L70,'DCP I (CF)'!L74,'DCP I (CF)'!L78,'DCP I (CF)'!L80,'DCP I (CF)'!L82,'DCP I (CF)'!L83,'DCP I (CF)'!L88) -> -3051999.8 | AI48: =[4]Cashflow!$P$31 -> -4000000 | AM48: 0 | AN48: 0 | AY48: 2025 is based on DCP estimate. Commitment has been fully called.
B49: =B48+1 -> 9 | C49: E15 Fund 1.5 | M49: =M13 -> 6000000 | T49: =SUM(U49:AX49) -> -4500000 | U49: 0 | V49: 0 | W49: 0 | X49: 0 | Y49: 0 | Z49: 0 | AA49: 0 | AB49: 0 | AC49: -4500000 | AD49: 0 | AE49: 0 | AF49: 0 | AG49: 0 | AH49: 0 | AI49: 0 | AJ49: 0 | AK49: 0 | AL49: 0 | AM49: 0 | AN49: 0 | AY49: Commitment amount has been fully called
B50: =B49+1 -> 10 | C50: Skycus China Fund | M50: =M14 -> 30000000 | T50: =SUM(U50:AX50) -> -30000000 | U50: 0 | V50: 0 | W50: 0 | X50: 0 | Y50: 0 | Z50: 0 | AA50: 0 | AB50: ='Skycus China CF'!L11+'Skycus China CF'!L12 -> -18000000 | AC50: 0 | AD50: ='Skycus China CF'!L13+'Skycus China CF'!L14+'Skycus China CF'!L15 -> -12000000 | AE50: 0 | AF50: 0 | AG50: 0 | AH50: 0 | AI50: 0 | AJ50: 0 | AK50: 0 | AL50: 0 | AM50: 0 | AN50: 0 | AY50: Commitment amount has been fully called
B51: =B50+1 -> 11 | C51: Hongshan Capital Venture Partners Fund VIII (AKA "Sequoia Capital China Venture Partners VIII") | M51: =M15 -> 4500000 | T51: =SUM(U51:AX51) -> -4500000 | U51: 0 | V51: 0 | W51: 0 | X51: 0 | Y51: 0 | Z51: 0 | AA51: 0 | AB51: 0 | AC51: 0 | AD51: ='HSG Growth VIII (CF)'!K10+'HSG Growth VIII (CF)'!K11 -> -900000 | AE51: ='HSG Growth VIII (CF)'!K12+'HSG Growth VIII (CF)'!K13+'HSG Growth VIII (CF)'!K14+'HSG Growth VIII (CF)'!K15 -> -2925000 | AF51: ='HSG Growth VIII (CF)'!K16+'HSG Growth VIII (CF)'!K17 -> -450000 | AG51: ='HSG Growth VIII (CF)'!K18 -> -225000 | AI51: 0 | AJ51: 0 | AK51: 0 | AL51: 0 | AM51: 0 | AN51: 0 | AY51: Commitment amount has been fully called
B52: =B51+1 -> 12 | C52: HongShan Capital Growth Partners Fund VI (AKA "Sequoia Capital China Growth Partners VI") | M52: =M16 -> 15750000 | T52: =SUM(U52:AX52) -> -15793291 | U52: 0 | V52: 0 | W52: 0 | X52: 0 | Y52: 0 | Z52: 0 | AA52: 0 | AB52: 0 | AC52: 0 | AD52: ='HSG Growth VI (CF) '!K10 -> -3150000 | AE52: ='HSG Growth VI (CF) '!K11+'HSG Growth VI (CF) '!K12+'HSG Growth VI (CF) '!K13+'HSG Growth VI (CF) '!K14+'HSG Growth VI (CF) '!K16 -> -9036409 | AF52: ='HSG Growth VI (CF) '!K17+'HSG Growth VI (CF) '!K18+'HSG Growth VI (CF) '!K19 -> -2032516.4 | AG52: ='HSG Growth VI (CF) '!K20 -> -1574366 | AH52: 0 | AI52: 0 | AJ52: 0 | AK52: 0 | AL52: 0 | AM52: 0 | AN52: 0 | AY52: Commitment amount has been fully called
B53: =B52+1 -> 13 | C53: West Street Capital Partners VIII | M53: =M17 -> 50000000 | T53: =SUM(U53:AX53) -> -50000000 | U53: 0 | V53: 0 | W53: 0 | X53: 0 | Y53: 0 | Z53: 0 | AA53: 0 | AB53: 0 | AC53: 0 | AD53: ='West Street VIII (CF)'!L11 -> -1500000 | AE53: ='West Street VIII (CF)'!L12+'West Street VIII (CF)'!L13+'West Street VIII (CF)'!L14+'West Street VIII (CF)'!L15+'West Street VIII (CF)'!L16 -> -10375000 | AF53: ='West Street VIII (CF)'!L17+'West Street VIII (CF)'!L18 -> -7325000 | AG53: ='West Street VIII (CF)'!L20+'West Street VIII (CF)'!L21+'West Street VIII (CF)'!L22+'West Street VIII (CF)'!L23 -> -8950000 | AH53: =SUM('West Street VIII (CF)'!L24:L26) -> -4950000 | AI53: =[4]Cashflow!$P$36 -> -2758657 | AJ53: =(-M17-SUM(AD53:AI53))/2 -> -7070671.5 | AK53: =AJ53 -> -7070671.5 | AL53: 0 | AM53: 0 | AN53: 0 | AY53: 2025 based on West Street guidance, with the remainder being evenly called over 2026-2027.
B54: =B53+1 -> 14 | C54: DCP Capital Partners II | M54: =M18 -> 100000000 | T54: =SUM(U54:AX54) -> -100000000 | U54: 0 | V54: 0 | W54: 0 | X54: 0 | Y54: 0 | Z54: 0 | AA54: 0 | AB54: 0 | AC54: 0 | AD54: 0 | AE54: 0 | AF54: ='DCP II (CF) '!L10 -> -10041861 | AG54: ='DCP II (CF) '!L13+'DCP II (CF) '!L15 -> -13859135 | AH54: =SUM('DCP II (CF) '!L16,'DCP II (CF) '!L18,'DCP II (CF) '!L20,'DCP II (CF) '!L21) -> -14030035 | AI54: =[4]Cashflow!$P$32 -> -30431536 | AJ54: =(-M18-SUM(AF54:AI54))/2 -> -15818716 | AK54: =AJ54 -> -15818716 | AY54: 2025 based on DCP estimate, with the remainder being evenly called over 2026-2027. DCP team guided ~20% of portfolio to be deployed p.a. until 2027.
B55: =B54+1 -> 15 | C55: Skycus USD Fund II (AKA “Lionet Fund LP”) | M55: =M19 -> 15000000 | T55: =SUM(U55:AX55) -> -15728508 | U55: 0 | V55: 0 | W55: 0 | X55: 0 | Y55: 0 | Z55: 0 | AA55: 0 | AB55: 0 | AC55: 0 | AD55: 0 | AE55: ='Lionet Fund CF'!L11+'Lionet Fund CF'!L12+'Lionet Fund CF'!L14+'Lionet Fund CF'!L15+'Lionet Fund CF'!L17+'Lionet Fund CF'!L19 -> -15607971 | AF55: 0 | AG55: ='Lionet Fund CF'!L21 -> -120537.13 | AH55: 0 | AI55: 0 | AJ55: 0 | AK55: 0 | AL55: 0 | AM55: 0 | AN55: 0 | AY55: Commitment amount has been fully called
B56: =B55+1 -> 16 | C56: BOYU Real Estate Fund I | M56: =M20 -> 30000000 | T56: =SUM(U56:AX56) -> -30000000 | U56: 0 | V56: 0 | W56: 0 | X56: 0 | Y56: 0 | Z56: 0 | AA56: 0 | AB56: 0 | AC56: 0 | AD56: 0 | AE56: ='Boyu Real Estate CF'!K10+'Boyu Real Estate CF'!K11+'Boyu Real Estate CF'!K12+'Boyu Real Estate CF'!K14+'Boyu Real Estate CF'!K15+'Boyu Real Estate CF'!K16+'Boyu Real Estate CF'!K21 -> -5603950.3 | AF56: ='Boyu Real Estate CF'!K23+'Boyu Real Estate CF'!K25+'Boyu Real Estate CF'!K27+'Boyu Real Estate CF'!K28+'Boyu Real Estate CF'!K29 -> -2675447 | AG56: ='Boyu Real Estate CF'!K30+'Boyu Real Estate CF'!K31+'Boyu Real Estate CF'!K33 -> -8387542.1 | AH56: =SUM('Boyu Real Estate CF'!K35:K38) -> -4559102.5 | AI56: =[4]Cashflow!$P$30 -> -2458295.5 | AJ56: =(M20+SUM(AE56:AI56))*-1 -> -6315662.6 | AY56: 2025 based on BOYU estimate. The remainder called in 2026.
B57: =B56+1 -> 17 | C57: E15 Fund II | M57: =M21 -> 10000000 | T57: =SUM(U57:AX57) -> -6830758.3 | U57: 0 | V57: 0 | W57: 0 | X57: 0 | Y57: 0 | Z57: 0 | AA57: 0 | AB57: 0 | AC57: 0 | AD57: 0 | AE57: ='E15 Fund II CF'!J10+'E15 Fund II CF'!J11+'E15 Fund II CF'!J12+'E15 Fund II CF'!J13 -> -4772276.5 | AF57: ='E15 Fund II CF'!J15+'E15 Fund II CF'!J16+'E15 Fund II CF'!J17+'E15 Fund II CF'!J18 -> -1108049 | AG57: ='E15 Fund II CF'!J20+'E15 Fund II CF'!J21+'E15 Fund II CF'!J22+'E15 Fund II CF'!J23 -> -589323.81 | AH57: =SUM('E15 Fund II CF'!J24:J26) -> -126227 | AI57: =[4]Cashflow!$P$37 -> -234882 | AJ57: 0 | AK57: 0 | AL57: 0 | AM57: 0 | AN57: 0 | AY57: 2025 based on E15 estimate. Assume no more capital call thereafter.
B58: =B57+1 -> 18 | C58: Cottonwood | M58: =M22 -> 12500000 | T58: =SUM(U58:AX58) -> -12500000 | U58: 0 | V58: 0 | W58: 0 | X58: 0 | Y58: 0 | Z58: 0 | AA58: 0 | AB58: 0 | AC58: 0 | AD58: 0 | AE58: 0 | AF58: 0 | AG58: 0 | AH58: ='Cottonwood (CF)'!N2 -> -3150647.5 | AI58: =[4]Cashflow!$P$33 -> -6340843.1 | AJ58: =(-M22-AH58-AI58)/2 -> -1504254.7 | AK58: =AJ58 -> -1504254.7 | AY58: 2025 based on Cottonwood estimate. With the remaining evenly called over 2026-2027.
B59: =B58+1 -> 19 | C59: Genedant Ventures I | M59: =M23 -> 37600000 | T59: =SUM(U59:AX59) -> -2954733 | U59: 0 | V59: 0 | W59: 0 | X59: 0 | Y59: 0 | Z59: 0 | AA59: 0 | AB59: 0 | AC59: 0 | AD59: 0 | AE59: 0 | AF59: 0 | AG59: 0 | AH59: =SUM('Genedent Ventures (CF)'!L10:L11) -> -2954733 | AI59: 0 | AJ59: 0 | AK59: 0 | AL59: 0 | AY59: Based on discussion with GCPL team, only US$30m out of the total commitment size will be called. Capital call will be frontloaded.
B60: =B59+1 -> 20 | C60: GTCR XIV Access Offshore LP | M60: =M24 -> 16940000 | T60: =SUM(U60:AX60) -> -16940000 | U60: 0 | V60: 0 | W60: 0 | X60: 0 | Y60: 0 | Z60: 0 | AA60: 0 | AB60: 0 | AC60: 0 | AD60: 0 | AE60: 0 | AF60: 0 | AG60: 0 | AH60: ='GTCR (CF)'!L10 -> -1756064.1 | AI60: =[4]Cashflow!$P$35 -> -2217004.7 | AJ60: =(-M24-AH60-AI60)/3 -> -4322310.4 | AK60: =AJ60 -> -4322310.4 | AL60: =AK60 -> -4322310.4 | AM60: =-M24-SUM(AH60:AL60) -> 0 | AY60: 2025 based on GTCR estimate. Assume even capital call for remaining investment period until 2028.
T62: =SUM(T41:T61) -> -4.5771721e+08 | U62: =SUM(U41:U61) -> -3026238.1 | V62: =SUM(V41:V61) -> -16372631 | W62: =SUM(W41:W61) -> -4433273.2 | X62: =SUM(X41:X61) -> -8413201.7 | Y62: =SUM(Y41:Y61) -> -6557838.9 | Z62: =SUM(Z41:Z61) -> -10713857 | AA62: =SUM(AA41:AA61) -> -7839909.1 | ... AX62: =SUM(AX41:AX61) -> 0
B64: Cash Inflow
B65: 1 | C65: BOYU Capital Fund I | T65: =SUM(U65:AX65) -> 92326400 | U65: ='BOYU Capital Fund I CF'!L11 -> 287574.3 | V65: ='BOYU Capital Fund I CF'!L13+'BOYU Capital Fund I CF'!L17+'BOYU Capital Fund I CF'!L19 -> 1410267.4 | W65: ='BOYU Capital Fund I CF'!L22+'BOYU Capital Fund I CF'!L24+'BOYU Capital Fund I CF'!L25 -> 1419239 | X65: ='BOYU Capital Fund I CF'!L28+'BOYU Capital Fund I CF'!L32+'BOYU Capital Fund I CF'!L33 -> 1989253.7 | Y65: ='BOYU Capital Fund I CF'!L35+'BOYU Capital Fund I CF'!L38+'BOYU Capital Fund I CF'!L39+'BOYU Capital Fund I CF'!L41+'BOYU Capital Fund I CF'!L42+'BOYU Capital Fund I CF'!L44+'BOYU Capital Fund I CF'!L45+'BOYU Capital Fund I CF'!L47+'BOYU Capital Fund I CF'!L48 -> 19272477 | Z65: ='BOYU Capital Fund I CF'!L50+'BOYU Capital Fund I CF'!L53+'BOYU Capital Fund I CF'!L54+'BOYU Capital Fund I CF'!L55 -> 13050585 | AA65: ='BOYU Capital Fund I CF'!L57+'BOYU Capital Fund I CF'!L58+'BOYU Capital Fund I CF'!L59+'BOYU Capital Fund I CF'!L61+'BOYU Capital Fund I CF'!L62+'BOYU Capital Fund I CF'!L63+'BOYU Capital Fund I CF'!L64 -> 22887747 | AB65: ='BOYU Capital Fund I CF'!L67+'BOYU Capital Fund I CF'!L68+'BOYU Capital Fund I CF'!L69+'BOYU Capital Fund I CF'!L71 -> 6392112.9 | AC65: ='BOYU Capital Fund I CF'!L73+'BOYU Capital Fund I CF'!L75+'BOYU Capital Fund I CF'!L76+'BOYU Capital Fund I CF'!L78+'BOYU Capital Fund I CF'!L79+'BOYU Capital Fund I CF'!L80 -> 8357339.6 | AD65: ='BOYU Capital Fund I CF'!L81+'BOYU Capital Fund I CF'!L83+'BOYU Capital Fund I CF'!L84+'BOYU Capital Fund I CF'!L86 -> 9152374.9 | AE65: ='BOYU Capital Fund I CF'!L88+'BOYU Capital Fund I CF'!L89+'BOYU Capital Fund I CF'!L91 -> 2802734.5 | AF65: 717981.21 | AG65: 4586713.4 | AH65: 0 | AI65: 0 | AJ65: 0 | AK65: 0 | AL65: 0 | AM65: 0 | AN65: 0 | AY65: Fund term has expired. No distributions expected in 2025 per Boyu.
B66: =B65+1 -> 2 | C66: Ascendent Fund | T66: =SUM(U66:AX66) -> 21392852 | U66: 0 | V66: ='Ascendant CP I CF'!L14+'Ascendant CP I CF'!L16 -> 600912.42 | W66: 0 | X66: ='Ascendant CP I CF'!L23+'Ascendant CP I CF'!L27+'Ascendant CP I CF'!L28+'Ascendant CP I CF'!L29+'Ascendant CP I CF'!L30+'Ascendant CP I CF'!L32+'Ascendant CP I CF'!L33 -> 2096011.6 | Y66: ='Ascendant CP I CF'!L35+'Ascendant CP I CF'!L36 -> 965837.56 | Z66: ='Ascendant CP I CF'!L39+'Ascendant CP I CF'!L41 -> 3089490.3 | AA66: ='Ascendant CP I CF'!L43+'Ascendant CP I CF'!L44 -> 3605265.3 | AB66: ='Ascendant CP I CF'!L48+'Ascendant CP I CF'!L50 -> 2027065.5 | AC66: 0 | AD66: ='Ascendant CP I CF'!L55 -> 1551192.4 | AE66: ='Ascendant CP I CF'!L57+'Ascendant CP I CF'!L59+'Ascendant CP I CF'!L60 -> 6155883.4 | AF66: 198397.62 | AG66: 502795.82 | AH66: 0 | AI66: 600000 | AJ66: 0 | AK66: 0 | AL66: 0 | AM66: 0 | AN66: 0 | AY66: 2025 based on Ascendent guidance.
B67: =B66+1 -> 3 | C67: BOYU Capital Offshore Fund | T67: =SUM(U67:AX67) -> 20506163 | U67: 0 | V67: 0 | W67: 0 | X67: 0 | Y67: 0 | Z67: 0 | AA67: 0 | AB67: 0 | AC67: 0 | AD67: ='BOYU Offshore CF'!D6+'BOYU Offshore CF'!D7+'BOYU Offshore CF'!D8+'BOYU Offshore CF'!D9 -> 11884980 | AE67: ='BOYU Offshore CF'!D11 -> 4435365 | AF67: 0 | AG67: 2720240.9 | AH67: 1155577.1 | AI67: 310000 | AJ67: 0 | AK67: 0 | AL67: 0 | AM67: 0 | AN67: 0 | AY67: 2025 based on Boyu guidance, with no further distribution assumed thereafter.
B68: =B67+1 -> 4 | C68: Ark Pacific Special Oppor Fund I | T68: =SUM(U68:AX68) -> 3636000 | U68: 0 | V68: 0 | W68: 0 | X68: 0 | Y68: 0 | Z68: 0 | AA68: 0 | AB68: 0 | AC68: 0 | AD68: 2232000 | AE68: 1200000 | AF68: 204000 | AG68: 0 | AH68: 0 | AI68: 0 | AJ68: 0 | AK68: 0 | AL68: 0 | AM68: 0 | AN68: 0 | AY68: The fund has terminated, so no more distribution in future
B69: =B68+1 -> 5 | C69: E15 Fund I | T69: =SUM(U69:AX69) -> 4858210.8 | U69: 0 | V69: 0 | W69: 0 | X69: 0 | Y69: 0 | Z69: 0 | AA69: 0 | AB69: 0 | AC69: ='E15 Fund I (CF) '!J12+'E15 Fund I (CF) '!J13 -> 3982313.7 | AD69: ='E15 Fund I (CF) '!J14+'E15 Fund I (CF) '!J15 -> 175897.13 | AE69: 0 | AF69: 0 | AG69: 0 | AH69: 0 | AI69: 700000 | AJ69: 0 | AK69: 0 | AL69: 0 | AM69: 0 | AN69: 0 | AY69: The fund has no more active investment, so expect final distribution from exit of SAM Labs at latest value. 2025 based on E15 guidance.
B70: =B69+1 -> 6 | C70: West Street Capital Partners VII | T70: =SUM(U70:AX70) -> 50000000 | U70: 0 | V70: 0 | W70: 0 | X70: 0 | Y70: 0 | Z70: 0 | AA70: 0 | AB70: 0 | AC70: 0 | AD70: 0 | AE70: ='West Street VII (CF)'!L14+'West Street VII (CF)'!L16+'West Street VII (CF)'!L17+'West Street VII (CF)'!L18 -> 3309646 | AF70: 10334517 | AG70: 352405 | AH70: 792997 | AI70: 2267217 | AJ70: 10981073 | AK70: 10981073 | AL70: 10981073 | AY70: 2025 based on West Street guidance. Assume even distribution at MoM of 2.0x from 2026 to 2028 (end of term).
B71: =B70+1 -> 7 | C71: C Ventures Fund II | T71: =SUM(U71:AX71) -> 30000000 | U71: 0 | V71: 0 | W71: 0 | X71: 0 | Y71: 0 | Z71: 0 | AA71: 0 | AB71: 0 | AC71: 0 | AD71: ='C Ventures II CF '!K18 -> 214285.72 | AE71: ='C Ventures II CF '!K25+'C Ventures II CF '!K26+'C Ventures II CF '!K27 -> 666514.2 | AF71: 2136450.5 | AG71: 3240962.2 | AH71: 0 | AI71: 2000000 | AJ71: 10870894 | AK71: 10870894 | AL71: 0 | AM71: 0 | AN71: 0 | AY71: Updated 2025 distribution based on C Capital estimate, assume even distribution at MoM of 1.5x from 2026 to 2027 (extension). A discount to target MoIC is made based on YTD performance.
B72: =B71+1 -> 8 | C72: DCP Capital Partners | T72: =SUM(U72:AX72) -> 90000000 | U72: 0 | V72: 0 | W72: 0 | X72: 0 | Y72: 0 | Z72: 0 | AA72: 0 | AB72: 0 | AC72: ='DCP I (CF)'!L30 -> 662589.26 | AD72: ='DCP I (CF)'!L33+'DCP I (CF)'!L35+'DCP I (CF)'!L36 -> 2639800.1 | AE72: ='DCP I (CF)'!L38+'DCP I (CF)'!L42+'DCP I (CF)'!L44+'DCP I (CF)'!L45 -> 3227173.9 | AF72: 3181636.9 | AG72: 13446533 | AH72: 5320663.2 | AI72: 5654980 | AJ72: 13966656 | AK72: 13966656 | AL72: 13966656 | AM72: 13966656 | AN72: 0 | AY72: Update 2025 distribution based on DCP estimate, assume even distirbution at MoM of 1.8x from 2026 to 2029 (extension).
B73: =B72+1 -> 9 | C73: E15 Fund 1.5 | T73: =SUM(U73:AX73) -> 2929359.9 | U73: 0 | V73: 0 | W73: 0 | X73: 0 | Y73: 0 | Z73: 0 | AA73: 0 | AB73: 0 | AC73: 2807879.7 | AD73: 121480.17 | AE73: 0 | AF73: 0 | AG73: 0 | AH73: 0 | AI73: 0 | AJ73: 0 | AK73: 0 | AL73: 0 | AY73: All portfolio realized, not more distribution
B74: =B73+1 -> 10 | C74: Skycus China Fund | T74: =SUM(U74:AX74) -> 54000000 | U74: 0 | V74: 0 | W74: 0 | X74: 0 | Y74: 0 | Z74: 0 | AA74: 0 | AB74: 0 | AC74: 0 | AD74: 0 | AE74: ='Skycus China CF'!L16+'Skycus China CF'!L17+'Skycus China CF'!L18 -> 2920577.9 | AF74: 0 | AG74: 852079.94 | AH74: 1555253.7 | AI74: 15600000 | AJ74: 11024029 | AK74: 11024029 | AL74: 11024029 | AN74: 0 | AY74: Update 2025 distribution based on Skycus estimates, assume MoM of 1.8x, include near term exit of JD industrial, JD logistic, SF express and Lalamove. Expect to exercise full extension by 2 years to 2028.
B75: =B74+1 -> 11 | C75: Hongshan Capital Venture Partners Fund VIII (AKA "Sequoia Capital China Venture Partners VIII") | T75: =SUM(U75:AX75) -> 12600000 | U75: 0 | V75: 0 | W75: 0 | X75: 0 | Y75: 0 | Z75: 0 | AA75: 0 | AB75: 0 | AC75: 0 | AD75: 0 | AE75: 0 | AF75: 0 | AG75: 0 | AH75: 0 | AI75: 2250000 | AJ75: 2070000 | AK75: 2070000 | AL75: 2070000 | AM75: 2070000 | AN75: 2070000 | AY75: 2025 based on HS guidance. Assume even distribution at MoM of 2.8x from 2026 to 2030, higher multiple due to its venture nature
B76: =B75+1 -> 12 | C76: HongShan Capital Growth Partners Fund VI (AKA "Sequoia Capital China Growth Partners VI") | T76: =SUM(U76:AX76) -> 31500000 | U76: 0 | V76: 0 | W76: 0 | X76: 0 | Y76: 0 | Z76: 0 | AA76: 0 | AB76: 0 | AC76: 0 | AD76: 0 | AE76: ='HSG Growth VI (CF) '!K15 -> 121791 | AF76: 0 | AG76: 0 | AH76: 0 | AI76: 5755000 | AJ76: 5124641.8 | AK76: 5124641.8 | AL76: 5124641.8 | AM76: 5124641.8 | AN76: 5124641.8 | AY76: 2025 based on HS guidance. Assume even distribution at MoM of 2x from 2026 to 2030
B77: =B76+1 -> 13 | C77: West Street Capital Partners VIII | T77: =SUM(U77:AX77) -> 100000000 | U77: 0 | V77: 0 | W77: 0 | X77: 0 | Y77: 0 | Z77: 0 | AA77: 0 | AB77: 0 | AC77: 0 | AD77: 0 | AE77: 0 | AF77: 650000 | AG77: 0 | AH77: 0 | AI77: 0 | AJ77: 19870000 | AK77: 19870000 | AL77: 19870000 | AM77: 19870000 | AN77: 19870000 | AY77: 2025 no distribution expected by West Street. Assume even distribution at MoM of 2x from 2026 to 2030 (end of term)
B78: =B77+1 -> 14 | C78: DCP Capital Partners II | T78: =SUM(U78:AX78) -> 1.8e+08 | U78: 0 | V78: 0 | W78: 0 | X78: 0 | Y78: 0 | Z78: 0 | AA78: 0 | AB78: 0 | AC78: 0 | AD78: 0 | AE78: 0 | AF78: 492504.54 | AG78: 89423.06 | AH78: 2586900.4 | AI78: 2000000 | AJ78: 24975882 | AK78: 24975882 | AL78: 24975882 | AM78: 24975882 | AN78: 24975882 | AO78: 24975882 | AP78: 24975882 | AY78: DCP estimate $2m distribution in 2025, assume even distribution at MoM of 1.8x from 2026 to 2032 (end of term)
B79: =B78+1 -> 15 | C79: Skycus USD Fund II (AKA “Lionet Fund LP”) | T79: =SUM(U79:AX79) -> 22500000 | U79: 0 | V79: 0 | W79: 0 | X79: 0 | Y79: 0 | Z79: 0 | AA79: 0 | AB79: 0 | AC79: 0 | AD79: 0 | AE79: ='Lionet Fund CF'!L13+'Lionet Fund CF'!L16+'Lionet Fund CF'!L18 -> 607971.2 | AF79: 0 | AG79: 212340.74 | AH79: 1377295.2 | AI79: 2133742.3 | AJ79: 3633730.1 | AK79: 3633730.1 | AL79: 3633730.1 | AM79: 3633730.1 | AN79: 3633730.1 | AY79: Updated 2025 distribution based on Skycus estimates, assume MoM of 2x with even distribution till 2030.
B80: =B79+1 -> 16 | C80: BOYU Real Estate Fund I | T80: =SUM(U80:AX80) -> 69000000 | U80: 0 | V80: 0 | W80: 0 | X80: 0 | Y80: 0 | Z80: 0 | AA80: 0 | AB80: 0 | AC80: 0 | AD80: 0 | AE80: ='Boyu Real Estate CF'!K13+'Boyu Real Estate CF'!K17+'Boyu Real Estate CF'!K18+'Boyu Real Estate CF'!K19+'Boyu Real Estate CF'!K20+'Boyu Real Estate CF'!K22 -> 1452983 | AF80: 692195.41 | AG80: 712155.9 | AH80: 0 | AI80: 0 | AJ80: 13228533 | AK80: 13228533 | AL80: 13228533 | AM80: 13228533 | AN80: 13228533 | AY80: Updated 2025 distribution based on Boyu estimate, assume even distirbution at MoM of 2.3x from 2026 to 2030, upgrade from prior forecast in view of growing demand for datacenter with AI development.
B81: =B80+1 -> 17 | C81: E15 Fund II | T81: =SUM(U81:AX81) -> 27270430 | U81: 0 | V81: 0 | W81: 0 | X81: 0 | Y81: 0 | Z81: 0 | AA81: 0 | AB81: 0 | AC81: 0 | AD81: 0 | AE81: 0 | AF81: 23939079 | AG81: 683168.56 | AH81: 0 | AI81: 0 | AJ81: 0 | AK81: 1324091.2 | AL81: 1324091.2 | AY81: Assume even distribution of KIL share (32.1%) of the remaining assets at latest NAV in 2027-2028
B82: =B81+1 -> 18 | C82: Cottonwood | T82: =SUM(U82:AX82) -> 31375000 | U82: 0 | V82: 0 | W82: 0 | X82: 0 | Y82: 0 | Z82: 0 | AA82: 0 | AB82: 0 | AC82: 0 | AD82: 0 | AE82: 0 | AF82: 0 | AG82: 0 | AH82: 0 | AI82: 125000 | AJ82: 0 | AK82: 6250000 | AL82: 6250000 | AM82: 6250000 | AN82: 6250000 | AO82: 6250000 | AY82: 2025 based on Cottonwood guidance. Assume even distribution at MoM of 2.5x from 2027 to 2031.
B83: =B82+1 -> 19 | C83: Genedant Ventures I | T83: =SUM(U83:AX83) -> 10341566 | AM83: 1723594.2 | AN83: 1723594.2 | AO83: 1723594.2 | AP83: 1723594.2 | AQ83: 1723594.2 | AR83: 1723594.2 | AY83: Based on dirrect input from GCPL team, overall the fund target to achieve MoM 3.5x
B84: =B83+1 -> 20 | C84: GTCR XIV Access Offshore LP | T84: =SUM(U84:AX84) -> 42350000 | AM84: 8470000 | AN84: 8470000 | AO84: 8470000 | AP84: 8470000 | AQ84: 8470000 | AY84: Assume even distribution at MoM of 2.5x from 2029 to 2033.
T86: =SUM(T65:T85) -> 8.9658598e+08 | U86: =SUM(U65:U85) -> 287574.3 | V86: =SUM(V65:V85) -> 2011179.8 | W86: =SUM(W65:W85) -> 1419239 | X86: =SUM(X65:X85) -> 4085265.3 | Y86: =SUM(Y65:Y85) -> 20238315 | Z86: =SUM(Z65:Z85) -> 16140075 | AA86: =SUM(AA65:AA85) -> 26493013 | ... AN86: =SUM(AN65:AN85) -> 85346381
B88: Net Cash Flow | T88: =T62+T86 -> 4.3886877e+08 | U88: =U62+U86 -> -2738663.8 | V88: =V62+V86 -> -14361451 | W88: =W62+W86 -> -3014034.2 | X88: =X62+X86 -> -4327936.3 | Y88: =Y62+Y86 -> 13680476 | Z88: =Z62+Z86 -> 5426217.9 | AA88: =AA62+AA86 -> 18653104 | ... AN88: =AN62+AN86 -> 85346381
B89: WACC | T89: 0.08
B90: Accumulated Net Cash Flow | T90: =AN90 -> 2.4872984e+93 | U90: =U88 -> -2738663.8 | V90: =V88 -> -14361451 | W90: =W88 -> -3014034.2 | X90: =X88 -> -4327936.3 | Y90: =Y88 -> 13680476 | Z90: =Z88 -> 5426217.9 | AA90: =AA88 -> 18653104 | AB90: =AB88 -> -11873619 | ... AH90: =AH88 -> -23020907 | AI90: =AI88*(1+$T$89)^(AI3-$AG$3) -> -2.4692428e+31 | AJ90: =AJ88*(1+$T$89)^(AJ3-$AG$3) -> 3.2906922e+44 | AK90: =AK88*(1+$T$89)^(AK3-$AG$3) -> 6.4270891e+56 | AL90: =AL88*(1+$T$89)^(AL3-$AG$3) -> 1.2564139e+69 | AM90: =AM88*(1+$T$89)^(AM3-$AG$3) -> 1.827588e+81 | AN90: =AN88*(1+$T$89)^(AN3-$AG$3) -> 2.4872984e+93

Sheet FUNDS >>

Sheet Ascendent CP I
A1: Fund Overview | D1: Fund Performance Indicator | E1: 45657 | H1: Fee Term
A2: Fund Full Name | B2: Ascendent Capital Partners I, L.P. | D2: Fair Value of Porfolio Companies (US$/mil) | E2: =W40 -> 6.4 | H2: Management fees - investment period | I2: 2% of commitment
A3: Initial Closing Date | B3: 40651 | D3: Total Net Asset Value (US$/mil) | E3: 9.490431 | H3: Management fees - after investment period | I3: 2% of invested capital
A4: Final Closing Date | B4: 41016 | D4: Fund Gross Multiple (x) | E4: 2.9 | H4: Preferred Return | I4: 0.08
A5: Vintage Year | B5: 2012 | D5: Fund Net Multiple (x) | E5: 2.1 | H5: Carried Interest | I5: 0.2
A6: General Partner ("GP") | B6: Ascendent Capital Partners I GP, L.P. | D6: Fund Gross IRR (%) | E6: 0.29 | H6: LP Reporting Timeline
A7: Investment Manager | B7: Ascendent Capital Partners Limited | D7: Fund Net IRR (%) | E7: 0.201 | H7: Quarterly report (after period end) | I7: 60 days
A8: Fund Domicile | B8: Cayman Islands | D8: Fund Distribution to Paid-in Capital (DPI %) | E8: =738.4/309.8 -> 2.3834732 | H8: Annual report (after period end) | I8: 120 days
A9: Fund Term | B9: 8 years from Final Closing Date | D9: CCG Performance Indicator
A10: Extensions | B10: 1 + 1 year | D10: Commitment (US$/mil) | E10: 10
A11: Investment Period | B11: 42277 | D11: Ownership % | E11: =10/365.4 -> 0.027367269
A12: Fund Currency | B12: USD | D12: Cumulative Contribution (US$/mil) | E12: =-'Ascendant CP I CF'!N2/10^6 -> 8.5702764
A13: Fund Size / Total Commitment | B13: US$365.4mil | D13: Remaining Unfunded Commitment (US$/mil) | E13: =E10-E12 -> 1.4297236
A14: Minimum Commitment | B14: US$10mil | D14: Cumulative Distribution (US$/mil) | E14: ='Ascendant CP I CF'!N3/10^6 -> 20.207464
A15: GP commitment | B15: US$21.5mil | D15: Capital Account Balance (US$/mil) | E15: ='Ascendant CP I CF'!N4/10^6 -> 0.249627
A16: Financial Year End | B16: 44196 | D16: Call-up Percentage (%) | E16: =E12/E10 -> 0.85702764
A17: Accounting Principles | B17: US GAAP | D17: Distribution to Paid-in Capital (DPI %) | E17: =E14/E12 -> 2.3578545
A18: Portfolio | D18: Multiple (x) | E18: =(E14+E15)/E12 -> 2.3869815
A19: Number of Portfolio Company | B19: 7 | D19: IRR (%) | E19: ='Ascendant CP I CF'!N5 -> 0.22429716
K30: Q4 2023 | T30: Q4 2024 | AC30: Q1 2025
A31: Portfolio | B31: Company Description | C31: Sector | D31: Status (Unrealized / Partial Realized / Realized / Write-off) | E31: First Investment Date | F31: IPO Date | G31: Ticker | H31: Exit Date | I31: Exit Method | J31: Holding Period (years) | K31: Investment Cost (USD/mil) | L31: % of Ownership | M31: Realized Value (USD/mil) | N31: Unrealized Value (USD/mil) | O31: Total Value (USD/mil) | P31: MOIC | Q31: IRR * | R31: Total Value - $ change YoY | S31: Total Value - % change YoY | T31: Investment Cost (USD/mil) | U31: % of Ownership | V31: Realized Value (USD/mil) | W31: Unrealized Value (USD/mil) | X31: Total Value (USD/mil) | Y31: MOIC | Z31: IRR * | AA31: Total Value - $ change YoY | AB31: Total Value - % change YoY | AC31: Investment Cost (USD/mil) | AD31: % of Ownership | AE31: Realized Value (USD/mil) | AF31: Unrealized Value (USD/mil) | AG31: Total Value (USD/mil) | AH31: MOIC | AI31: IRR * | AJ31: Total Value - $ change YoY | AK31: Total Value - % change YoY | AL31: Total Value - $ change QoQ | AM31: Total Value - % change QoQ
A32: WH Group Limited | B32: Previously under Shuanghui International; largest meat processor in China and pork producer in the world. | C32: Consumer | D32: Realized | E32: 40909 | J32: - | K32: 40.2 | L32: - | M32: 69.6 | N32: 0 | O32: =M32+N32 -> 69.6 | P32: =O32/K32 -> 1.7313433 | Q32: 0.232 | R32: 0 | S32: - | T32: 40.2 | U32: - | V32: 69.6 | W32: 0 | X32: =V32+W32 -> 69.6 | Y32: =X32/T32 -> 1.7313433 | Z32: 0 | AA32: =X32-O32 -> 0 | AB32: =IFERROR(X32/O32-1,0) -> 0
A33: Nano Resources Limited | B33: SPV to acquire Tong Dai, a railway supplier of parts for high speed trains in China. | C33: Industrials | D33: Realized | E33: 41244 | J33: - | K33: 32 | L33: - | M33: 163.1 | N33: 0 | O33: =N33+M33 -> 163.1 | P33: =O33/K33 -> 5.096875 | Q33: 0.649 | R33: 0 | S33: - | T33: 32 | U33: - | V33: 163.1 | W33: 0 | X33: =W33+V33 -> 163.1 | Y33: =X33/T33 -> 5.096875 | Z33: 0 | AA33: =X33-O33 -> 0 | AB33: =IFERROR(X33/O33-1,0) -> 0
A34: CFP Incorporated | B34: One of the largest metal packaging suppliers in China for consumer goods such as beverages and food products. | C34: Consumer | D34: Realized | E34: 41395 | J34: - | K34: 70 | L34: - | M34: 140.3 | N34: 0 | O34: =N34+M34 -> 140.3 | P34: =O34/K34 -> 2.0042857 | Q34: 0.223 | R34: 0 | S34: - | T34: 70 | U34: - | V34: 140.3 | W34: 0 | X34: =W34+V34 -> 140.3 | Y34: =X34/T34 -> 2.0042857 | Z34: 0 | AA34: =X34-O34 -> 0 | AB34: =IFERROR(X34/O34-1,0) -> 0
A35: Internet Plus Holdings Ltd | B35: One of largest online to offline platforms in China for local consumer products and retail services, monetizing on advertising solutions. | C35: Consumer | D35: Realized | E35: 42005 | J35: =YEAR(H35)-YEAR(E35) -> -115 | K35: 20 | L35: - | M35: 49.9 | N35: 0 | O35: =N35+M35 -> 49.9 | P35: =O35/K35 -> 2.495 | Q35: 0.284 | R35: 0 | S35: - | T35: 20 | U35: - | V35: 49.9 | W35: 0 | X35: =W35+V35 -> 49.9 | Y35: =X35/T35 -> 2.495 | Z35: 0 | AA35: =X35-O35 -> 0 | AB35: =IFERROR(X35/O35-1,0) -> 0
A36: Ningxia Harmony Dairy | B36: Regional dairy company in north China under the name of "Xiajin" | C36: Consumer | D36: Realized | E36: 41791 | J36: - | K36: 46 | L36: - | M36: 100.5 | N36: 0 | O36: =N36+M36 -> 100.5 | P36: =O36/K36 -> 2.1847826 | Q36: 0.131 | R36: 0 | S36: - | T36: 46 | U36: - | V36: 100.5 | W36: 0 | X36: =W36+V36 -> 100.5 | Y36: =X36/T36 -> 2.1847826 | Z36: 0 | AA36: =X36-O36 -> 0 | AB36: =IFERROR(X36/O36-1,0) -> 0
A37: Yongding Healthcare Management | B37: Ownership of YD Hospital, a Grade II general hospital and 2nd largest general hospital in Wujiang, Suzhou providing basic medical services to local residents. | C37: Healthcare | D37: Realized | E37: 41791 | J37: - | K37: 36.3 | L37: - | M37: 199 | N37: 0 | O37: =N37+M37 -> 199 | P37: =O37/K37 -> 5.4820937 | Q37: 0.307 | R37: 0 | S37: - | T37: 36.3 | U37: - | V37: 199 | W37: 0 | X37: =W37+V37 -> 199 | Y37: =X37/T37 -> 5.4820937 | Z37: 0 | AA37: =X37-O37 -> 0 | AB37: =IFERROR(X37/O37-1,0) -> 0
A38: Yan'an Pharmaceutical | B38: Generic pharmaceutical production to sell in county/rural drugstores, community healthcare centres and private clinics across 18 provinces | C38: Healthcare | D38: Partial Realized | E38: 42248 | F38: - | G38: - | H38: - | I38: - | J38: - | K38: 16.2 | L38: - | M38: 16.5 | N38: 8.2 | O38: =N38+M38 -> 24.7 | P38: =O38/K38 -> 1.5246914 | Q38: 0.056 | R38: 0 | S38: - | T38: 16.2 | U38: - | V38: 19.2 | W38: 6.4 | X38: =W38+V38 -> 25.6 | Y38: =X38/T38 -> 1.5802469 | Z38: 0 | AA38: =X38-O38 -> 0.9 | AB38: =IFERROR(X38/O38-1,0) -> 0.036437247
A40: Grand Total | K40: =SUM(K32:K38) -> 260.7 | M40: =SUM(M32:M38) -> 738.9 | N40: =SUM(N32:N38) -> 8.2 | O40: =SUM(O32:O38) -> 747.1 | P40: =O40/K40 -> 2.8657461 | Q40: - | R40: - | S40: - | T40: =SUM(T32:T38) -> 260.7 | V40: =SUM(V32:V38) -> 741.6 | W40: =SUM(W32:W38) -> 6.4 | X40: =SUM(X32:X38) -> 748 | Y40: =X40/T40 -> 2.8691983 | Z40: - | AA40: =X40-O40 -> 0.9 | AB40: =IFERROR(X40/O40-1,0) -> 0.001204658
A42: Sub-Total - Unrealized & Partial Realized | K42: =SUMIF($D$32:$D$38,"Unrealized",K$32:K$38)+SUMIF($D$32:$D$38,"Partial Realized",K$32:K$38) -> 16.2 | M42: =SUMIF($D$32:$D$38,"Unrealized",M$32:M$38)+SUMIF($D$32:$D$38,"Partial Realized",M$32:M$38) -> 16.5 | N42: =SUMIF($D$32:$D$38,"Unrealized",N$32:N$38)+SUMIF($D$32:$D$38,"Partial Realized",N$32:N$38) -> 8.2 | O42: =SUMIF($D$32:$D$38,"Unrealized",O$32:O$38)+SUMIF($D$32:$D$38,"Partial Realized",O$32:O$38) -> 24.7 | P42: =O42/K42 -> 1.5246914 | R42: - | S42: - | T42: =SUMIF($D$32:$D$38,"Unrealized",T$32:T$38)+SUMIF($D$32:$D$38,"Partial Realized",T$32:T$38) -> 16.2 | V42: =SUMIF($D$32:$D$38,"Unrealized",V$32:V$38)+SUMIF($D$32:$D$38,"Partial Realized",V$32:V$38) -> 19.2 | W42: =SUMIF($D$32:$D$38,"Unrealized",W$32:W$38)+SUMIF($D$32:$D$38,"Partial Realized",W$32:W$38) -> 6.4 | X42: =SUMIF($D$32:$D$38,"Unrealized",X$32:X$38)+SUMIF($D$32:$D$38,"Partial Realized",X$32:X$38) -> 25.6 | Y42: =X42/T42 -> 1.5802469 | AA42: =X42-O42 -> 0.9 | AB42: =IFERROR(X42/O42-1,0) -> 0.036437247
A43: Sub-Total - Realized | K43: =SUMIF($D$32:$D$38,"Realized",K$32:K$38)+SUMIF($D$32:$D$38,"Write-off",K$32:K$38) -> 244.5 | M43: =SUMIF($D$32:$D$38,"Realized",M$32:M$38)+SUMIF($D$32:$D$38,"Write-off",M$32:M$38) -> 722.4 | N43: =SUMIF($D$32:$D$38,"Realized",N$32:N$38)+SUMIF($D$32:$D$38,"Write-off",N$32:N$38) -> 0 | O43: =SUMIF($D$32:$D$38,"Realized",O$32:O$38)+SUMIF($D$32:$D$38,"Write-off",O$32:O$38) -> 722.4 | P43: =O43/K43 -> 2.9546012 | R43: - | S43: - | T43: =SUMIF($D$32:$D$38,"Realized",T$32:T$38)+SUMIF($D$32:$D$38,"Write-off",T$32:T$38) -> 244.5 | V43: =SUMIF($D$32:$D$38,"Realized",V$32:V$38)+SUMIF($D$32:$D$38,"Write-off",V$32:V$38) -> 722.4 | W43: =SUMIF($D$32:$D$38,"Realized",W$32:W$38)+SUMIF($D$32:$D$38,"Write-off",W$32:W$38) -> 0 | X43: =SUMIF($D$32:$D$38,"Realized",X$32:X$38)+SUMIF($D$32:$D$38,"Write-off",X$32:X$38) -> 722.4 | Y43: =X43/T43 -> 2.9546012 | AA43: =X43-O43 -> 0 | AB43: =IFERROR(X43/O43-1,0) -> 0
A46: Commentary / Q&A - Tracker
K47: Q4 2023 | T47: Q4 2024 | AC47: Q1 2025
A48: Portfolio | B48: Company Description | C48: Sector | D48: Status (Unrealized / Partial Realized / Realized / Write-off) | E48: First Investment Date | F48: IPO Date | G48: Ticker | H48: Exit Date | I48: Exit Method | J48: Holding Period (years) | K48: Question | O48: Response / Commentary | T48: Question | X48: Response / Commentary | AC48: Question | AG48: Response / Commentary

Sheet Ascendant CP I CF
B1: Fund Investment Cashflow | M1: =C3 -> 45657 | O1: CAS | P1: Recon
M2: Cummulative Contribution | N2: =M65 -> -8570276.4 | O2: -8570277 | P2: =N2-O2 -> 0.65
B3: Date: | C3: ='Ascendent CP I'!E1 -> 45657 | M3: Cummulative Distribution | N3: =R65 -> 20207464 | O3: 20207464 | P3: =N3-O3 -> 0.43
M4: Capital Account Balance | N4: =L67 -> 249627
B5: Fund: | C5: Ascendant Capital Fund | M5: IRR | N5: =XIRR(L11:L67,E11:E67,0) -> 0.22429716
B6: Curr: | C6: USD
B7: Commitment | C7: 10000000
B10: Transaction type (Call/Distribution) | C10: No. | D10: Document date | E10: Trans. Date | F10: Year | G10: Project | H10: Portfolio Investment | I10: Mgmt fee | J10: Partnership exp | K10: Org Fee | L10: Trans. Amt | M10: Cum. Capital called | N10: Remaining callable capital | O10: Distributions | P10: Cum. Dist before Carry | Q10: Carry Interest | R10: Cum. Dist after Carry | S10: Capital Account Balance
B11: Capital Call | C11: CC#1 | D11: 40893 | E11: 40912 | F11: =YEAR(E11) -> 2012 | G11: Shuanghui | H11: -1661500.3 | I11: -49315.07 | K11: -170695.38 | L11: =SUM(H11:K11) -> -1881510.8 | M11: =IF(L11<0,L11,0) -> -1881510.8 | N11: =M11+$C$7 -> 8118489.2 | O11: =IF(L11>0,L11,0) -> 0 | P11: =O11 -> 0
B12: Capital Call | C12: CC#2 | D12: 40994 | E12: 41011 | F12: =YEAR(E12) -> 2012 | I12: -49863.01 | J12: -4133.09 | K12: -20665.43 | L12: =SUM(H12:K12) -> -74661.53 | M12: =M11+IF(L12<0,L12,0) -> -1956172.3 | N12: =M12+$C$7 -> 8043827.7 | O12: =IF(L12>0,L12,0) -> 0 | P12: =P11+O12 -> 0
B13: Capital Call | C13: CC#3 | D13: 41075 | E13: 41093 | F13: =YEAR(E13) -> 2012 | I13: -50410.96 | L13: =SUM(H13:K13) -> -50410.96 | M13: =M12+IF(L13<0,L13,0) -> -2006583.3 | N13: =M13+$C$7 -> 7993416.8 | O13: =IF(L13>0,L13,0) -> 0 | P13: =P12+O13 -> 0 | T13: Ties to 2012 Q2 CAS
B14: Recallable distribution | C14: DD#1 | D14: 41246 | E14: 41260 | F14: =YEAR(E14) -> 2012 | H14: 561366.21 | J14: 1396.44 | K14: 22624.42 | L14: =SUM(H14:K14) -> 585387.07 | M14: =M13+IF(L14<0,L14,0)+L14 -> -1421196.2 | N14: =M14+$C$7 -> 8578803.8 | O14: 0 | P14: =P13+O14 -> 0 | T14: Ties to 2012 Q3 CAS
B15: Capital Call | C15: CC#4 | D15: 41246 | E15: 41260 | F15: =YEAR(E15) -> 2012 | G15: Queens | H15: -875728.63 | I15: =-50410.96 -> -50410.96 | J15: -5473.3 | L15: =SUM(H15:K15) -> -931612.89 | M15: =M14+IF(L15<0,L15,0) -> -2352809.1 | N15: =M15+$C$7 -> 7647190.9 | O15: =IF(L15>0,L15,0) -> 0 | P15: =P14+O15 -> 0
B16: Distribution | C16: DD#1 | D16: 41246 | E16: 41260 | F16: =YEAR(E16) -> 2012 | G16: Shuanghui dvd | H16: 15525.35 | L16: =SUM(H16:K16) -> 15525.35 | M16: =M15+IF(L16<0,L16,0) -> -2352809.1 | N16: =M16+$C$7 -> 7647190.9 | O16: =IF(L16>0,L16,0) -> 15525.35 | P16: =P15+O16 -> 15525.35 | R16: =P15+O16 -> 15525.35 | T16: Ties to 2012 Q4 CAS
B17: Capital Call | C17: CC#5 | D17: 41000 | E17: 41292 | F17: =YEAR(E17) -> 2013 | I17: -49315.07 | L17: =SUM(H17:K17) -> -49315.07 | M17: =M16+IF(L17<0,L17,0) -> -2402124.1 | N17: =M17+$C$7 -> 7597875.9 | O17: =IF(L17>0,L17,0) -> 0 | P17: =P16+O17 -> 15525.35 | R17: =P16+O17 -> 15525.35 | T17: Ties to 2013 Q1 CAS
B18: Capital Call | C18: CC#7 | D18: 41415 | E18: 41428 | F18: =YEAR(E18) -> 2013 | G18: CAN | H18: -1477792.1 | L18: =SUM(H18:K18) -> -1477792.1 | M18: =M17+IF(L18<0,L18,0) -> -3879916.2 | N18: =M18+$C$7 -> 6120083.8 | O18: =IF(L18>0,L18,0) -> 0 | P18: =P17+O18 -> 15525.35 | R18: =P17+O18 -> 15525.35
B19: Capital Call | C19: CC#8 | D19: 41439 | E19: 41452 | F19: =YEAR(E19) -> 2013 | G19: CAN | H19: -437864.32 | I19: -50410.96 | L19: =SUM(H19:K19) -> -488275.28 | M19: =M18+IF(L19<0,L19,0) -> -4368191.5 | N19: =M19+$C$7 -> 5631808.5 | O19: =IF(L19>0,L19,0) -> 0 | P19: =P18+O19 -> 15525.35 | R19: =P18+O19 -> 15525.35
B20: Capital Call | C20: CC#6 | D20: 41382 | E20: 41336 | F20: =YEAR(E20) -> 2013 | I20: -49863.01 | J20: -8209.96 | K20: 2300.16 | L20: =SUM(H20:K20) -> -55772.81 | M20: =M19+IF(L20<0,L20,0) -> -4423964.3 | N20: =M20+$C$7 -> 5576035.7 | O20: =IF(L20>0,L20,0) -> 0 | P20: =P19+O20 -> 15525.35 | R20: =P19+O20 -> 15525.35 | T20: Ties to 2013 Q2 CAS
B21: Capital Call | C21: CC#9 | D21: 41544 | E21: 41562 | F21: =YEAR(E21) -> 2013 | I21: -50410.96 | L21: =SUM(H21:K21) -> -50410.96 | M21: =M20+IF(L21<0,L21,0) -> -4474375.3 | N21: =M21+$C$7 -> 5525624.7 | O21: =IF(L21>0,L21,0) -> 0 | P21: =P20+O21 -> 15525.35 | R21: =P20+O21 -> 15525.35 | T21: Ties to 2013 Q3 CAS
B22: Capital Call | C22: CC#10 | D22: 41626 | E22: 41645 | F22: =YEAR(E22) -> 2014 | I22: -49315.07 | J22: -5473.3 | L22: =SUM(H22:K22) -> -54788.37 | M22: =M21+IF(L22<0,L22,0) -> -4529163.6 | N22: =M22+$C$7 -> 5470836.4 | O22: =IF(L22>0,L22,0) -> 0 | P22: =P21+O22 -> 15525.35 | R22: =P21+O22 -> 15525.35
B23: Distribution | C23: DD#2 | D23: 41626 | E23: 41645 | F23: =YEAR(E23) -> 2014 | H23: 41256.55 | L23: =SUM(H23:K23) -> 41256.55 | M23: =M22+IF(L23<0,L23,0) -> -4529163.6 | N23: =M23+$C$7 -> 5470836.4 | O23: =IF(L23>0,L23,0) -> 41256.55 | P23: =P22+O23 -> 56781.9 | R23: =P22+O23 -> 56781.9
B24: Capital Call | C24: CC#11 | D24: 41717 | E24: 41732 | F24: =YEAR(E24) -> 2014 | I24: -49863.01 | J24: -5473.3 | L24: =SUM(H24:K24) -> -55336.31 | M24: =M23+IF(L24<0,L24,0) -> -4584499.9 | N24: =M24+$C$7 -> 5415500.1 | O24: =IF(L24>0,L24,0) -> 0 | P24: =P23+O24 -> 56781.9 | R24: =P23+O24 -> 56781.9 | T24: Ties to 2014 Q1 CAS
B25: Capital Call | C25: CC#12 | D25: 41779 | E25: 41794 | F25: =YEAR(E25) -> 2014 | G25: Bronze | H25: -738896.03 | L25: =SUM(H25:K25) -> -738896.03 | M25: =M24+IF(L25<0,L25,0) -> -5323396 | N25: =M25+$C$7 -> 4676604 | O25: =IF(L25>0,L25,0) -> 0 | P25: =P24+O25 -> 56781.9 | R25: =P24+O25 -> 56781.9
B26: Capital Call | C26: CC#13 | D26: 41794 | E26: 41809 | F26: =YEAR(E26) -> 2014 | G26: Summer | H26: -1258859.9 | I26: -50410.96 | J26: -5473.3 | L26: =SUM(H26:K26) -> -1314744.2 | M26: =M25+IF(L26<0,L26,0) -> -6638140.1 | N26: =M26+$C$7 -> 3361859.9 | O26: =IF(L26>0,L26,0) -> 0 | P26: =P25+O26 -> 56781.9 | R26: =P25+O26 -> 56781.9
B27: Recallable distribution | C27: DD#3 | D27: 41794 | E27: 41809 | F27: =YEAR(E27) -> 2014 | G27: CAN | H27: 437864.32 | L27: =SUM(H27:K27) -> 437864.32 | M27: =M26 -> -6638140.1 | N27: =M27+$C$7 -> 3361859.9 | O27: =IF(L27>0,L27,0) -> 437864.32 | P27: =P26+O27 -> 494646.22 | R27: =P26+O27 -> 494646.22
B28: Distribution | C28: DD#3 | D28: 41794 | E28: 41809 | F28: =YEAR(E28) -> 2014 | G28: CAN | H28: 53912.04 | L28: =SUM(H28:K28) -> 53912.04 | M28: =M27+IF(L28<0,L28,0) -> -6638140.1 | N28: =M28+$C$7 -> 3361859.9 | O28: =IF(L28>0,L28,0) -> 53912.04 | P28: =P27+O28 -> 548558.26 | R28: =P27+O28 -> 548558.26
B29: Distribution | C29: DD#4 | D29: 41836 | E29: 41850 | F29: =YEAR(E29) -> 2014 | G29: Nano dvd | H29: 100690.83 | L29: =SUM(H29:K29) -> 100690.83 | M29: =M28+IF(L29<0,L29,0) -> -6638140.1 | N29: =M29+$C$7 -> 3361859.9 | O29: =IF(L29>0,L29,0) -> 100690.83 | P29: =P28+O29 -> 649249.09 | R29: =P28+O29 -> 649249.09
B30: Distribution | C30: DD#5 | D30: 41872 | E30: 41880 | F30: =YEAR(E30) -> 2014 | G30: Shuanghui | H30: 1169767.9 | L30: =SUM(H30:K30) -> 1169767.9 | M30: =M29+IF(L30<0,L30,0) -> -6638140.1 | N30: =M30+$C$7 -> 3361859.9 | O30: =IF(L30>0,L30,0) -> 1169767.9 | P30: =P29+O30 -> 1819016.9 | R30: =P29+O30 -> 1819016.9 | T30: Ties to 2014 Q3 CAS
B31: Capital Call | C31: CC#14 | D31: 41968 | E31: 41971 | F31: =YEAR(E31) -> 2014 | I31: -50410.96 | L31: =SUM(H31:K31) -> -50410.96 | M31: =M30+IF(L31<0,L31,0) -> -6688551.1 | N31: =M31+$C$7 -> 3311448.9 | O31: =IF(L31>0,L31,0) -> 0 | P31: =P30+O31 -> 1819016.9 | R31: =P30+O31 -> 1819016.9
B32: Distribution | C32: DD#6 | D32: 41968 | E32: 41971 | F32: =YEAR(E32) -> 2014 | G32: CAN & Nano dvd | H32: 197424 | L32: =SUM(H32:K32) -> 197424 | M32: =M31+IF(L32<0,L32,0) -> -6688551.1 | N32: =M32+$C$7 -> 3311448.9 | O32: =IF(L32>0,L32,0) -> 197424 | P32: =P31+O32 -> 2016440.9 | R32: =P31+O32 -> 2016440.9
B33: Recallable distribution | C33: DD#6 | D33: 41968 | E33: 41971 | F33: =YEAR(E33) -> 2014 | G33: CAN | H33: 95096.03 | L33: =SUM(H33:K33) -> 95096.03 | M33: =M32 -> -6688551.1 | N33: =M33+$C$7 -> 3311448.9 | O33: =IF(L33>0,L33,0) -> 95096.03 | P33: =P32+O33 -> 2111537 | R33: =P32+O33 -> 2111537 | T33: Ties to 2014 Q4 CAS
B34: Capital Call | C34: CC#15 | D34: 42018 | E34: 42023 | F34: =YEAR(E34) -> 2015 | G34: Dianping | H34: -547330.4 | I34: -99178 | J34: -8209.96 | L34: =SUM(H34:K34) -> -654718.36 | M34: =M33+IF(L34<0,L34,0) -> -7343269.5 | N34: =M34+$C$7 -> 2656730.5 | O34: =IF(L34>0,L34,0) -> 0 | P34: =P33+O34 -> 2111537 | R34: =P33+O34 -> 2111537 | T34: Ties to 2015 Q1,Q2 CAS
B35: Distribution | C35: DD#7 | D35: 42018 | E35: 42023 | F35: =YEAR(E35) -> 2015 | G35: Shuanghui sale & Nano dvd | H35: 822168.26 | L35: =SUM(H35:K35) -> 822168.26 | M35: =M34+IF(L35<0,L35,0) -> -7343269.5 | N35: =M35+$C$7 -> 2656730.5 | O35: =IF(L35>0,L35,0) -> 822168.26 | P35: =P34+O35 -> 2933705.2 | R35: =P34+O35 -> 2933705.2
B36: Distribution | C36: DD#8 | D36: 42229 | E36: 42243 | F36: =YEAR(E36) -> 2015 | G36: Can & Yongding | H36: 143669.3 | L36: =SUM(H36:K36) -> 143669.3 | M36: =M35+IF(L36<0,L36,0) -> -7343269.5 | N36: =M36+$C$7 -> 2656730.5 | O36: =IF(L36>0,L36,0) -> 143669.3 | P36: =P35+O36 -> 3077374.5 | R36: =P35+O36 -> 3077374.5
B37: Capital Call | C37: CC#17 | D37: 42229 | E37: 42243 | F37: =YEAR(E37) -> 2015 | G37: Mint & Yongding | H37: =-443337.62-115951.98 -> -559289.6 | I37: -50410.96 | J37: -10946.61 | L37: =SUM(H37:K37) -> -620647.17 | M37: =M36+IF(L37<0,L37,0) -> -7963916.6 | N37: =M37+$C$7 -> 2036083.4 | O37: =IF(L37>0,L37,0) -> 0 | P37: =P36+O37 -> 3077374.5 | R37: =P36+O37 -> 3077374.5 | T37: Ties to 2015 Q3 CAS
B38: Capital Call | C38: CC#18 | D38: 42401 | E38: 42404 | F38: =YEAR(E38) -> 2016 | I38: -53481.08 | J38: -10946.61 | L38: =SUM(H38:K38) -> -64427.69 | M38: =M37+IF(L38<0,L38,0) -> -8028344.3 | N38: =M38+$C$7 -> 1971655.7 | O38: =IF(L38>0,L38,0) -> 0 | P38: =P37+O38 -> 3077374.5 | R38: =P37+O38 -> 3077374.5
B39: Distribution | C39: DD#9 | D39: 42401 | E39: 42404 | F39: =YEAR(E39) -> 2016 | G39: Shuanghui sale & Nano dvd | H39: =2374372.74+89913 -> 2464285.7 | L39: =SUM(H39:K39) -> 2464285.7 | M39: =M38+IF(L39<0,L39,0) -> -8028344.3 | N39: =M39+$C$7 -> 1971655.7 | O39: =IF(L39>0,L39,0) -> 2464285.7 | P39: =P38+O39+Q39 -> 5631573.3 | Q39: 89913 | R39: =P38+O39-0.4 -> 5541659.9 | T39: Ties to 2016 Q1 CAS
B40: Capital Call | C40: CC#19 | D40: 42496 | E40: 42500 | F40: =YEAR(E40) -> 2016 | G40: Bronze | H40: -138556.66 | I40: -22373.89 | L40: =SUM(H40:K40) -> -160930.55 | M40: =M39+IF(L40<0,L40,0) -> -8189274.9 | N40: =M40+$C$7 -> 1810725.1 | O40: =IF(L40>0,L40,0) -> 0 | P40: =P39+O40+Q40 -> 5631573.3 | R40: =R39+O40 -> 5541659.9
B41: Distribution | C41: DD#10 | D41: 42496 | E41: 42500 | F41: =YEAR(E41) -> 2016 | G41: Nano sale & Bronze dvd | H41: 625204.57 | L41: =SUM(H41:K41) -> 625204.57 | M41: =M40+IF(L41<0,L41,0) -> -8189274.9 | N41: =M41+$C$7 -> 1810725.1 | O41: =IF(L41>0,L41,0) -> 625204.57 | P41: =P40+O41 -> 6256777.8 | Q41: 110000.91 | R41: =R40+O41 -> 6166864.4 | T41: Ties to 2016 Q2,Q3,Q4, 2017 Q1 CAS
B42: Capital Call | C42: CC#20 | D42: 42865 | E42: 42870 | F42: =YEAR(E42) -> 2017 | I42: -126777 | L42: =SUM(H42:K42) -> -126777 | M42: =M41+IF(L42<0,L42,0) -> -8316051.9 | N42: =M42+$C$7 -> 1683948.1 | O42: =IF(L42>0,L42,0) -> 0 | P42: =P41+O42+Q42 -> 6256777.8 | R42: =R41+O42 -> 6166864.4
B43: Distribution | C43: DD#11 | D43: 42865 | E43: 42870 | F43: =YEAR(E43) -> 2017 | H43: =552530 -> 552530 | L43: =SUM(H43:K43) -> 552530 | M43: =M42+IF(L43<0,L43,0) -> -8316051.9 | N43: =M43+$C$7 -> 1683948.1 | O43: =IF(L43>0,L43,0) -> 552530 | P43: =P42+O43+Q43 -> 6811404.8 | Q43: 2097 | R43: =R42+O43 -> 6719394.4 | T43: Ties to 2017 Q2 CAS
B44: Distribution | C44: DD#12 | D44: 42982 | E44: 42989 | F44: =YEAR(E44) -> 2017 | G44: Can | H44: =2983649.1+69086.18 -> 3052735.3 | L44: =SUM(H44:K44) -> 3052735.3 | M44: =M43+IF(L44<0,L44,0) -> -8316051.9 | N44: =M44+$C$7 -> 1683948.1 | O44: =IF(L44>0,L44,0) -> 3052735.3 | P44: =P43+O44+Q44 -> 9933226.3 | Q44: 69086.18 | R44: =R43+O44 -> 9772129.7 | T44: Ties to 2017 Q3,Q4 CAS
B45: Capital Call | C45: CC#23 | D45: 43123 | E45: 43136 | F45: =YEAR(E45) -> 2018 | I45: -32340.48 | J45: -10946.61 | L45: =SUM(H45:K45) -> -43287.09 | M45: =M44+IF(L45<0,L45,0) -> -8359339 | N45: =M45+$C$7 -> 1640661 | O45: =IF(L45>0,L45,0) -> 0 | P45: =P44+O45+Q45 -> 9933226.3 | R45: =R44+O45 -> 9772129.7
B46: Capital Call | C46: CC#24 | D46: 43175 | E46: 43193 | F46: =YEAR(E46) -> 2018 | I46: -16170.24 | L46: =SUM(H46:K46) -> -16170.24 | M46: =M45+IF(L46<0,L46,0) -> -8375509.2 | N46: =M46+$C$7 -> 1624490.8 | O46: =IF(L46>0,L46,0) -> 0 | P46: =P45+O46+Q46 -> 9933226.3 | R46: =R45+O46 -> 9772129.7 | T46: Ties to 2018 Q1 CAS
B47: Capital Call | C47: CC#25 | D47: 43266 | E47: 43272 | F47: =YEAR(E47) -> 2018 | I47: -16347.93 | J47: -8209.96 | L47: =SUM(H47:K47) -> -24557.89 | M47: =M46+IF(L47<0,L47,0) -> -8400067.1 | N47: =M47+$C$7 -> 1599932.9 | O47: =IF(L47>0,L47,0) -> 0 | P47: =P46+O47+Q47 -> 9933226.3 | R47: =R46+O47 -> 9772129.7
B48: Distribution | C48: DD#13 | D48: 43266 | E48: 43272 | F48: =YEAR(E48) -> 2018 | G48: Nano | H48: 664212.8 | L48: =SUM(H48:K48) -> 664212.8 | M48: =M47+IF(L48<0,L48,0) -> -8400067.1 | N48: =M48+$C$7 -> 1599932.9 | O48: =IF(L48>0,L48,0) -> 664212.8 | P48: =P47+O48+Q48 -> 10665295 | Q48: 67855.97 | R48: =R47+O48 -> 10436343 | T48: Ties to 2018 Q2 CAS
B49: Capital Call | C49: CC#26 | D49: 43370 | E49: 43378 | F49: =YEAR(E49) -> 2018 | I49: -13588.79 | J49: -12314.93 | L49: =SUM(H49:K49) -> -25903.72 | M49: =M48+IF(L49<0,L49,0) -> -8425970.8 | N49: =M49+$C$7 -> 1574029.2 | O49: =IF(L49>0,L49,0) -> 0 | P49: =P48+O49+Q49 -> 10665295 | R49: =R48+O49 -> 10436343
B50: Distribution | C50: DD#14 | D50: 43370 | E50: 43378 | F50: =YEAR(E50) -> 2018 | G50: Meituan | H50: 1362852.7 | L50: =SUM(H50:K50) -> 1362852.7 | M50: =M49+IF(L50<0,L50,0) -> -8425970.8 | N50: =M50+$C$7 -> 1574029.2 | O50: =IF(L50>0,L50,0) -> 1362852.7 | P50: =P49+O50+Q50 -> 13019867 | Q50: 991719.48 | R50: =R49+O50 -> 11799195 | T50: Ties to 2018 Q3,Q4 CAS
B51: Capital Call | C51: CC#27 | D51: 43545 | E51: 43559 | F51: =YEAR(E51) -> 2019 | I51: -26734.46 | L51: =SUM(H51:K51) -> -26734.46 | M51: =M50+IF(L51<0,L51,0) -> -8452705.3 | N51: =M51+$C$7 -> 1547294.7 | O51: =IF(L51>0,L51,0) -> 0 | P51: =P50+O51+Q51 -> 13019867 | R51: =R50+O51 -> 11799195 | T51: Ties to 2019 Q1,Q2,Q3 CAS
B52: Capital Call | C52: CC#28 | D52: 43769 | E52: 43784 | F52: =YEAR(E52) -> 2019 | I52: -27177.58 | L52: =SUM(H52:K52) -> -27177.58 | M52: =M51+IF(L52<0,L52,0) -> -8479882.9 | N52: =M52+$C$7 -> 1520117.1 | O52: =IF(L52>0,L52,0) -> 0 | P52: =P51+O52+Q52 -> 13019867 | R52: =R51+O52 -> 11799195 | T52: Ties to 2019 Q4 CAS
B53: Capital Call | C53: CC#29 | D53: 43910 | E53: 43924 | F53: =YEAR(E53) -> 2020 | I53: -26734.46 | L53: =SUM(H53:K53) -> -26734.46 | M53: =M52+IF(L53<0,L53,0) -> -8506617.3 | N53: =M53+$C$7 -> 1493382.7 | O53: =IF(L53>0,L53,0) -> 0 | P53: =P52+O53+Q53 -> 13019867 | R53: =R52+O53 -> 11799195 | T53: Ties to 2020 Q1,Q2 CAS
B54: Capital Call | C54: CC#30 | D54: 44069 | E54: 44076 | F54: =YEAR(E54) -> 2020 | I54: -23369.96 | J54: -8209.96 | L54: =SUM(H54:K54) -> -31579.92 | M54: =M53+IF(L54<0,L54,0) -> -8538197.2 | N54: =M54+$C$7 -> 1461802.8 | O54: =IF(L54>0,L54,0) -> 0 | P54: =P53+O54+Q54 -> 13019867 | R54: =R53+O54 -> 11799195
B55: Distribution | C55: DD#15 | D55: 44069 | E55: 44076 | F55: =YEAR(E55) -> 2020 | G55: New Hope Diary | H55: 1551192.4 | L55: =SUM(H55:K55) -> 1551192.4 | M55: =M54+IF(L55<0,L55,0) -> -8538197.2 | N55: =M55+$C$7 -> 1461802.8 | O55: =IF(L55>0,L55,0) -> 1551192.4 | P55: =P54+O55+Q55 -> 14685845 | Q55: 114785.27 | R55: =R54+O55 -> 13350388 | T55: Ties to 2020 Q3,Q4 CAS
B56: Capital Call | C56: CC#31 | D56: 44201 | E56: 44208 | F56: =YEAR(E56) -> 2021 | I56: -14249.34 | J56: -8209.96 | L56: =SUM(H56:K56) -> -22459.3 | M56: =M55+L56 -> -8560656.5 | N56: =M56+$C$7 -> 1439343.5 | O56: =IF(L56>0,L56,0) -> 0 | P56: =P55+O56+Q56 -> 14685845 | Q56: 0 | R56: =R55+O56 -> 13350388
B57: Distribution | C57: DD#16 | D57: 44201 | E57: 44208 | F57: =YEAR(E57) -> 2021 | G57: Ningxia Harmony | H57: 1198653.6 | L57: =SUM(H57:K57) -> 1198653.6 | M57: =M56+IF(L57<0,L57,0) -> -8560656.5 | N57: =M57+$C$7 -> 1439343.5 | O57: =IF(L57>0,L57,0) -> 1198653.6 | P57: =P56+O57+Q57 -> 15999977 | Q57: 115478.95 | R57: =R56+O57 -> 14549041 | T57: Ties to 2021 Q1 CAS
B58: Capital Call | C58: CC#32 | D58: 44365 | E58: 44372 | F58: 2021 | I58: -4469.81 | L58: =SUM(H58:K58) -> -4469.81 | M58: =M57+IF(L58<0,L58,0) -> -8565126.3 | N58: =M58+$C$7 -> 1434873.7 | O58: =IF(L58>0,L58,0) -> 0 | P58: =P57+O58+Q58 -> 15999977 | R58: =R57+O58 -> 14549041
B59: Distribution | C59: DD#17 | D59: 44329 | E59: 44334 | F59: 2021 | H59: 4445495.2 | L59: =SUM(H59:K59) -> 4445495.2 | M59: =M58+IF(L59<0,L59,0) -> -8565126.3 | N59: =M59+$C$7 -> 1434873.7 | O59: =IF(L59>0,L59,0) -> 4445495.2 | P59: =P58+O59+Q59 -> 21149770 | Q59: 704297.82 | R59: =R58+O59 -> 18994536
B60: Distribution | C60: DD#18 | D60: 44365 | E60: 44372 | F60: 2021 | H60: =511734.62 -> 511734.62 | L60: =SUM(H60:K60) -> 511734.62 | M60: =M59+IF(L60<0,L60,0) -> -8565126.3 | N60: =M60+$C$7 -> 1434873.7 | O60: =IF(L60>0,L60,0) -> 511734.62 | P60: =P59+O60+Q60 -> 21763014 | Q60: 101508.52 | R60: =R59+O60 -> 19506271 | T60: Ties to 2021 Q2,Q3 CAS
B61: Capital Call | C61: CC#33 | E61: 44571 | F61: =YEAR(E61) -> 2022 | I61: -4396.94 | L61: =SUM(H61:K61) -> -4396.94 | M61: =M60+IF(L61<0,L61,0) -> -8569523.3 | N61: =M61+$C$7 -> 1430476.7 | O61: =IF(L61>0,L61,0) -> 0 | P61: =P60+O61+Q61 -> 21763014 | R61: =R60+O61 -> 19506271
B62: Distribution | C62: DD#19 | E62: 44571 | F62: =YEAR(E62) -> 2022 | H62: 198397.62 | L62: =SUM(H62:K62) -> 198397.62 | M62: =M61+IF(L62<0,L62,0) -> -8569523.3 | N62: =M62+$C$7 -> 1430476.7 | O62: =IF(L62>0,L62,0) -> 198397.62 | P62: =P61+O62+Q62 -> 22000266 | Q62: 38854.77 | R62: =R61+O62 -> 19704669
B63: Capital Call | C63: CC#34 | E63: 44965 | F63: =YEAR(E63) -> 2023 | I63: -753.07 | L63: =SUM(H63:K63) -> -753.07 | M63: =M62+IF(L63<0,L63,0) -> -8570276.4 | N63: =M63+$C$7 -> 1429723.6 | O63: =IF(L63>0,L63,0) -> 0 | P63: =P62+O63+Q63 -> 22000266 | R63: =R62+O63 -> 19704669
B64: Distribution | C64: DD#20 | E64: 44965 | F64: =YEAR(E64) -> 2023 | H64: 342367.44 | L64: =SUM(H64:K64) -> 342367.44 | M64: =M63+IF(L64<0,L64,0) -> -8570276.4 | N64: =M64+$C$7 -> 1429723.6 | O64: =IF(L64>0,L64,0) -> 342367.44 | P64: =P63+O64+Q64 -> 22372892 | Q64: 30258.12 | R64: =R63+O64 -> 20047036 | T64: Ties to 2023 Q2 CAS
B65: Distribution | C65: DD#21 | E65: 45149 | F65: =YEAR(E65) -> 2023 | H65: 160428.38 | L65: =SUM(H65:K65) -> 160428.38 | M65: =M64+IF(L65<0,L65,0) -> -8570276.4 | N65: =M65+$C$7 -> 1429723.6 | O65: =IF(L65>0,L65,0) -> 160428.38 | P65: =P64+O65+Q65 -> 22538818 | Q65: 5498.58 | R65: =R64+O65 -> 20207464 | T65: Ties to 2024 Q4 CAS
B67: Capital Account Balance | E67: =C3 -> 45657 | L67: 249627

Sheet BOYU Capital Fund I
A1: Fund Overview | D1: Fund Performance Indicator | E1: 45657 | H1: Key Fee Term
A2: Fund Full Name | B2: BOYU Capital Fund I, L.P. | D2: Fair Value of Porfolio Companies (US$/mil) | E2: =W44 -> 0.3 | H2: Management fees - investment period | I2: 2% of commitment
A3: Initial Closing Date | B3: 40705 | D3: Total Net Asset Value (US$/mil) | E3: 2.403843 | H3: Management fees - after investment period | I3: 2% of invested capital
A4: Final Closing Date | B4: 40799 | D4: Fund Gross Multiple (x) | E4: 4.3 | H4: Preferred Return | I4: 0.08
A5: Vintage Year | B5: 2011 | D5: Fund Net Multiple (x) | E5: n.a.* | H5: Carried Interest | I5: 0.2
A6: General Partner ("GP") | B6: BOYU Capital General Partner I, L.P. | D6: Fund Gross IRR (%) | E6: n.a.* | H6: LP Reporting Timeline
A7: Investment Manager | B7: BOYU Capital Management Ltd. | D7: Fund Net IRR (%) | E7: n.a.* | H7: Quarterly report (after period end) | I7: 60 days
A8: Fund Domicile | B8: Cayman Islands | D8: Fund Distribution to Paid-in Capital (DPI %) | E8: =3699.5/1010.3 -> 3.6617836 | H8: Annual report (after period end) | I8: 90 days
A9: Fund Term | B9: Jun 2021 (10 years from Initial Closing Date) | D9: CCG Performance Indicator
A10: Extensions | B10: 1 + 1 year | D10: Commitment (US$/mil) | E10: 30
A11: Investment Period | B11: Jun 2016 (5 years from Initial Closing Date) | D11: Ownership % | E11: =E10/1030.133 -> 0.029122453
A12: Fund Currency | B12: USD | D12: Cumulative Contribution (US$/mil) | E12: =-'BOYU Capital Fund I CF'!M2/10^6 -> 29.454452
A13: Fund Size / Total Commitment | B13: US$1.0301b | D13: Remaining Unfunded Commitment (US$/mil) | E13: =E10-E12+2.076182 -> 2.62173
A14: Minimum Commitment | B14: US$10mil | D14: Cumulative Distribution (US$/mil) | E14: ='BOYU Capital Fund I CF'!M3/10^6 -> 92.038826
A15: GP commitment | B15: US$10.2mil | D15: Capital Account Balance (US$/mil) | E15: ='BOYU Capital Fund I CF'!M4/10^6 -> 0.051248
A16: Financial Year End | B16: 44196 | D16: Call-up Percentage (%) | E16: =E12/E10 -> 0.98181507
A17: Accounting Principles | B17: US GAAP | D17: Distribution to Paid-in Capital (DPI %) | E17: =E14/E12 -> 3.1247849
A18: Portfolio | D18: Multiple (x) | E18: =(E14+E15)/E12 -> 3.1265248
A19: Number of Portfolio Company | B19: 11 | D19: IRR (%) | E19: ='BOYU Capital Fund I CF'!M5 -> 0.3363551
K30: Q4 2023 | T30: Q4 2024 | AC30: Q1 2025
A31: Portfolio | B31: Company Description | C31: Sector | D31: Status (Unrealized / Partial Realized / Realized / Write-off) | E31: First Investment Date | F31: IPO Date | G31: Ticker | H31: Exit Date | I31: Exit Method | J31: Holding Period (years) | K31: Investment Cost (USD/mil) | L31: % of Ownership | M31: Realized Value (USD/mil) | N31: Unrealized Value (USD/mil) | O31: Total Value (USD/mil) | P31: MOIC | Q31: IRR * | R31: Total Value - $ change YoY | S31: Total Value - % change YoY | T31: Investment Cost (USD/mil) | U31: % of Ownership | V31: Realized Value (USD/mil) | W31: Unrealized Value (USD/mil) | X31: Total Value (USD/mil) | Y31: MOIC | Z31: IRR * | AA31: Total Value - $ change YoY | AB31: Total Value - % change YoY | AC31: Investment Cost (USD/mil) | AD31: % of Ownership | AE31: Realized Value (USD/mil) | AF31: Unrealized Value (USD/mil) | AG31: Total Value (USD/mil) | AH31: MOIC | AI31: IRR * | AJ31: Total Value - $ change YoY | AK31: Total Value - % change YoY | AL31: Total Value - $ change QoQ | AM31: Total Value - % change QoQ
A32: Uni-Champion (Sunrise) | B32: Holding company of Sunrise Duty Free, leading private operator of duty free shops in China's 3 largest airports | C32: Consumer | D32: Realized | E32: 40756 | J32: - | K32: 80.7 | L32: - | M32: 941 | N32: 0 | O32: =M32+N32 -> 941 | P32: =O32/K32 -> 11.660471 | Q32: 0 | R32: 0 | S32: - | T32: 80.7 | U32: - | V32: 941 | W32: 0 | X32: =V32+W32 -> 941 | Y32: =X32/T32 -> 11.660471 | Z32: 0 | AA32: =X32-O32 -> 0 | AB32: =IFERROR(X32/O32-1,0) -> 0
A33: China Cinda Asset Management (Cinda) | B33: Non-banking financial institution regulated by China Banking Regulatory Commission. Actively engaged in acquisition and disposal of non-performing assets from China's banking sector. Also established a comprehensive multi-licensed financial services platform. | C33: Financials | D33: Realized | E33: 40969 | J33: - | K33: 76.5 | L33: - | M33: 145.7 | N33: 0 | O33: =N33+M33 -> 145.7 | P33: =O33/K33 -> 1.9045752 | Q33: 0 | R33: 0 | S33: - | T33: 76.5 | U33: - | V33: 145.7 | W33: 0 | X33: =W33+V33 -> 145.7 | Y33: =X33/T33 -> 1.9045752 | Z33: 0 | AA33: =X33-O33 -> 0 | AB33: =IFERROR(X33/O33-1,0) -> 0
A34: Far East Horizon | B34: One of the largest and best managed financial leasing companies in China, providing tailor-made financial leasing services, advisory, trading and brokerage services to SME customers across various industries including healthcare, shipping, construction and education. | C34: Financials | D34: Realized | E34: 41061 | J34: - | K34: 35.4 | L34: - | M34: 63.8 | N34: 0 | O34: =N34+M34 -> 63.8 | P34: =O34/K34 -> 1.8022599 | Q34: 0 | R34: 0 | S34: - | T34: 35.4 | U34: - | V34: 63.8 | W34: 0 | X34: =W34+V34 -> 63.8 | Y34: =X34/T34 -> 1.8022599 | Z34: 0 | AA34: =X34-O34 -> 0 | AB34: =IFERROR(X34/O34-1,0) -> 0
A35: SH SMG-CJ (OCJ) | B35: Largest home shopping company in China, marketing its products under "Oriental Shopping" through various media platforms. | C35: Technology | D35: Realized | E35: 41091 | J35: - | K35: 78.3 | L35: - | M35: 218.8 | N35: 0 | O35: =N35+M35 -> 218.8 | P35: =O35/K35 -> 2.7943806 | Q35: 0 | R35: 0 | S35: - | T35: 78.3 | U35: - | V35: 218.8 | W35: 0 | X35: =W35+V35 -> 218.8 | Y35: =X35/T35 -> 2.7943806 | Z35: 0 | AA35: =X35-O35 -> 0 | AB35: =IFERROR(X35/O35-1,0) -> 0
A36: Alibaba Group | B36: Largest internet asset in China and ecommerce online platform, including alibaba.com, Taobao Group. IPO in Sept 2014. One of the top valued public companies in the world. | C36: Technology | D36: Realized | E36: 41153 | J36: - | K36: 163.1 | L36: - | M36: 1181.6 | N36: 0 | O36: =N36+M36 -> 1181.6 | P36: =O36/K36 -> 7.2446352 | Q36: 0 | R36: 0 | S36: - | T36: 163.1 | U36: - | V36: 1181.6 | W36: 0 | X36: =W36+V36 -> 1181.6 | Y36: =X36/T36 -> 7.2446352 | Z36: 0 | AA36: =X36-O36 -> 0 | AB36: =IFERROR(X36/O36-1,0) -> 0
A37: Marisfrolg | B37: Leading high-end multi-brand apparel company in China, based in Shenzhen. | C37: Consumer | D37: Realized | E37: 41244 | J37: - | K37: 44 | L37: - | M37: 76.2 | N37: 0 | O37: =N37+M37 -> 76.2 | P37: =O37/K37 -> 1.7318182 | Q37: 0 | R37: 0 | S37: - | T37: 44 | U37: - | V37: 76.2 | W37: 0 | X37: =W37+V37 -> 76.2 | Y37: =X37/T37 -> 1.7318182 | Z37: 0 | AA37: =X37-O37 -> 0 | AB37: =IFERROR(X37/O37-1,0) -> 0
A38: Stelux Holdings | B38: Mid-end watch and optical products targeting middle income consumers in Greater China and SE Asia. Owns City Chain and Optical88 retail chains and has own brands including Solvil et Titus, CYMA, Pronto, Ellesse and Universal Geneve. | C38: Consumer | D38: Realized | E38: 41244 | J38: - | K38: 48.5 | L38: - | M38: 69 | N38: 0 | O38: =N38+M38 -> 69 | P38: =O38/K38 -> 1.4226804 | Q38: 0 | R38: 0 | S38: - | T38: 48.5 | U38: - | V38: 69 | W38: 0 | X38: =W38+V38 -> 69 | Y38: =X38/T38 -> 1.4226804 | Z38: 0 | AA38: =X38-O38 -> 0 | AB38: =IFERROR(X38/O38-1,0) -> 0
A39: Multi Concepts Link (MCL) | B39: China-style dessert chain with 20-year exclusive franchise right expiring in 2028 for China and 2030 for Singapore. Operates under the brand "Honeymoon Dessert". | C39: Consumer | D39: Realized | E39: 41548 | J39: - | K39: 49.4 | L39: - | M39: 7.5 | N39: 0 | O39: =N39+M39 -> 7.5 | P39: =O39/K39 -> 0.15182186 | Q39: 0 | R39: 0 | S39: - | T39: 49.4 | U39: - | V39: 7.5 | W39: 0 | X39: =W39+V39 -> 7.5 | Y39: =X39/T39 -> 0.15182186 | Z39: 0 | AA39: =X39-O39 -> 0 | AB39: =IFERROR(X39/O39-1,0) -> 0
A40: Meituan Dianping | B40: One of largest online to offline platforms in China for local consumer products and retail services, monetizing on advertising solutions. | C40: Technology | D40: Realized | E40: 41730 | J40: - | K40: 158.2 | L40: - | M40: 738.8 | N40: 0 | O40: =N40+M40 -> 738.8 | P40: =O40/K40 -> 4.6700379 | Q40: 0 | R40: 0 | S40: - | T40: 158.2 | U40: - | V40: 738.8 | W40: 0 | X40: =W40+V40 -> 738.8 | Y40: =X40/T40 -> 4.6700379 | Z40: 0 | AA40: =X40-O40 -> 0 | AB40: =IFERROR(X40/O40-1,0) -> 0
A41: Ping An Insurance | B41: Leading integrated financial services conglomerate in China in life insurance, P&C insurance, banking, trust, securities and asset management. Largest non-state owned and best-run insurance player in China. | C41: Financials | D41: Realized | E41: 41760 | J41: - | K41: 70.8 | L41: - | M41: 147 | N41: 0 | O41: =N41+M41 -> 147 | P41: =O41/K41 -> 2.0762712 | Q41: 0 | R41: 0 | S41: - | T41: 70.8 | U41: - | V41: 147 | W41: 0 | X41: =W41+V41 -> 147 | Y41: =X41/T41 -> 2.0762712 | Z41: 0 | AA41: =X41-O41 -> 0 | AB41: =IFERROR(X41/O41-1,0) -> 0
A42: COFCO Meat | B42: China's largest food processor, manufacturer and trader. COFCO Group's core subsidiary primarily for feedstuff producing, breeding, slaughtering, processing and distribution. Listed on HKEX in 2016. | C42: Consumer | D42: Partial Realized | E42: 41760 | J42: - | K42: 52.1 | L42: - | M42: 114 | N42: 0.3 | O42: =N42+M42 -> 114.3 | P42: =O42/K42 -> 2.193858 | Q42: 0 | R42: 0 | S42: - | T42: 52.1 | U42: - | V42: 114 | W42: 0.3 | X42: =W42+V42 -> 114.3 | Y42: =X42/T42 -> 2.193858 | Z42: 0 | AA42: =X42-O42 -> 0 | AB42: =IFERROR(X42/O42-1,0) -> 0
A44: Grand Total | K44: =SUM(K32:K42) -> 857 | M44: =SUM(M32:M42) -> 3703.4 | N44: =SUM(N32:N42) -> 0.3 | O44: =SUM(O32:O42) -> 3703.7 | P44: =O44/K44 -> 4.3217036 | Q44: - | R44: - | S44: - | T44: =SUM(T32:T42) -> 857 | V44: =SUM(V32:V42) -> 3703.4 | W44: =SUM(W32:W42) -> 0.3 | X44: =SUM(X32:X42) -> 3703.7 | Y44: =X44/T44 -> 4.3217036 | Z44: - | AA44: =X44-O44 -> 0 | AB44: =IFERROR(X44/O44-1,0) -> 0
A46: Sub-Total - Unrealized & Partial Realized | K46: =SUMIF($D$32:$D$42,"Unrealized",K$32:K$42)+SUMIF($D$32:$D$42,"Partial Realized",K$32:K$42) -> 52.1 | M46: =SUMIF($D$32:$D$42,"Unrealized",M$32:M$42)+SUMIF($D$32:$D$42,"Partial Realized",M$32:M$42) -> 114 | N46: =SUMIF($D$32:$D$42,"Unrealized",N$32:N$42)+SUMIF($D$32:$D$42,"Partial Realized",N$32:N$42) -> 0.3 | O46: =SUMIF($D$32:$D$42,"Unrealized",O$32:O$42)+SUMIF($D$32:$D$42,"Partial Realized",O$32:O$42) -> 114.3 | P46: =O46/K46 -> 2.193858 | R46: - | S46: - | T46: =SUMIF($D$32:$D$42,"Unrealized",T$32:T$42)+SUMIF($D$32:$D$42,"Partial Realized",T$32:T$42) -> 52.1 | V46: =SUMIF($D$32:$D$42,"Unrealized",V$32:V$42)+SUMIF($D$32:$D$42,"Partial Realized",V$32:V$42) -> 114 | W46: =SUMIF($D$32:$D$42,"Unrealized",W$32:W$42)+SUMIF($D$32:$D$42,"Partial Realized",W$32:W$42) -> 0.3 | X46: =SUMIF($D$32:$D$42,"Unrealized",X$32:X$42)+SUMIF($D$32:$D$42,"Partial Realized",X$32:X$42) -> 114.3 | Y46: =X46/T46 -> 2.193858 | AA46: =X46-O46 -> 0 | AB46: =IFERROR(X46/O46-1,0) -> 0
A47: Sub-Total - Realized | K47: =SUMIF($D$32:$D$42,"Realized",K$32:K$42)+SUMIF($D$32:$D$42,"Write-off",K$32:K$42) -> 804.9 | M47: =SUMIF($D$32:$D$42,"Realized",M$32:M$42)+SUMIF($D$32:$D$42,"Write-off",M$32:M$42) -> 3589.4 | N47: =SUMIF($D$32:$D$42,"Realized",N$32:N$42)+SUMIF($D$32:$D$42,"Write-off",N$32:N$42) -> 0 | O47: =SUMIF($D$32:$D$42,"Realized",O$32:O$42)+SUMIF($D$32:$D$42,"Write-off",O$32:O$42) -> 3589.4 | P47: =O47/K47 -> 4.459436 | R47: - | S47: - | T47: =SUMIF($D$32:$D$42,"Realized",T$32:T$42)+SUMIF($D$32:$D$42,"Write-off",T$32:T$42) -> 804.9 | V47: =SUMIF($D$32:$D$42,"Realized",V$32:V$42)+SUMIF($D$32:$D$42,"Write-off",V$32:V$42) -> 3589.4 | W47: =SUMIF($D$32:$D$42,"Realized",W$32:W$42)+SUMIF($D$32:$D$42,"Write-off",W$32:W$42) -> 0 | X47: =SUMIF($D$32:$D$42,"Realized",X$32:X$42)+SUMIF($D$32:$D$42,"Write-off",X$32:X$42) -> 3589.4 | Y47: =X47/T47 -> 4.459436 | AA47: =X47-O47 -> 0 | AB47: =IFERROR(X47/O47-1,0) -> 0
A50: Commentary / Q&A - Tracker
K51: Q4 2023 | T51: Q4 2024 | AC51: Q1 2025
A52: Portfolio | B52: Company Description | C52: Sector | D52: Status (Unrealized / Partial Realized / Realized / Write-off) | E52: First Investment Date | F52: IPO Date | G52: Ticker | H52: Exit Date | I52: Exit Method | J52: Holding Period (years) | K52: Question | O52: Response / Commentary | T52: Question | X52: Response / Commentary | AC52: Question | AG52: Response / Commentary

Sheet BOYU Capital Fund I CF
B1: Fund Investment Cashflow | L1: =C3 -> 45657
L2: Cummulative Contribution | M2: =M98 -> -29454452
B3: Date: | C3: ='BOYU Capital Fund I'!E1 -> 45657 | L3: Cummulative Distribution | M3: =P98 -> 92038826
L4: Capital Account Balance | M4: =L100 -> 51248
B5: Fund: | C5: Boyu Capital Fund I | L5: IRR | M5: =XIRR(L10:L100,E10:E100,0) -> 0.3363551
B6: Curr: | C6: USD
B7: Commitment | C7: 30000000
B9: Transaction type (Call/Distribution) | C9: No. | D9: Document date | E9: Trans. Date | F9: Year | G9: Project | H9: Portfolio Investment | I9: Mgmt Fee | J9: Partnership Exp | K9: Org Fee | L9: Trans. Amt | M9: Cum. Capital called | N9: Remaining callable capital | O9: Distributions (after Carried) | P9: Cum. Dist | R9: Carried Interest
B10: Capital Call | C10: CC#1 | D10: 40754 | E10: 40767 | F10: =YEAR(E10) -> 2011 | G10: Sunrise Duty Free | H10: -2608318.6 | I10: -333149.17 | J10: -35864.38 | K10: =-48905.97 -> -48905.97 | L10: =SUM(H10:K10) -> -3026238.1 | M10: =L10 -> -3026238.1 | N10: =$C$7+M10 -> 26973762 | O10: =SUMIF(H10:K10,">0", H10:K10) -> 0 | P10: =O10 -> 0
B11: Partial refund of capital call #1 | D11: 40819 | E11: 40819 | F11: =YEAR(E11) -> 2011 | L11: 287574.3 | M11: =M10+L11 -> -2738663.8 | N11: =$C$7+M11 -> 27261336 | O11: =SUMIF(H11:K11,">0", H11:K11) -> 0 | P11: =O11+P10 -> 0
B12: Capital Call | C12: CC#2 | D12: 40926 | E12: 40942 | F12: =YEAR(E12) -> 2012 | G12: Cinda | H12: -2195507.2 | I12: -300000 | J12: -65518.61 | L12: =SUM(H12:K12) -> -2561025.8 | M12: =M11+IF(L12<0,L12,0) -> -5299689.6 | N12: =$C$7+M12 -> 24700310 | O12: =SUMIF(H12:K12,">0", H12:K12) -> 0 | P12: =P11+O12 -> 0
B13: Distribution | C13: DD#1 | D13: 40926 | E13: 40942 | F13: =YEAR(E13) -> 2012 | G13: Sunrise Duty Free dividend | H13: 238804.12 | L13: =SUM(H13:K13) -> 238804.12 | M13: =M12+IF(L13<0,L13,0) -> -5299689.6 | N13: =$C$7+M13 -> 24700310 | O13: =SUMIF(H13:K13,">0", H13:K13) -> 238804.12 | P13: =P12+O13 -> 238804.12
B14: Capital Call | C14: CC#3 | D14: 41036 | E14: 41047 | F14: =YEAR(E14) -> 2012 | G14: SMJ-CJ Home | H14: -2262813.6 | J14: -17759.41 | L14: =SUM(H14:K14) -> -2280573 | M14: =M13+IF(L14<0,L14,0) -> -7580262.6 | N14: =$C$7+M14 -> 22419737 | O14: =SUMIF(H14:K14,">0", H14:K14) -> 0 | P14: =P13+O14 -> 238804.12
B15: Capital Call | C15: CC#4 | D15: 41094 | E15: 41107 | F15: =YEAR(E15) -> 2012 | I15: -300000 | L15: =SUM(H15:K15) -> -300000 | M15: =M14+IF(L15<0,L15,0) -> -7880262.6 | N15: =$C$7+M15 -> 22119737 | O15: =SUMIF(H15:K15,">0", H15:K15) -> 0 | P15: =P14+O15 -> 238804.12
B16: Capital Call | C16: CC#5 | D16: 41148 | E16: 41159 | F16: =YEAR(E16) -> 2012 | G16: Alibaba & Far East Horizon | H16: =-4744746.56-735496.43 -> -5480243 | J16: -11061.35 | L16: =SUM(H16:K16) -> -5491304.3 | M16: =M15+IF(L16<0,L16,0) -> -13371567 | N16: =$C$7+M16 -> 16628433 | O16: =SUMIF(H16:K16,">0", H16:K16) -> 0 | P16: =P15+O16 -> 238804.12
B17: Distribution | C17: DD#2 | D17: 41148 | E17: 41159 | F17: =YEAR(E17) -> 2012 | G17: Far East Horizon Dividend | H17: 6565.12 | L17: =SUM(H17:K17) -> 6565.12 | M17: =M16+IF(L17<0,L17,0) -> -13371567 | N17: =$C$7+M17 -> 16628433 | O17: =SUMIF(H17:K17,">0", H17:K17) -> 6565.12 | P17: =P16+O17 -> 245369.24
B18: Capital Call | C18: CC#6 | D18: 41242 | E18: 41255 | F18: =YEAR(E18) -> 2012 | G18: Far East Horizon, Marisflog, Stelux | H18: =-83662.29-1277625.49-1395122.14 -> -2756409.9 | J18: -47598.93 | K18: 2477.45 | L18: =SUM(H18:K18) -> -2801531.4 | M18: =M17+IF(L18<0,L18,0) -> -16173098 | N18: =$C$7+M18 -> 13826902 | P18: =P17+O18 -> 245369.24
B19: Distribution | C19: DD#3 | D19: 41242 | E19: 41255 | F19: =YEAR(E19) -> 2012 | G19: Sunrise Duty Free dividend | H19: 1164898.1 | L19: =SUM(H19:K19) -> 1164898.1 | M19: =M18+IF(L19<0,L19,0) -> -16173098 | N19: =$C$7+M19 -> 13826902 | O19: =SUMIF(H19:K19,">0", H19:K19) -> 1164898.1 | P19: =P18+O19 -> 1410267.4
B20: Capital Call | C20: CC#7 | D20: 41282 | E20: 41295 | F20: =YEAR(E20) -> 2013 | I20: -300000 | J20: -5824.49 | L20: =SUM(H20:K20) -> -305824.49 | M20: =M19+IF(L20<0,L20,0) -> -16478923 | N20: =$C$7+M20 -> 13521077 | O20: =SUMIF(H20:K20,">0", H20:K20) -> 0 | P20: =P19+O20 -> 1410267.4
B21: Capital Call | C21: CC#8 | D21: 41457 | E21: 41470 | F21: =YEAR(E21) -> 2013 | I21: -300000 | L21: =SUM(H21:K21) -> -300000 | M21: =M20+IF(L21<0,L21,0) -> -16778923 | N21: =$C$7+M21 -> 13221077 | O21: =SUMIF(H21:K21,">0", H21:K21) -> 0 | P21: =P20+O21 -> 1410267.4
B22: Distribution | C22: DD#4 | D22: 41457 | E22: 41470 | F22: =YEAR(E22) -> 2013 | G22: Stelux CB interest | H22: 25719.2 | L22: =SUM(H22:K22) -> 25719.2 | M22: =M21+IF(L22<0,L22,0) -> -16778923 | N22: =$C$7+M22 -> 13221077 | O22: =SUMIF(H22:K22,">0", H22:K22) -> 25719.2 | P22: =P21+O22 -> 1435986.6
B23: Capital Call | C23: CC#9 | D23: 41547 | E23: 41562 | F23: =YEAR(E23) -> 2013 | G23: Far East & MCL | H23: =-(208381.07+1431996.96) -> -1640378 | J23: -65504.48 | L23: =SUM(H23:K23) -> -1705882.5 | M23: =M22+IF(L23<0,L23,0) -> -18484805 | N23: =$C$7+M23 -> 11515195 | O23: =SUMIF(H23:K23,">0", H23:K23) -> 0 | P23: =P22+O23 -> 1435986.6
B24: Distribution | C24: DD#5 | D24: 41547 | E24: 41562 | F24: =YEAR(E24) -> 2013 | G24: Sunrise dvd, Far East dvd, Marisfrog dvd, Stelux CB interest | H24: 1227958.7 | L24: =SUM(H24:K24) -> 1227958.7 | M24: =M23+IF(L24<0,L24,0) -> -18484805 | N24: =$C$7+M24 -> 11515195 | O24: =SUMIF(H24:K24,">0", H24:K24) -> 1227958.7 | P24: =P23+O24 -> 2663945.3
B25: Distribution | C25: DD#6 | D25: 41570 | E25: 41572 | F25: =YEAR(E25) -> 2013 | G25: Cinda & CJ dvd | H25: 165561.08 | L25: =SUM(H25:K25) -> 165561.08 | M25: =M24+IF(L25<0,L25,0) -> -18484805 | N25: =$C$7+M25 -> 11515195 | O25: =SUMIF(H25:K25,">0", H25:K25) -> 165561.08 | P25: =P24+O25 -> 2829506.3
B26: Capital Call | C26: CC#10 | D26: 41641 | E26: 41654 | F26: =YEAR(E26) -> 2014 | I26: -300000 | L26: =SUM(H26:K26) -> -300000 | M26: =M25+IF(L26<0,L26,0) -> -18784805 | N26: =$C$7+M26 -> 11215195 | O26: =SUMIF(H26:K26,">0", H26:K26) -> 0 | P26: =P25+O26 -> 2829506.3
B27: Capital Call | C27: CC#11 | D27: 41727 | E27: 41740 | F27: =YEAR(E27) -> 2014 | G27: Meituan | H27: -1977545.8 | J27: -16764.57 | L27: =SUM(H27:K27) -> -1994310.3 | M27: =M26+IF(L27<0,L27,0) -> -20779116 | N27: =$C$7+M27 -> 9220884.3 | O27: =SUMIF(H27:K27,">0", H27:K27) -> 0 | P27: =P26+O27 -> 2829506.3
B28: Distribution | C28: DD#7 | D28: 41727 | E28: 41740 | F28: =YEAR(E28) -> 2014 | G28: Marisfrolg dvd, Stelux CB interest | H28: 38667.55 | L28: =SUM(H28:K28) -> 38667.55 | M28: =M27+IF(L28<0,L28,0) -> -20779116 | N28: =$C$7+M28 -> 9220884.3 | O28: =SUMIF(H28:K28,">0", H28:K28) -> 38667.55 | P28: =P27+O28 -> 2868173.9
B29: Capital Call | C29: CC#12 | D29: 41744 | E29: 41759 | F29: =YEAR(E29) -> 2014 | G29: Ping An Insurance | H29: -2035705.9 | L29: =SUM(H29:K29) -> -2035705.9 | M29: =M28+IF(L29<0,L29,0) -> -22814822 | N29: =$C$7+M29 -> 7185178.4 | O29: =SUMIF(H29:K29,">0", H29:K29) -> 0 | P29: =P28+O29 -> 2868173.9
B30: Capital Call | C30: CC#13 | D30: 41771 | E30: 41782 | F30: =YEAR(E30) -> 2014 | G30: COFCO Meat | H30: -1523767.2 | J30: -12909.12 | L30: =SUM(H30:K30) -> -1536676.4 | M30: =M29+IF(L30<0,L30,0) -> -24351498 | N30: =$C$7+M30 -> 5648502.1 | O30: =SUMIF(H30:K30,">0", H30:K30) -> 0 | P30: =P29+O30 -> 2868173.9
B31: Capital Call | C31: CC#14 | D31: 41822 | E31: 41835 | F31: =YEAR(E31) -> 2014 | G31: Ping An Insurance | H31: =-20594.08 -> -20594.08 | I31: -300000 | L31: =SUM(H31:K31) -> -320594.08 | M31: =M30+IF(L31<0,L31,0) -> -24672092 | N31: =$C$7+M31 -> 5327908 | O31: =SUMIF(H31:K31,">0", H31:K31) -> 0 | P31: =P30+O31 -> 2868173.9
B32: Distribution | C32: DD#8 | D32: 41822 | E32: 41835 | F32: =YEAR(E32) -> 2014 | G32: Ping An dvd, Marisfrolg dvd | H32: =52649.71 -> 52649.71 | L32: =SUM(H32:K32) -> 52649.71 | M32: =M31+IF(L32<0,L32,0) -> -24672092 | N32: =$C$7+M32 -> 5327908 | O32: =SUMIF(H32:K32,">0", H32:K32) -> 52649.71 | P32: =P31+O32 -> 2920823.6
B33: Distribution | C33: DD#9 | D33: 41920 | E33: 41927 | F33: =YEAR(E33) -> 2014 | G33: Alibaba sale, FEH/OCJ/Ping An dvd, Stelux CB interest | H33: 1897936.4 | L33: =SUM(H33:K33) -> 1897936.4 | M33: =M32+IF(L33<0,L33,0) -> -24672092 | N33: =$C$7+M33 -> 5327908 | O33: =SUMIF(H33:K33,">0", H33:K33) -> 1897936.4 | P33: =P32+O33 -> 4818760 | R33: 306789.19
B34: Capital Call | C34: CC#15 | D34: 41920 | E34: 41927 | F34: =YEAR(E34) -> 2014 | G34: Ping An Insurance | H34: -11739.16 | L34: =SUM(H34:K34) -> -11739.16 | M34: =M33+IF(L34<0,L34,0) -> -24683831 | N34: =$C$7+M34 -> 5316168.8 | O34: =SUMIF(H34:K34,">0", H34:K34) -> 0 | P34: =P33+O34 -> 4818760
B35: Distribution | C35: DD#10 | D35: 42010 | E35: 42017 | F35: =YEAR(E35) -> 2015 | G35: Sunrise/Cinda/Marisfrolg dvd | H35: 528174.09 | L35: =SUM(H35:K35) -> 528174.09 | M35: =M34+IF(L35<0,L35,0) -> -24683831 | N35: =$C$7+M35 -> 5316168.8 | O35: =SUMIF(H35:K35,">0", H35:K35) -> 528174.09 | P35: =P34+O35 -> 5346934.1 | R35: 22650.75
B36: Capital Call | C36: CC#16 | D36: 42010 | E36: 42017 | F36: =YEAR(E36) -> 2015 | I36: -300000 | J36: -27055.46 | L36: =SUM(H36:K36) -> -327055.46 | M36: =M35+IF(L36<0,L36,0) -> -25010887 | N36: =$C$7+M36 -> 4989113.4 | O36: =SUMIF(H36:K36,">0", H36:K36) -> 0 | P36: =P35+O36 -> 5346934.1
B37: Capital Call | C37: CC#17 | D37: 42032 | E37: 42045 | F37: =YEAR(E37) -> 2015 | G37: Meituan | H37: -2617351.6 | J37: -1163.26 | L37: =SUM(H37:K37) -> -2618514.8 | M37: =M36+IF(L37<0,L37,0) -> -27629401 | N37: =$C$7+M37 -> 2370598.6 | O37: =SUMIF(H37:K37,">0", H37:K37) -> 0 | P37: =P36+O37 -> 5346934.1
B38: Distribution | C38: DD#11 | D38: 42156 | E38: 42158 | F38: =YEAR(E38) -> 2015 | G38: Sunrise DVD, Sterlux CB interest | H38: 1076690.5 | L38: =SUM(H38:K38) -> 1076690.5 | M38: =M37+IF(L38<0,L38,0) -> -27629401 | N38: =$C$7+M38 -> 2370598.6 | O38: =SUMIF(H38:K38,">0", H38:K38) -> 1076690.5 | P38: =P37+O38 -> 6423624.6 | R38: 331095.14
B39: Distribution | C39: DD#12 | D39: 42165 | E39: 42167 | F39: =YEAR(E39) -> 2015 | G39: Cinda sale | H39: 3807147.9 | L39: =SUM(H39:K39) -> 3807147.9 | M39: =M38+IF(L39<0,L39,0) -> -27629401 | N39: =$C$7+M39 -> 2370598.6 | O39: =SUMIF(H39:K39,">0", H39:K39) -> 3807147.9 | P39: =P38+O39 -> 10230773 | R39: 354348.02
B40: Capital Call | C40: CC#18 | D40: 42188 | E40: 42201 | F40: =YEAR(E40) -> 2015 | I40: -300000 | J40: -16453.31 | L40: =SUM(H40:K40) -> -316453.31 | M40: =M39+IF(L40<0,L40,0) -> -27945855 | N40: =$C$7+M40 -> 2054145.2 | O40: =SUMIF(H40:K40,">0", H40:K40) -> 0 | P40: =P39+O40 -> 10230773
B41: Distribution | C41: DD#13 | D41: 42188 | E41: 42201 | F41: =YEAR(E41) -> 2015 | G41: Far East Horizon / OCJ dvd | H41: 218860 | L41: =SUM(H41:K41) -> 218860 | M41: =M40+IF(L41<0,L41,0) -> -27945855 | N41: =$C$7+M41 -> 2054145.2 | O41: =SUMIF(H41:K41,">0", H41:K41) -> 218860 | P41: =P40+O41 -> 10449633
B42: Distribution | C42: DD#14 | D42: 42213 | E42: 42215 | F42: =YEAR(E42) -> 2015 | G42: Ping An sale | H42: 2098541.1 | L42: =SUM(H42:K42) -> 2098541.1 | M42: =M41+IF(L42<0,L42,0) -> -27945855 | N42: =$C$7+M42 -> 2054145.2 | O42: =SUMIF(H42:K42,">0", H42:K42) -> 2098541.1 | P42: =P41+O42 -> 12548174
B43: Capital Call | C43: CC#19 | D43: 42213 | E43: 42215 | F43: =YEAR(E43) -> 2015 | J43: -43683.67 | L43: =SUM(H43:K43) -> -43683.67 | M43: =M42+IF(L43<0,L43,0) -> -27989538 | N43: =$C$7+M43 -> 2010461.6 | O43: =SUMIF(H43:K43,">0", H43:K43) -> 0 | P43: =P42+O43 -> 12548174
B44: Distribution | C44: DD#15 | D44: 42220 | E44: 42222 | F44: =YEAR(E44) -> 2015 | G44: OCJ sale | H44: 5239980.9 | L44: =SUM(H44:K44) -> 5239980.9 | M44: =M43+IF(L44<0,L44,0) -> -27989538 | N44: =$C$7+M44 -> 2010461.6 | O44: =SUMIF(H44:K44,">0", H44:K44) -> 5239980.9 | P44: =P43+O44 -> 17788155 | R44: 759580.58
B45: Distribution | C45: DD#16 | D45: 42284 | E45: 42286 | F45: =YEAR(E45) -> 2015 | G45: FEH sale, Sunrise dvd, Stelux CB interest | H45: 2592073.9 | L45: =SUM(H45:K45) -> 2592073.9 | M45: =M44+IF(L45<0,L45,0) -> -27989538 | N45: =$C$7+M45 -> 2010461.6 | O45: =SUMIF(H45:K45,">0", H45:K45) -> 2592073.9 | P45: =P44+O45 -> 20380228 | R45: =25102.26+534160.57 -> 559262.83
B46: Capital Call | C46: CC#20 | D46: 42284 | E46: 42286 | F46: =YEAR(E46) -> 2015 | K46: -3494.7 | L46: =SUM(H46:K46) -> -3494.7 | M46: =M45+IF(L46<0,L46,0) -> -27993033 | N46: =$C$7+M46 -> 2006966.9 | O46: =SUMIF(H46:K46,">0", H46:K46) -> 0 | P46: =P45+O46 -> 20380228
B47: Distribution | C47: DD#17 | D47: 42307 | E47: 42311 | F47: =YEAR(E47) -> 2015 | G47: Sunrise dvd | H47: 562359.27 | L47: =SUM(H47:K47) -> 562359.27 | M47: =M46+IF(L47<0,L47,0) -> -27993033 | N47: =$C$7+M47 -> 2006966.9 | O47: =SUMIF(H47:K47,">0", H47:K47) -> 562359.27 | P47: =P46+O47 -> 20942588 | R47: 141926.49
B48: Distribution | C48: DD#18 | D48: 42368 | E48: 42369 | F48: =YEAR(E48) -> 2015 | G48: Alibaba sale & Marisfrolg dvd | H48: 3148649.5 | L48: =SUM(H48:K48) -> 3148649.5 | M48: =M47+IF(L48<0,L48,0) -> -27993033 | N48: =$C$7+M48 -> 2006966.9 | O48: =SUMIF(H48:K48,">0", H48:K48) -> 3148649.5 | P48: =P47+O48 -> 24091237 | R48: -522146.48
B49: Capital Call | C49: CC#21 | D49: 42374 | E49: 42387 | F49: =YEAR(E49) -> 2016 | I49: -300000 | L49: =SUM(H49:K49) -> -300000 | M49: =M48+IF(L49<0,L49,0) -> -28293033 | N49: =$C$7+M49 -> 1706966.9 | O49: =SUMIF(H49:K49,">0", H49:K49) -> 0 | P49: =P48+O49 -> 24091237
B50: Distribution | C50: DD#19 | D50: 42551 | E50: 42556 | F50: =YEAR(E50) -> 2016 | G50: Ping An & Stelux CB | H50: 1704300.1 | L50: =SUM(H50:K50) -> 1704300.1 | M50: =M49+IF(L50<0,L50,0) -> -28293033 | N50: =$C$7+M50 -> 1706966.9 | O50: =SUMIF(H50:K50,">0", H50:K50) -> 1704300.1 | P50: =P49+O50 -> 25795537 | R50: -359631.63
B51: Capital Call | C51: CC#22 | D51: 42551 | E51: 42556 | F51: =YEAR(E51) -> 2016 | I51: -172483.51 | J51: -12811.84 | L51: =SUM(H51:K51) -> -185295.35 | M51: =M50+IF(L51<0,L51,0) -> -28478328 | N51: =$C$7+M51 -> 1521671.5 | O51: =SUMIF(H51:K51,">0", H51:K51) -> 0 | P51: =P50+O51 -> 25795537
B52: Capital Call | C52: CC#23 | D52: 42613 | E52: 42618 | F52: =YEAR(E52) -> 2016 | J52: -3203.47 | L52: =SUM(H52:K52) -> -3203.47 | M52: =M51+IF(L52<0,L52,0) -> -28481532 | N52: =$C$7+M52 -> 1518468.1 | O52: =SUMIF(H52:K52,">0", H52:K52) -> 0 | P52: =P51+O52 -> 25795537
B53: Distribution | C53: DD#20 | D53: 42613 | E53: 42618 | F53: =YEAR(E53) -> 2016 | G53: Alibaba Sale & FEH dvd | H53: 5774612.3 | L53: =SUM(H53:K53) -> 5774612.3 | M53: =M52+IF(L53<0,L53,0) -> -28481532 | N53: =$C$7+M53 -> 1518468.1 | O53: =SUMIF(H53:K53,">0", H53:K53) -> 5774612.3 | P53: =P52+O53 -> 31570150 | R53: -1119024
B54: Distribution | C54: DD#21 | D54: 42633 | E54: 42636 | F54: =YEAR(E54) -> 2016 | G54: Alibaba Sale & Stelux CB early redemption | H54: 4717524.7 | L54: =SUM(H54:K54) -> 4717524.7 | M54: =M53+IF(L54<0,L54,0) -> -28481532 | N54: =$C$7+M54 -> 1518468.1 | O54: =SUMIF(H54:K54,">0", H54:K54) -> 4717524.7 | P54: =P53+O54 -> 36287674 | R54: -565767.59
B55: Distribution | C55: DD#22 | D55: 42678 | E55: 42682 | F55: =YEAR(E55) -> 2016 | G55: Alibaba sale & Marisfrolg dvd | H55: 854147.57 | L55: =SUM(H55:K55) -> 854147.57 | M55: =M54+IF(L55<0,L55,0) -> -28481532 | N55: =$C$7+M55 -> 1518468.1 | O55: =SUMIF(H55:K55,">0", H55:K55) -> 854147.57 | P55: =P54+O55 -> 37141822 | R55: -154963.32
B56: Capital Call | C56: CC#24 | D56: 42738 | E56: 42751 | F56: =YEAR(E56) -> 2017 | I56: -139631.36 | L56: =SUM(H56:K56) -> -139631.36 | M56: =M55+IF(L56<0,L56,0) -> -28621163 | N56: =$C$7+M56 -> 1378836.7 | O56: =SUMIF(H56:K56,">0", H56:K56) -> 0 | P56: =P55+O56 -> 37141822
B57: Distribution | C57: DD#23 | D57: 42783 | E57: 42787 | F57: =YEAR(E57) -> 2017 | G57: Alibaba sale & Sunrise DVD | H57: 6006711.1 | L57: =SUM(H57:K57) -> 6006711.1 | M57: =M56+IF(L57<0,L57,0) -> -28621163 | N57: =$C$7+M57 -> 1378836.7 | O57: =SUMIF(H57:K57,">0", H57:K57) -> 6006711.1 | P57: =P56+O57 -> 43148533 | R57: =-881376.26-496008.88 -> -1377385.1
B58: Distribution | C58: DD#24 | D58: 42828 | E58: 42830 | F58: =YEAR(E58) -> 2017 | G58: Sunrise DVD | H58: 685810.4 | L58: =SUM(H58:K58) -> 685810.4 | M58: =M57+IF(L58<0,L58,0) -> -28621163 | N58: =$C$7+M58 -> 1378836.7 | O58: =SUMIF(H58:K58,">0", H58:K58) -> 685810.4 | P58: =P57+O58 -> 43834343 | R58: -171554.62
B59: Distribution | C59: DD#25 | D59: 42864 | E59: 42866 | F59: =YEAR(E59) -> 2017 | G59: Alibaba sale & Sunrise DVD | H59: 2885749.9 | L59: =SUM(H59:K59) -> 2885749.9 | M59: =M58+IF(L59<0,L59,0) -> -28621163 | N59: =$C$7+M59 -> 1378836.7 | O59: =SUMIF(H59:K59,">0", H59:K59) -> 2885749.9 | P59: =P58+O59 -> 46720093 | R59: =-564725.73-46595.92 -> -611321.65
B60: Capital Call | C60: CC#25 | D60: 42920 | E60: 42922 | F60: =YEAR(E60) -> 2017 | I60: -130577.8 | L60: =SUM(H60:K60) -> -130577.8 | M60: =M59+IF(L60<0,L60,0) -> -28751741 | N60: =$C$7+M60 -> 1248258.9 | O60: =SUMIF(H60:K60,">0", H60:K60) -> 0 | P60: =P59+O60 -> 46720093
B61: Distribution | C61: DD#26 | D61: 42920 | E61: 42922 | F61: =YEAR(E61) -> 2017 | G61: Sunrise DVD | H61: 1059968.3 | L61: =SUM(H61:K61) -> 1059968.3 | M61: =M60+IF(L61<0,L61,0) -> -28751741 | N61: =$C$7+M61 -> 1248258.9 | O61: =SUMIF(H61:K61,">0", H61:K61) -> 1059968.3 | P61: =P60+O61 -> 47780062 | R61: =-260915.41-76994.03 -> -337909.44
B62: Distribution | C62: DD#27 | D62: 42972 | E62: 42976 | F62: =YEAR(E62) -> 2017 | G62: IPH Shares Sales & FEH DVD | H62: 3890469 | L62: =SUM(H62:K62) -> 3890469 | M62: =M61+IF(L62<0,L62,0) -> -28751741 | N62: =$C$7+M62 -> 1248258.9 | O62: =SUMIF(H62:K62,">0", H62:K62) -> 3890469 | P62: =P61+O62 -> 51670531 | R62: -508526.08
B63: Distribution | C63: DD#28 | D63: 43014 | E63: 43018 | F63: =YEAR(E63) -> 2017 | G63: IPH Shares Sales | H63: 3992858.1 | L63: =SUM(H63:K63) -> 3992858.1 | M63: =M62+IF(L63<0,L63,0) -> -28751741 | N63: =$C$7+M63 -> 1248258.9 | O63: =SUMIF(H63:K63,">0", H63:K63) -> 3992858.1 | P63: =P62+O63 -> 55663389 | R63: -587486.85
B64: Distribution | C64: DD#29 | D64: 43084 | E64: 43088 | F64: =YEAR(E64) -> 2017 | G64: Alibaba sale | H64: 4366180.5 | L64: =SUM(H64:K64) -> 4366180.5 | M64: =M63+IF(L64<0,L64,0) -> -28751741 | N64: =$C$7+M64 -> 1248258.9 | O64: =SUMIF(H64:K64,">0", H64:K64) -> 4366180.5 | P64: =P63+O64 -> 60029569 | R64: -962164.57
B65: Capital Call | C65: CC#26 | D65: 43084 | E65: 43088 | F65: =YEAR(E65) -> 2017 | J65: -2922.93 | L65: =SUM(H65:K65) -> -2922.93 | M65: =M64+IF(L65<0,L65,0) -> -28754664 | N65: =$C$7+M65 -> 1245336 | O65: =SUMIF(H65:K65,">0", H65:K65) -> 0 | P65: =P64+O65 -> 60029569
B66: Capital Call | C66: CC#27 | D66: 43102 | E66: 43115 | F66: =YEAR(E66) -> 2018 | I66: -97345.98 | L66: =SUM(H66:K66) -> -97345.98 | M66: =M65+IF(L66<0,L66,0) -> -28852010 | N66: =$C$7+M66 -> 1147990 | O66: =SUMIF(H66:K66,">0", H66:K66) -> 0 | P66: =P65+O66 -> 60029569
B67: Distribution | C67: DD#30 | D67: 43102 | E67: 43115 | F67: =YEAR(E67) -> 2018 | G67: Marisfrolg dvd | H67: 20622.15 | L67: =SUM(H67:K67) -> 20622.15 | M67: =M66+IF(L67<0,L67,0) -> -28852010 | N67: =$C$7+M67 -> 1147990 | O67: =SUMIF(H67:K67,">0", H67:K67) -> 20622.15 | P67: =P66+O67 -> 60050191
B68: Distribution | C68: DD#31 | D68: 43153 | E68: 43157 | F68: =YEAR(E68) -> 2018 | G68: Alibaba sale | H68: 3565111 | L68: =SUM(H68:K68) -> 3565111 | M68: =M67+IF(L68<0,L68,0) -> -28852010 | N68: =$C$7+M68 -> 1147990 | O68: =SUMIF(H68:K68,">0", H68:K68) -> 3565111 | P68: =P67+O68 -> 63615302 | R68: -776095.88
B69: Distribution | C69: DD#32 | D69: 43259 | E69: 43263 | F69: =YEAR(E69) -> 2018 | G69: Sunrise dvd & FEH sale | H69: 2794834.1 | L69: =SUM(H69:K69) -> 2794834.1 | M69: =M68+IF(L69<0,L69,0) -> -28852010 | N69: =$C$7+M69 -> 1147990 | O69: =SUMIF(H69:K69,">0", H69:K69) -> 2794834.1 | P69: =P68+O69 -> 66410136 | R69: =-412913.72-93824.69 -> -506738.41
B70: Capital Call | C70: CC#28 | D70: 43284 | E70: 43297 | F70: =YEAR(E70) -> 2018 | I70: -85532.88 | L70: =SUM(H70:K70) -> -85532.88 | M70: =M69+IF(L70<0,L70,0) -> -28937543 | N70: =$C$7+M70 -> 1062457.1 | O70: =SUMIF(H70:K70,">0", H70:K70) -> 0 | P70: =P69+O70 -> 66410136
B71: Distribution | C71: DD#33 | D71: 43458 | E71: 43462 | F71: =YEAR(E71) -> 2018 | G71: Marisfrolg dvd | H71: 11545.65 | L71: =SUM(H71:K71) -> 11545.65 | M71: =M70+IF(L71<0,L71,0) -> -28937543 | N71: =$C$7+M71 -> 1062457.1 | O71: =SUMIF(H71:K71,">0", H71:K71) -> 11545.65 | P71: =P70+O71 -> 66421682
B72: Capital Call | C72: CC#29 | D72: 43468 | E72: 43481 | F72: =YEAR(E72) -> 2019 | I72: -85532.87 | J72: -4947.34 | L72: =SUM(H72:K72) -> -90480.21 | M72: =M71+IF(L72<0,L72,0) -> -29028023 | N72: =$C$7+M72 -> 971976.89 | O72: =SUMIF(H72:K72,">0", H72:K72) -> 0 | P72: =P71+O72 -> 66421682
B73: Distribution | C73: DD#34 | D73: 43518 | E73: 43522 | F73: =YEAR(E73) -> 2019 | G73: Sunrise DVD | H73: 1249106.1 | L73: =SUM(H73:K73) -> 1249106.1 | M73: =M72+IF(L73<0,L73,0) -> -29028023 | N73: =$C$7+M73 -> 971976.89 | O73: =SUMIF(H73:K73,">0", H73:K73) -> 1249106.1 | P73: =P72+O73 -> 67670788
B74: Capital Call | C74: CC#30 | D74: 43518 | E74: 43522 | F74: =YEAR(E74) -> 2019 | J74: -2912.24 | L74: =SUM(H74:K74) -> -2912.24 | M74: =M73+IF(L74<0,L74,0) -> -29030935 | N74: =$C$7+M74 -> 969064.65 | O74: =SUMIF(H74:K74,">0", H74:K74) -> 0 | P74: =P73+O74 -> 67670788
B75: Distribution | C75: DD#35 | D75: 43563 | E75: 43565 | F75: =YEAR(E75) -> 2019 | G75: Meituan sales | H75: 1758756 | L75: =SUM(H75:K75) -> 1758756 | M75: =M74+IF(L75<0,L75,0) -> -29030935 | N75: =$C$7+M75 -> 969064.65 | O75: =SUMIF(H75:K75,">0", H75:K75) -> 1758756 | P75: =P74+O75 -> 69429544 | R75: -271808.99
B76: Distribution | C76: DD#36 | D76: 43602 | E76: 43606 | F76: =YEAR(E76) -> 2019 | G76: COFCO Meat sales | H76: 585747.54 | L76: =SUM(H76:K76) -> 585747.54 | M76: =M75+IF(L76<0,L76,0) -> -29030935 | N76: =$C$7+M76 -> 969064.65 | O76: =SUMIF(H76:K76,">0", H76:K76) -> 585747.54 | P76: =P75+O76 -> 70015292 | R76: -53830.17
B77: Capital Call | C77: CC#31 | D77: 43649 | E77: 43651 | F77: =YEAR(E77) -> 2019 | I77: -64032.13 | L77: =SUM(H77:K77) -> -64032.13 | M77: =M76+IF(L77<0,L77,0) -> -29094967 | N77: =$C$7+M77 -> 905032.52 | O77: =SUMIF(H77:K77,">0", H77:K77) -> 0 | P77: =P76+O77 -> 70015292
B78: Distribution | C78: DD#37 | D78: 43649 | E78: 43651 | F78: =YEAR(E78) -> 2019 | G78: Marisfrolg sales | H78: 1763518.8 | L78: =SUM(H78:K78) -> 1763518.8 | M78: =M77+IF(L78<0,L78,0) -> -29094967 | N78: =$C$7+M78 -> 905032.52 | O78: =SUMIF(H78:K78,">0", H78:K78) -> 1763518.8 | P78: =P77+O78 -> 71778810 | R78: -69087.21
B79: Distribution | C79: DD#38 | D79: 43728 | E79: 43732 | F79: =YEAR(E79) -> 2019 | G79: Meituan sales | H79: 2801794.8 | L79: =SUM(H79:K79) -> 2801794.8 | M79: =M78+IF(L79<0,L79,0) -> -29094967 | N79: =$C$7+M79 -> 905032.52 | O79: =SUMIF(H79:K79,">0", H79:K79) -> 2801794.8 | P79: =P78+O79 -> 74580605 | R79: -612050.55
B80: Distribution | C80: DD#39 | D80: 43791 | E80: 43795 | F80: =YEAR(E80) -> 2019 | G80: COFCO Meat sales | H80: 198416.43 | L80: =SUM(H80:K80) -> 198416.43 | M80: =M79+IF(L80<0,L80,0) -> -29094967 | N80: =$C$7+M80 -> 905032.52 | O80: =SUMIF(H80:K80,">0", H80:K80) -> 198416.43 | P80: =P79+O80 -> 74779022 | R80: -262.22
B81: Distribution | C81: DD#40 | D81: 43833 | E81: 43837 | F81: =YEAR(E81) -> 2020 | G81: Alibaba sale | H81: 1406708.9 | L81: =SUM(H81:K81) -> 1406708.9 | M81: =M80+IF(L81<0,L81,0) -> -29094967 | N81: =$C$7+M81 -> 905032.52 | O81: =SUMIF(H81:K81,">0", H81:K81) -> 1406708.9 | P81: =P80+O81 -> 76185731 | R81: -315084.35
B82: Capital Call | C82: CC#32 | D82: 43833 | E82: 43837 | F82: =YEAR(E82) -> 2020 | I82: -55102.83 | J82: -13100.04 | L82: =SUM(H82:K82) -> -68202.87 | M82: =M81+IF(L82<0,L82,0) -> -29163170 | N82: =$C$7+M82 -> 836829.65 | O82: =SUMIF(H82:K82,">0", H82:K82) -> 0 | P82: =P81+O82 -> 76185731
B83: Distribution | C83: DD#41 | D83: 43852 | E83: 43854 | F83: =YEAR(E83) -> 2020 | G83: Sunrise DVD | H83: 898852.04 | L83: =SUM(H83:K83) -> 898852.04 | M83: =M82+IF(L83<0,L83,0) -> -29163170 | N83: =$C$7+M83 -> 836829.65 | O83: =SUMIF(H83:K83,">0", H83:K83) -> 898852.04 | P83: =P82+O83 -> 77084583 | R83: -219450.16
B84: Distribution | C84: DD#42 | D84: 44005 | E84: 44008 | F84: =YEAR(E84) -> 2020 | G84: Meituan sales | H84: 5826836.5 | L84: =SUM(H84:K84) -> 5826836.5 | M84: =M83+IF(L84<0,L84,0) -> -29163170 | N84: =$C$7+M84 -> 836829.65 | O84: =SUMIF(H84:K84,">0", H84:K84) -> 5826836.5 | P84: =P83+O84 -> 82911419 | R84: =-1270782.11+289751.87 -> -981030.24
B85: Capital Call | C85: CC#33 | D85: 44014 | E85: 44027 | F85: =YEAR(E85) -> 2020 | I85: -49162.12 | J85: -2912.24 | L85: =SUM(H85:K85) -> -52074.36 | M85: =M86+IF(L85<0,L85,0) -> -29215245 | N85: =$C$7+M85 -> 784755.29 | O85: =SUMIF(H85:K85,">0", H85:K85) -> 0 | P85: =P86+O85 -> 83931397
B86: Distribution | C86: DD#43 | D86: 44179 | E86: 44182 | F86: =YEAR(E86) -> 2020 | G86: COFCO Meat | H86: 1019977.5 | L86: =SUM(H86:K86) -> 1019977.5 | M86: =M84+IF(L86<0,L86,0) -> -29163170 | N86: =$C$7+M86 -> 836829.65 | O86: =SUMIF(H86:K86,">0", H86:K86) -> 1019977.5 | P86: =P84+O86 -> 83931397
B87: Capital Call | C87: CC#34 | D87: 44202 | E87: 44215 | F87: =YEAR(E87) -> 2021 | I87: -40030.52 | J87: -2912.25 | L87: =SUM(H87:K87) -> -42942.77 | M87: =M85+IF(L87<0,L87,0) -> -29258187 | N87: =$C$7+M87 -> 741812.52 | O87: =SUMIF(H87:K87,">0", H87:K87) -> 0 | P87: =P85+O87 -> 83931397
B88: Distribution | C88: DD#44 | D88: 44202 | E88: 44215 | F88: =YEAR(E88) -> 2021 | G88: COFCO Meat | H88: 5983.58 | L88: =SUM(H88:K88) -> 5983.58 | M88: =M87+IF(L88<0,L88,0) -> -29258187 | N88: =$C$7+M88 -> 741812.52 | O88: =SUMIF(H88:K88,">0", H88:K88) -> 5983.58 | P88: =P87+O88 -> 83937380
B89: Distribution | C89: DD#45 | E89: 44421 | F89: =YEAR(E89) -> 2021 | G89: COFCO Meat | H89: 2315721.4 | L89: =SUM(H89:K89) -> 2315721.4 | M89: =M88+IF(L89<0,L89,0) -> -29258187 | N89: =$C$7+M89 -> 741812.52 | O89: =SUMIF(H89:K89,">0", H89:K89) -> 2315721.4 | P89: =P88+O89 -> 86253102
B90: Capital Call | C90: CC#35 | E90: 44421 | F90: =YEAR(E90) -> 2021 | I90: -29873.46 | L90: =SUM(H90:K90) -> -29873.46 | M90: =M89+IF(L90<0,L90,0) -> -29288061 | N90: =$C$7+M90 -> 711939.06 | O90: =SUMIF(H90:K90,">0", H90:K90) -> 0 | P90: =P89+O90 -> 86253102
B91: Distribution | C91: DD#46 | E91: 44512 | F91: =YEAR(E91) -> 2021 | G91: Sunrise dividends | H91: 481029.47 | L91: =SUM(H91:K91) -> 481029.47 | M91: =M90+IF(L91<0,L91,0) -> -29288061 | N91: =$C$7+M91 -> 711939.06 | O91: =SUMIF(H91:K91,">0", H91:K91) -> 481029.47 | P91: =P90+O91 -> 86734131 | R91: -112789
B92: Capital Call | C92: CC#36 | E92: 44574 | F92: =YEAR(E92) -> 2022 | I92: -21729.94 | J92: -5824.51 | L92: =SUM(H92:K92) -> -27554.45 | M92: =M91+IF(L92<0,L92,0) -> -29315615 | N92: =$C$7+M92 -> 684384.61 | O92: =SUMIF(H92:K92,">0", H92:K92) -> 0 | P92: =P91+O92 -> 86734131
B93: Distribution | C93: DD#47 | E93: 44677 | F93: =YEAR(E93) -> 2022 | G93: Sunrise dividends | H93: 717981.21 | L93: =SUM(H93:K93) -> 717981.21 | M93: =M92+IF(L93<0,L93,0) -> -29315615 | N93: =$C$7+M93 -> 684384.61 | O93: =SUMIF(H93:K93,">0", H93:K93) -> 717981.21 | P93: =P92+O93 -> 87452112 | R93: -172606.7
B94: Capital Call | C94: CC#37 | E94: 44756 | F94: =YEAR(E94) -> 2022 | I94: -26827.09 | J94: -2912.24 | L94: =SUM(H94:K94) -> -29739.33 | M94: =M93+IF(L94<0,L94,0) -> -29345355 | N94: =$C$7+M94 -> 654645.28 | O94: =SUMIF(H94:K94,">0", H94:K94) -> 0 | P94: =P93+O94 -> 87452112
B95: Capital Call | C95: CC#38 | E95: 44932 | F95: =YEAR(E95) -> 2023 | I95: -21729.94 | J95: -2912.25 | L95: =SUM(H95:K95) -> -24642.19 | M95: =M94+IF(L95<0,L95,0) -> -29369997 | N95: =$C$7+M95 -> 630003.09 | O95: =SUMIF(H95:K95,">0", H95:K95) -> 0 | P95: =P94+O95 -> 87452112
B96: Capital Call | C96: CC#39 | D96: 44202 | E96: 45071 | F96: =YEAR(E96) -> 2023 | J96: -84455.11 | L96: =SUM(H96:K96) -> -84455.11 | M96: =M95+IF(L96<0,L96,0) -> -29454452 | N96: =$C$7+M96 -> 545547.98 | O96: =SUMIF(H96:K96,">0", H96:K96) -> 0 | P96: =P95+O96 -> 87452112
B97: Distribution | C97: DD#48 | D97: 44202 | E97: 45071 | F97: =YEAR(E97) -> 2023 | G97: COFCO Meat | H97: 4580080.5 | L97: =SUM(H97:K97) -> 4580080.5 | M97: =M96+IF(L97<0,L97,0) -> -29454452 | N97: =$C$7+M97 -> 545547.98 | O97: =SUMIF(H97:K97,">0", H97:K97) -> 4580080.5 | P97: =P96+O97 -> 92032193 | S97: Ties to 2023 Q3 CAS
B98: Distribution | C98: DD#49 | D98: 44202 | E98: 45275 | F98: =YEAR(E98) -> 2023 | G98: COFCO Meat | H98: 6632.82 | L98: =SUM(H98:K98) -> 6632.82 | M98: =M97+IF(L98<0,L98,0) -> -29454452 | N98: =$C$7+M98 -> 545547.98 | O98: =SUMIF(H98:K98,">0", H98:K98) -> 6632.82 | P98: =P97+O98 -> 92038826 | S98: Ties to 2024 Q4 CAS
B100: Capital Account Balance | D100: 44196 | E100: =L1 -> 45657 | F100: =YEAR(E100) -> 2024 | L100: 51248
B103: Sunrise Dividend Distribution History
B104: Transaction type (Call/Distribution) | C104: No. | E104: Trans. Date | F104: Year | H104: Trans. Amt
...

Sheet BOYU Offshore CF
A1: BOYU CAPITAL OFFSHORE FUND
A2: {='[5]BOYU I CF - NEW'!C3:D3} -> 45657 | B2: 0
A3: Transation History | I3: SERIES A UNRESTRICTED INITIAL SERIES - MAY 2016 | M3: SERIES A UNRESTRICTED INITIAL SERIES - MAY 2016 - OFFSHORE NOV 2020/FEB 2021 | Q3: BOYU CAPITAL FUND SP INITIAL SERIES A UR - JANUARY 2020/March 2021 | U3: BOYU CAPITAL FUND SP INITIAL SERIES A UR - DEC21 | Y3: BOYU CAPITAL FUND SP INITIAL SERIES A UR - MAR22 | AC3: BOYU CAPITAL FUND SP INITIAL SERIES A UR - MAY23 | AG3: BOYU CAPITAL FUND SP INITIAL SERIES A UR - JUN23 | AK3: BOYU CAPITAL FUND SP2 INITIAL SERIES A UR - JULY 2020/FEB 2021 | AO3: SR15 MAY22 | AS3: BOYU CAPITAL FUND SP3 INITIAL SERIES A UR - SEPTEMBER 2020 | AW3: BOYU CAPITAL FUND SP4 INITIAL SERIES A UR - JANUARY 2021 | BA3: SP8 SERIES A UR MAY 21 | BE3: SP9 SERIES A UR MAY 21 | BI3: SP10 SERIES A UR MAY 21 | BM3: SP7 SERIES A UR MAY 21 | BQ3: SP SERIES A UR SR01 JUN21 | BU3: SP13 SERIES A UR SR01 JUL21 | BY3: SP14 SERIES A UR SR01 JUL21 | CC3: SP15 SERIES A UR SR01 AUG21 | CG3: SP16 SERIES A UR SR01 AUG21 | CK3: SP17 SERIES A UR SR01 NOV21 | CO3: SP18 SERIES A UR SR01 JAN22 | CS3: SP19 SERIES A UR SR01 JAN22 | CW3: Consolidated
A4: NAV Date | B4: No. of Shares | C4: NAV | D4: Transaction Amount | E4: Market value | H4: Date | I4: No. of Shares | J4: Amount | K4: Gain/(loss) | L4: Market value | M4: No. of Shares | N4: Amount | O4: Gain/(loss) | P4: Market value | Q4: No. of Shares | R4: Amount | S4: Gain/(loss) | T4: Market value | U4: No. of Shares | V4: Amount | W4: Gain/(loss) | X4: Market value | Y4: No. of Shares | Z4: Amount | AA4: Gain/(loss) | AB4: Market value | AC4: No. of Shares | AD4: Amount | AE4: Gain/(loss) | AF4: Market value | AG4: No. of Shares | AH4: Amount | AI4: Gain/(loss) | AJ4: Market value | AK4: No. of Shares | AL4: Amount | AM4: Gain/(loss) | AN4: Market value | AO4: No. of Shares | AP4: Amount | AQ4: Gain/(loss) | AR4: Market value | AS4: No. of Shares | AT4: Amount | AU4: Gain/(loss) | AV4: Market value | AW4: No. of Shares | AX4: Amount | AY4: Gain/(loss) | AZ4: Market value | BA4: No. of Shares | BB4: Amount | BC4: Gain/(loss) | BD4: Market value | BE4: No. of Shares | BF4: Amount | BG4: Gain/(loss) | BH4: Market value | BI4: No. of Shares | BJ4: Amount | BK4: Gain/(loss) | BL4: Market value | BM4: No. of Shares | BN4: Amount | BO4: Gain/(loss) | BP4: Market value | BQ4: No. of Shares | BR4: Amount | BS4: Gain/(loss) | BT4: Market value | BU4: No. of Shares | BV4: Amount | BW4: Gain/(loss) | BX4: Market value | BY4: No. of Shares | BZ4: Amount | CA4: Gain/(loss) | CB4: Market value | CC4: No. of Shares | CD4: Amount | CE4: Gain/(loss) | CF4: Market value | CG4: No. of Shares | CH4: Amount | CI4: Gain/(loss) | CJ4: Market value | CK4: No. of Shares | CL4: Amount | CM4: Gain/(loss) | CN4: Market value | CO4: No. of Shares | CP4: Amount | CQ4: Gain/(loss) | CR4: Market value | CS4: No. of Shares | CT4: Amount | CU4: Gain/(loss) | CV4: Market value | CW4: Amount | CX4: Gain/(loss) | CY4: Market value
A5: 42618 | B5: =-10000 -> -10000 | C5: =D5/B5 -> 1000 | D5: -10000000 | F5: Subscription | H5: 43830 | L5: 15920800 | P5: 0 | T5: 0 | AN5: 0 | AR5: 0 | AV5: 0 | AZ5: 0 | BD5: 0 | BH5: 0 | BL5: 0 | BP5: 0 | BT5: 0 | CW5: =J5+R5+AP5+AT5+N5+AX5+BB5+BF5+BJ5+BN5+BR5 -> 0 | CX5: =K5+S5+AQ5+AU5+O5+AY5+BC5+BG5+BK5+BO5+BS5 -> 0 | CY5: =L5+T5+AR5+AV5+P5+AZ5+BD5+BH5+BL5+BP5+BT5 -> 15920800
A6: 43921 | B6: 1500 | C6: 1667.67 | D6: =B6*C6 -> 2501505 | F6: 1st Redemption | H6: 43861 | I6: -682.0301 | J6: -1085846.6 | K6: 476148.34 | L6: =L5+J6+K6 -> 15311102 | P6: =P5+N6+O6 -> 0 | Q6: 1085.8466 | R6: 1085846.6 | S6: -868.64 | T6: =T5+R6+S6 -> 1084977.9 | AN6: =AN5+AL6+AM6 -> 0 | AR6: =AR5+AP6+AQ6 -> 0 | AV6: =AV5+AT6+AU6 -> 0 | AZ6: =AZ5+AX6+AY6 -> 0 | BD6: =BD5+BB6+BC6 -> 0 | BH6: =BH5+BF6+BG6 -> 0 | BL6: =BL5+BJ6+BK6 -> 0 | BP6: =BP5+BN6+BO6 -> 0 | BT6: =BT5+BR6+BS6 -> 0 | CW6: =J6+R6+AP6+AT6+N6+AX6+BB6+BF6+BJ6+BN6+BR6 -> 0 | CX6: =K6+S6+AQ6+AU6+O6+AY6+BC6+BG6+BK6+BO6+BS6 -> 475279.7 | CY6: =L6+T6+AR6+AV6+P6+AZ6+BD6+BH6+BL6+BP6+BT6 -> 16396080
A7: 44012 | B7: 1500 | C7: =D7/B7 -> 1929.12 | D7: 2893680 | F7: 2nd Redemption | H7: 43890 | K7: 724844.88 | L7: =L6+J7+K7 -> 16035947 | P7: =P6+N7+O7 -> 0 | T7: =T6+R7+S7 -> 1084977.9 | AN7: =AN6+AL7+AM7 -> 0 | AR7: =AR6+AP7+AQ7 -> 0 | AV7: =AV6+AT7+AU7 -> 0 | AZ7: =AZ6+AX7+AY7 -> 0 | BD7: =BD6+BB7+BC7 -> 0 | BH7: =BH6+BF7+BG7 -> 0 | BL7: =BL6+BJ7+BK7 -> 0 | BP7: =BP6+BN7+BO7 -> 0 | BT7: =BT6+BR7+BS7 -> 0 | CW7: =J7+R7+AP7+AT7+N7+AX7+BB7+BF7+BJ7+BN7+BR7 -> 0 | CX7: =K7+S7+AQ7+AU7+O7+AY7+BC7+BG7+BK7+BO7+BS7 -> 724844.88 | CY7: =L7+T7+AR7+AV7+P7+AZ7+BD7+BH7+BL7+BP7+BT7 -> 17120925
A8: 44104 | B8: 1500 | C8: =D8/B8 -> 1939.44 | D8: 2909160 | F8: 3rd Redemption | H8: 43921 | K8: -496647.8 | L8: =L7+J8+K8 -> 15539299 | P8: =P7+N8+O8 -> 0 | T8: =T7+R8+S8 -> 1084977.9 | AN8: =AN7+AL8+AM8 -> 0 | AR8: =AR7+AP8+AQ8 -> 0 | AV8: =AV7+AT8+AU8 -> 0 | AZ8: =AZ7+AX8+AY8 -> 0 | BD8: =BD7+BB8+BC8 -> 0 | BH8: =BH7+BF8+BG8 -> 0 | BL8: =BL7+BJ8+BK8 -> 0 | BP8: =BP7+BN8+BO8 -> 0 | BT8: =BT7+BR8+BS8 -> 0 | CW8: =J8+R8+AP8+AT8+N8+AX8+BB8+BF8+BJ8+BN8+BR8 -> 0 | CX8: =K8+S8+AQ8+AU8+O8+AY8+BC8+BG8+BK8+BO8+BS8 -> -496647.8 | CY8: =L8+T8+AR8+AV8+P8+AZ8+BD8+BH8+BL8+BP8+BT8 -> 16624277
A9: 44196 | B9: 1500 | C9: =D9/B9 -> 2387.09 | D9: 3580635 | F9: 4th Redemption | H9: 43951 | I9: -1500 | J9: -2501505 | K9: 527243.89 | L9: =L8+J9+K9 -> 13565038 | P9: =P8+N9+O9 -> 0 | T9: =T8+R9+S9 -> 1084977.9 | AN9: =AN8+AL9+AM9 -> 0 | AR9: =AR8+AP9+AQ9 -> 0 | AV9: =AV8+AT9+AU9 -> 0 | AZ9: =AZ8+AX9+AY9 -> 0 | BD9: =BD8+BB9+BC9 -> 0 | BH9: =BH8+BF9+BG9 -> 0 | BL9: =BL8+BJ9+BK9 -> 0 | BP9: =BP8+BN9+BO9 -> 0 | BT9: =BT8+BR9+BS9 -> 0 | CW9: =J9+R9+AP9+AT9+N9+AX9+BB9+BF9+BJ9+BN9+BR9 -> -2501505 | CX9: =K9+S9+AQ9+AU9+O9+AY9+BC9+BG9+BK9+BO9+BS9 -> 527243.89 | CY9: =L9+T9+AR9+AV9+P9+AZ9+BD9+BH9+BL9+BP9+BT9 -> 14650016
A10: 44286 | E10: 12070889 | F10: NAV | H10: 43982 | K10: 525211.22 | L10: =L9+J10+K10 -> 14090249 | P10: =P9+N10+O10 -> 0 | T10: =T9+R10+S10 -> 1084977.9 | AN10: =AN9+AL10+AM10 -> 0 | AR10: =AR9+AP10+AQ10 -> 0 | AV10: =AV9+AT10+AU10 -> 0 | AZ10: =AZ9+AX10+AY10 -> 0 | BD10: =BD9+BB10+BC10 -> 0 | BH10: =BH9+BF10+BG10 -> 0 | BL10: =BL9+BJ10+BK10 -> 0 | BP10: =BP9+BN10+BO10 -> 0 | BT10: =BT9+BR10+BS10 -> 0 | CW10: =J10+R10+AP10+AT10+N10+AX10+BB10+BF10+BJ10+BN10+BR10 -> 0 | CX10: =K10+S10+AQ10+AU10+O10+AY10+BC10+BG10+BK10+BO10+BS10 -> 525211.22 | CY10: =L10+T10+AR10+AV10+P10+AZ10+BD10+BH10+BL10+BP10+BT10 -> 15175227
A11: 44377 | B11: 1500 | C11: =D11/B11 -> 2956.91 | D11: 4435365 | E11: 11843271 | F11: 5th Redemption | H11: 44012 | K11: 991553.12 | L11: =L10+J11+K11 -> 15081802 | P11: =P10+N11+O11 -> 0 | T11: =T10+R11+S11 -> 1084977.9 | AN11: =AN10+AL11+AM11 -> 0 | AR11: =AR10+AP11+AQ11 -> 0 | AV11: =AV10+AT11+AU11 -> 0 | AZ11: =AZ10+AX11+AY11 -> 0 | BD11: =BD10+BB11+BC11 -> 0 | BH11: =BH10+BF11+BG11 -> 0 | BL11: =BL10+BJ11+BK11 -> 0 | BP11: =BP10+BN11+BO11 -> 0 | BT11: =BT10+BR11+BS11 -> 0 | CW11: =J11+R11+AP11+AT11+N11+AX11+BB11+BF11+BJ11+BN11+BR11 -> 0 | CX11: =K11+S11+AQ11+AU11+O11+AY11+BC11+BG11+BK11+BO11+BS11 -> 991553.12 | CY11: =L11+T11+AR11+AV11+P11+AZ11+BD11+BH11+BL11+BP11+BT11 -> 16166780
A12: 44408
A13: 44469 | E13: =CY27 -> 6088998 | F13: NAV | H13: 44043 | I13: -1533.9613 | J13: -2959195.5 | K13: 328653.72 | L13: =L11+J13+K13 -> 12451260 | P13: =P11+N13+O13 -> 0 | S13: -32.57 | T13: =T11+R13+S13 -> 1084945.4 | AK13: 65.5155 | AL13: 65515.49 | AM13: 0.01 | AN13: =AN11+AL13+AM13 -> 65515.5 | AR13: =AR11+AP13+AQ13 -> 0 | AS13: 0 | AT13: 0 | AU13: 0 | AV13: =AV11+AT13+AU13 -> 0 | AZ13: =AZ11+AX13+AY13 -> 0 | BD13: =BD11+BB13+BC13 -> 0 | BH13: =BH11+BF13+BG13 -> 0 | BL13: =BL11+BJ13+BK13 -> 0 | BP13: =BP11+BN13+BO13 -> 0 | BT13: =BT11+BR13+BS13 -> 0 | CW13: =J13+R13+AP13+AT13+N13+AX13+BB13+BF13+BJ13+BN13+BR13 -> -2959195.5 | CX13: =K13+S13+AQ13+AU13+O13+AY13+BC13+BG13+BK13+BO13+BS13 -> 328621.15 | CY13: =L13+T13+AR13+AV13+P13+AZ13+BD13+BH13+BL13+BP13+BT13 -> 13536206
A14: 44500 | H14: 44074 | K14: 104817.26 | L14: =L13+J14+K14 -> 12556078 | P14: =P13+N14+O14 -> 0 | T14: =T13+R14+S14 -> 1084945.4 | AN14: =AN13+AL14+AM14 -> 65515.5 | AR14: =AR13+AP14+AQ14 -> 0 | AV14: =AV13+AT14+AU14 -> 0 | AZ14: =AZ13+AX14+AY14 -> 0 | BD14: =BD13+BB14+BC14 -> 0 | BH14: =BH13+BF14+BG14 -> 0 | BL14: =BL13+BJ14+BK14 -> 0 | BP14: =BP13+BN14+BO14 -> 0 | BT14: =BT13+BR14+BS14 -> 0 | CW14: =J14+R14+AP14+AT14+N14+AX14+BB14+BF14+BJ14+BN14+BR14 -> 0 | CX14: =K14+S14+AQ14+AU14+O14+AY14+BC14+BG14+BK14+BO14+BS14 -> 104817.26 | CY14: =L14+T14+AR14+AV14+P14+AZ14+BD14+BH14+BL14+BP14+BT14 -> 13641023
A15: 44530 | H15: 44104 | I15: -128.3595 | J15: -248945.5 | K15: -368619.99 | L15: =L14+J15+K15 -> 11938512 | P15: =P14+N15+O15 -> 0 | T15: =T14+R15+S15 -> 1084945.4 | AN15: =AN14+AL15+AM15 -> 65515.5 | AR15: =AR14+AP15+AQ15 -> 0 | AS15: 248.9455 | AT15: 248945.5 | AV15: =AV14+AT15+AU15 -> 248945.5 | AZ15: =AZ14+AX15+AY15 -> 0 | BD15: =BD14+BB15+BC15 -> 0 | BH15: =BH14+BF15+BG15 -> 0 | BL15: =BL14+BJ15+BK15 -> 0 | BP15: =BP14+BN15+BO15 -> 0 | BT15: =BT14+BR15+BS15 -> 0 | CW15: =J15+R15+AP15+AT15+N15+AX15+BB15+BF15+BJ15+BN15+BR15 -> 0 | CX15: =K15+S15+AQ15+AU15+O15+AY15+BC15+BG15+BK15+BO15+BS15 -> -368619.99 | CY15: =L15+T15+AR15+AV15+P15+AZ15+BD15+BH15+BL15+BP15+BT15 -> 13272403
A16: 44561 | E16: =CY30 -> 5407052.4 | F16: NAV | H16: 44135 | I16: -1500 | J16: -2909160 | K16: 280130.41 | L16: =L15+J16+K16 -> 9309482.5 | P16: =P15+N16+O16 -> 0 | T16: =T15+R16+S16 -> 1084945.4 | AN16: =AN15+AL16+AM16 -> 65515.5 | AR16: =AR15+AP16+AQ16 -> 0 | AV16: =AV15+AT16+AU16 -> 248945.5 | AZ16: =AZ15+AX16+AY16 -> 0 | BD16: =BD15+BB16+BC16 -> 0 | BH16: =BH15+BF16+BG16 -> 0 | BL16: =BL15+BJ16+BK16 -> 0 | BP16: =BP15+BN16+BO16 -> 0 | BT16: =BT15+BR16+BS16 -> 0 | CW16: =J16+R16+AP16+AT16+N16+AX16+BB16+BF16+BJ16+BN16+BR16 -> -2909160 | CX16: =K16+S16+AQ16+AU16+O16+AY16+BC16+BG16+BK16+BO16+BS16 -> 280130.41 | CY16: =L16+T16+AR16+AV16+P16+AZ16+BD16+BH16+BL16+BP16+BT16 -> 10643373
A17: 44592 | E17: =CY31 -> 5139609 | F17: NAV | H17: 44165 | K17: 821908.29 | L17: =L16+J17+K17 -> 10131391 | M17: 99.1472 | N17: 99147.23 | O17: -979.6 | P17: =P16+N17+O17 -> 98167.63 | S17: 10.86 | T17: =T16+R17+S17 -> 1084956.2 | AK17: -65.5155 | AL17: -99147.23 | AM17: 33631.73 | AN17: =AN16+AL17+AM17 -> 0 | AR17: =AR16+AP17+AQ17 -> 0 | AV17: =AV16+AT17+AU17 -> 248945.5 | AZ17: =AZ16+AX17+AY17 -> 0 | BD17: =BD16+BB17+BC17 -> 0 | BH17: =BH16+BF17+BG17 -> 0 | BL17: =BL16+BJ17+BK17 -> 0 | BP17: =BP16+BN17+BO17 -> 0 | BT17: =BT16+BR17+BS17 -> 0 | CW17: =J17+R17+AP17+AT17+N17+AX17+BB17+BF17+BJ17+BN17+BR17 -> 99147.23 | CX17: =K17+S17+AQ17+AU17+O17+AY17+BC17+BG17+BK17+BO17+BS17 -> 820939.55 | CY17: =L17+T17+AR17+AV17+P17+AZ17+BD17+BH17+BL17+BP17+BT17 -> 11563460
A18: 44620 | E18: =CY32 -> 5007824.8 | F18: NAV | H18: 44196 | K18: 982062.62 | L18: =L17+J18+K18 -> 11113453 | O18: 9128.48 | P18: =P17+N18+O18 -> 107296.11 | T18: =T17+R18+S18 -> 1084956.2 | AN18: =AN17+AL18+AM18 -> 0 | AR18: =AR17+AP18+AQ18 -> 0 | AV18: =AV17+AT18+AU18 -> 248945.5 | AZ18: =AZ17+AX18+AY18 -> 0 | BD18: =BD17+BB18+BC18 -> 0 | BH18: =BH17+BF18+BG18 -> 0 | BL18: =BL17+BJ18+BK18 -> 0 | BP18: =BP17+BN18+BO18 -> 0 | BT18: =BT17+BR18+BS18 -> 0 | CW18: =J18+R18+AP18+AT18+N18+AX18+BB18+BF18+BJ18+BN18+BR18 -> 0 | CX18: =K18+S18+AQ18+AU18+O18+AY18+BC18+BG18+BK18+BO18+BS18 -> 991191.1 | CY18: =L18+T18+AR18+AV18+P18+AZ18+BD18+BH18+BL18+BP18+BT18 -> 12554651
A19: 44651 | E19: =CY33 -> 4614634.6 | F19: NAV | H19: 44227 | I19: -1589.1087 | J19: -3793345.4 | K19: 730480.46 | L19: =L18+J19+K19 -> 8050588.5 | M19: -99.1472 | N19: -107296.11 | P19: =P18+N19+O19 -> -1.4551915e-11 | S19: -1813.37 | T19: =T18+R19+S19 -> 1083142.8 | AN19: =AN18+AL19+AM19 -> 0 | AR19: =AR18+AP19+AQ19 -> 0 | AU19: -415.74 | AV19: =AV18+AT19+AU19 -> 248529.76 | AW19: 320.0065 | AX19: 320006.47 | AY19: -534.38 | AZ19: =AZ18+AX19+AY19 -> 319472.09 | BD19: =BD18+BB19+BC19 -> 0 | BH19: =BH18+BF19+BG19 -> 0 | BL19: =BL18+BJ19+BK19 -> 0 | BP19: =BP18+BN19+BO19 -> 0 | BT19: =BT18+BR19+BS19 -> 0 | CW19: =J19+R19+AP19+AT19+N19+AX19+BB19+BF19+BJ19+BN19+BR19 -> -3580635 | CX19: =K19+S19+AQ19+AU19+O19+AY19+BC19+BG19+BK19+BO19+BS19 -> 727716.97 | CY19: =L19+T19+AR19+AV19+P19+AZ19+BD19+BH19+BL19+BP19+BT19 -> 9701733.2
A20: 44681 | E20: =CY34 -> 4389797.9 | F20: NAV | H20: 44255 | I20: -30.3695 | J20: -82564.66 | K20: 1457282.9 | L20: =L19+J20+K20 -> 9425306.8 | M20: 2075.2411 | N20: =M20*1000 -> 2075241.1 | O20: 285677.7 | P20: =P19+N20+O20 -> 2360918.8 | Q20: -1085.8466 | R20: -2095998.8 | S20: 1012856 | T20: =T19+R20+S20 -> 0 | AK20: 103.3224 | AL20: =AK20*1000 -> 103322.4 | AM20: -148.78 | AN20: =AN19+AL20+AM20 -> 103173.62 | AR20: =AR19+AP20+AQ20 -> 0 | AU20: -413.25 | AV20: =AV19+AT20+AU20 -> 248116.51 | AY20: -531.21 | AZ20: =AZ19+AX20+AY20 -> 318940.88 | BD20: =BD19+BB20+BC20 -> 0 | BH20: =BH19+BF20+BG20 -> 0 | BL20: =BL19+BJ20+BK20 -> 0 | BP20: =BP19+BN20+BO20 -> 0 | BT20: =BT19+BR20+BS20 -> 0 | CW20: =J20+R20+AP20+AT20+N20+AX20+BB20+BF20+BJ20+BN20+BR20 -> -103322.39 | CX20: =K20+S20+AQ20+AU20+O20+AY20+BC20+BG20+BK20+BO20+BS20 -> 2754872.2 | CY20: =L20+T20+AR20+AV20+P20+AZ20+BD20+BH20+BL20+BP20+BT20 -> 12353283
A21: 44712 | E21: =CY35 -> 4515453.7 | F21: NAV | H21: 44286 | I21: -13.2383 | J21: -41096.01 | K21: -308913.65 | L21: =L20+J21+K21 -> 9075297.1 | M21: -9.0484 | N21: -10294.02 | O21: -75374.69 | P21: =P20+N21+O21 -> 2275250.1 | R21: 51390.03 | S21: -85.85 | T21: =T20+R21+S21 -> 51304.18 | AM21: -249.01 | AN21: =AN20+AL21+AM21 -> 102924.61 | AR21: =AR20+AP21+AQ21 -> 0 | AU21: -413.25 | AV21: =AV20+AT21+AU21 -> 247703.26 | AY21: -531.21 | AZ21: =AZ20+AX21+AY21 -> 318409.67 | BD21: =BD20+BB21+BC21 -> 0 | BH21: =BH20+BF21+BG21 -> 0 | BL21: =BL20+BJ21+BK21 -> 0 | BP21: =BP20+BN21+BO21 -> 0 | BT21: =BT20+BR21+BS21 -> 0 | CW21: =J21+R21+AP21+AT21+N21+AX21+BB21+BF21+BJ21+BN21+BR21 -> -3.6379788e-12 | CX21: =K21+S21+AQ21+AU21+O21+AY21+BC21+BG21+BK21+BO21+BS21 -> -385318.65 | CY21: =L21+T21+AR21+AV21+P21+AZ21+BD21+BH21+BL21+BP21+BT21 -> 11967964
A22: 44742 | E22: =CY36 -> 4938092.3 | F22: NAV | H22: 44316 | K22: 129048.99 | L22: =L21+J22+K22 -> 9204346.1 | O22: 31488.77 | P22: =P21+N22+O22 -> 2306738.9 | S22: -85.31 | T22: =T21+R22+S22 -> 51218.87 | AM22: -661.26 | AN22: =AN21+AL22+AM22 -> 102263.35 | AR22: =AR21+AP22+AQ22 -> 0 | AU22: -413.25 | AV22: =AV21+AT22+AU22 -> 247290.01 | AY22: -531.21 | AZ22: =AZ21+AX22+AY22 -> 317878.46 | BD22: =BD21+BB22+BC22 -> 0 | BH22: =BH21+BF22+BG22 -> 0 | BL22: =BL21+BJ22+BK22 -> 0 | BP22: =BP21+BN22+BO22 -> 0 | BT22: =BT21+BR22+BS22 -> 0 | CW22: =J22+R22+AP22+AT22+N22+AX22+BB22+BF22+BJ22+BN22+BR22 -> 0 | CX22: =K22+S22+AQ22+AU22+O22+AY22+BC22+BG22+BK22+BO22+BS22 -> 159507.99 | CY22: =L22+T22+AR22+AV22+P22+AZ22+BD22+BH22+BL22+BP22+BT22 -> 12127472
A23: 44773 | E23: =CY37 -> 4699654.8 | F23: NAV | H23: 44347 | I23: -103.6496 | J23: -305534.27 | K23: -293466.17 | L23: =L22+J23+K23 -> 8605345.7 | M23: -70.8454 | N23: -76638.52 | O23: -71593.48 | P23: =P22+N23+O23 -> 2158506.9 | S23: -85.31 | T23: =T22+R23+S23 -> 51133.56 | AM23: -170.49 | AN23: =AN22+AL23+AM23 -> 102092.86 | AR23: =AR22+AP23+AQ23 -> 0 | AU23: -413.25 | AV23: =AV22+AT23+AU23 -> 246876.76 | AY23: -531.21 | AZ23: =AZ22+AX23+AY23 -> 317347.25 | BA23: 118.3216 | BB23: 118321.61 | BC23: -0.01 | BD23: =BD22+BB23+BC23 -> 118321.6 | BE23: 141.986 | BF23: 141985.93 | BG23: 0.07 | BH23: =BH22+BF23+BG23 -> 141986 | BI23: 74.0815 | BJ23: 74081.52 | BK23: -0.02 | BL23: =BL22+BJ23+BK23 -> 74081.5 | BM23: 47.7838 | BN23: 47783.73 | BO23: 0.07 | BP23: =BP22+BN23+BO23 -> 47783.8 | BT23: =BT22+BR23+BS23 -> 0 | CW23: =J23+R23+AP23+AT23+N23+AX23+BB23+BF23+BJ23+BN23+BR23 -> -5.0931703e-11 | CX23: =K23+S23+AQ23+AU23+O23+AY23+BC23+BG23+BK23+BO23+BS23 -> -366089.31 | CY23: =L23+T23+AR23+AV23+P23+AZ23+BD23+BH23+BL23+BP23+BT23 -> 11761383
A24: 44804 | E24: =CY38 -> 4692118 | F24: NAV | H24: 44377 | I24: -28.282 | J24: -83368.89 | K24: 26453 | L24: =L23+J24+K24 -> 8548429.8 | M24: -19.331 | N24: -20911.68 | O24: 6461.56 | P24: =P23+N24+O24 -> 2144056.7 | Q24: -51.39 | R24: -60857.58 | S24: =9809.32-85.3 -> 9724.02 | T24: =T23+R24+S24 -> 0 | AM24: -169.45 | AN24: =AN23+AL24+AM24 -> 101923.41 | AR24: =AR23+AP24+AQ24 -> 0 | AU24: -463.04 | AV24: =AV23+AT24+AU24 -> 246413.72 | AY24: -528.01 | AZ24: =AZ23+AX24+AY24 -> 316819.24 | BC24: -197.6 | BD24: =BD23+BB24+BC24 -> 118124 | BG24: -237.12 | BH24: =BH23+BF24+BG24 -> 141748.88 | BK24: -123.72 | BL24: =BL23+BJ24+BK24 -> 73957.78 | BO24: -93.18 | BP24: =BP23+BN24+BO24 -> 47690.62 | BQ24: =48.626+55.6546 -> 104.2806 | BR24: 104280.57 | BS24: =-92.96-81.16 -> -174.12 | BT24: =BT23+BR24+BS24 -> 104106.45 | CW24: =J24+R24+AP24+AT24+N24+AX24+BB24+BF24+BJ24+BN24+BR24 -> -60857.58 | CX24: =K24+S24+AQ24+AU24+O24+AY24+BC24+BG24+BK24+BO24+BS24 -> 40821.79 | CY24: =L24+T24+AR24+AV24+P24+AZ24+BD24+BH24+BL24+BP24+BT24 -> 11741347
A25: 44834 | E25: =CY39 -> 4316023.6 | F25: NAV | H25: 44408 | I25: -1574.7883 | J25: -4624423 | K25: -596752.67 | L25: =L24+J25+K25 -> 3327254.1 | M25: -106.2427 | N25: -97199.4 | O25: -336238.86 | P25: =P24+N25+O25 -> 1710618.5 | Q25: 60.8575 | R25: 60857.58 | S25: -0.08 | T25: =T24+R25+S25 -> 60857.5 | AM25: -179.78 | AN25: =AN24+AL25+AM25 -> 101743.63 | AR25: =AR24+AP25+AQ25 -> 0 | AU25: -433.16 | AV25: =AV24+AT25+AU25 -> 245980.56 | AY25: -544.02 | AZ25: =AZ24+AX25+AY25 -> 316275.22 | BC25: -205.88 | BD25: =BD24+BB25+BC25 -> 117918.12 | BG25: -247.05 | BH25: =BH24+BF25+BG25 -> 141501.83 | BK25: -131.12 | BL25: =BL24+BJ25+BK25 -> 73826.66 | BO25: -86.96 | BP25: =BP24+BN25+BO25 -> 47603.66 | BS25: =-100.18-88.01 -> -188.19 | BT25: =BT24+BR25+BS25 -> 103918.26 | BU25: 275.2476 | BV25: 275247.52 | BW25: 0.08 | BX25: =BX24+BV25+BW25 -> 275247.6 | BY25: 11.0099 | BZ25: 11009.9 | CB25: =CB24+BZ25+CA25 -> 11009.9 | CW25: =J25+R25+AP25+AT25+N25+AX25+BB25+BF25+BJ25+BN25+BR25 -> -4660764.8 | CX25: =K25+S25+AQ25+AU25+O25+AY25+BC25+BG25+BK25+BO25+BS25+BW25+CA25 -> -934827.91 | CY25: =L25+T25+AR25+AV25+P25+AZ25+BD25+BH25+BL25+BP25+BT25+BX25+CB25 -> 6432011.9
A26: 44865 | E26: =CY40 -> 3935505.5 | F26: NAV | H26: 44439 | I26: -44.4142 | J26: -106958.12 | K26: -157550.81 | L26: =L25+J26+K26 -> 3062745.1 | M26: -63.0938 | N26: -54353.37 | O26: -99864.65 | P26: =P25+N26+O26 -> 1556400.5 | Q26: -2.0535 | R26: -1933.69 | S26: -3552.2 | T26: =T25+R26+S26 -> 55371.61 | AM26: -177.71 | AN26: =AN25+AL26+AM26 -> 101565.92 | AR26: =AR25+AP26+AQ26 -> 0 | AU26: -430.68 | AV26: =AV25+AT26+AU26 -> 245549.88 | AY26: -540.81 | AZ26: =AZ25+AX26+AY26 -> 315734.41 | BC26: -221.26 | BD26: =BD25+BB26+BC26 -> 117696.86 | BG26: -244.22 | BH26: =BH25+BF26+BG26 -> 141257.61 | BK26: -129.64 | BL26: =BL25+BJ26+BK26 -> 73697.02 | BO26: -103.22 | BP26: =BP25+BN26+BO26 -> 47500.44 | BS26: =-93.36-97.95 -> -191.31 | BT26: =BT25+BR26+BS26 -> 103726.95 | BW26: -476.18 | BX26: =BX25+BV26+BW26 -> 274771.42 | CA26: -27.86 | CB26: =CB25+BZ26+CA26 -> 10982.04 | CC26: 81.7284 | CD26: 81728.44 | CE26: -0.04 | CF26: =CF25+CD26+CE26 -> 81728.4 | CG26: 81.5167 | CH26: 81516.74 | CI26: -0.04 | CJ26: =CJ25+CH26+CI26 -> 81516.7 | CW26: =J26+R26+AP26+AT26+N26+AX26+BB26+BF26+BJ26+BN26+BR26 -> -163245.18 | CX26: =K26+S26+AQ26+AU26+O26+AY26+BC26+BG26+BK26+BO26+BS26+BW26+CA26+CE26+CI26 -> -263332.92 | CY26: =L26+T26+AR26+AV26+P26+AZ26+BD26+BH26+BL26+BP26+BT26+BX26+CB26+CF26+CJ26 -> 6168679
A27: 44895 | E27: =CY41 -> 4707575.3 | F27: NAV | H27: 44469 | I27: -0.0562 | J27: -135.47 | K27: -48224.34 | L27: =L26+J27+K27 -> 3014385.3 | M27: -0.0799 | N27: -68.84 | O27: -27857.76 | P27: =P26+N27+O27 -> 1528473.9 | Q27: -0.0025 | R27: -2.45 | S27: -991.3 | T27: =T26+R27+S27 -> 54377.86 | AM27: -177.72 | AN27: =AN26+AL27+AM27 -> 101388.2 | AR27: =AR26+AP27+AQ27 -> 0 | AU27: -428.18 | AV27: =AV26+AT27+AU27 -> 245121.7 | AY27: -544.01 | AZ27: =AZ26+AX27+AY27 -> 315190.4 | BC27: -204.69 | BD27: =BD26+BB27+BC27 -> 117492.17 | BG27: -244.21 | BH27: =BH26+BF27+BG27 -> 141013.4 | BK27: -129.65 | BL27: =BL26+BJ27+BK27 -> 73567.37 | BO27: -84.58 | BP27: =BP26+BN27+BO27 -> 47415.86 | BS27: =-86.07-98.51 -> -184.58 | BT27: =BT26+BR27+BS27 -> 103542.37 | BW27: -470.67 | BX27: =BX26+BV27+BW27 -> 274300.75 | CA27: -21.02 | CB27: =CB26+BZ27+CA27 -> 10961.02 | CE27: -147.93 | CF27: =CF26+CD27+CE27 -> 81580.47 | CG27: 0.02067 | CH27: 206.76 | CI27: -147.98 | CJ27: =CJ26+CH27+CI27 -> 81575.48 | CW27: =J27+R27+AP27+AT27+N27+AX27+BB27+BF27+BJ27+BN27+BR27 -> -206.76 | CX27: =K27+S27+AQ27+AU27+O27+AY27+BC27+BG27+BK27+BO27+BS27+BW27+CA27+CE27+CI27 -> -79680.9 | CY27: =L27+T27+AR27+AV27+P27+AZ27+BD27+BH27+BL27+BP27+BT27+BX27+CB27+CF27+CJ27 -> 6088998
A28: 44926 | E28: =CY42+0.01 -> 4824435.6 | F28: NAV | H28: 44500 | K28: -125864.34 | L28: =L27+J28+K28 -> 2888521 | O28: -63809.11 | P28: =P27+N28+O28 -> 1464664.8 | S28: -2270.32 | T28: =T27+R28+S28 -> 52107.54 | AM28: -176.68 | AN28: =AN27+AL28+AM28 -> 101211.52 | AR28: =AR27+AP28+AQ28 -> 0 | AU28: -428.19 | AV28: =AV27+AT28+AU28 -> 244693.51 | AY28: -537.61 | AZ28: =AZ27+AX28+AY28 -> 314652.79 | BC28: -203.52 | BD28: =BD27+BB28+BC28 -> 117288.65 | BG28: -244.22 | BH28: =BH27+BF28+BG28 -> 140769.18 | BK28: -128.9 | BL28: =BL27+BJ28+BK28 -> 73438.47 | BO28: -84.57 | BP28: =BP27+BN28+BO28 -> 47331.29 | BS28: =-86.07-97.95 -> -184.02 | BT28: =BT27+BR28+BS28 -> 103358.35 | BW28: -470.68 | BX28: =BX27+BV28+BW28 -> 273830.07 | CA28: -20.92 | CB28: =CB27+BZ28+CA28 -> 10940.1 | CE28: -141.39 | CF28: =CF27+CD28+CE28 -> 81439.08 | CI28: -141.38 | CJ28: =CJ27+CH28+CI28 -> 81434.1 | CW28: =J28+R28+AP28+AT28+N28+AX28+BB28+BF28+BJ28+BN28+BR28 -> 0 | CX28: =K28+S28+AQ28+AU28+O28+AY28+BC28+BG28+BK28+BO28+BS28+BW28+CA28+CE28+CI28 -> -194529.17 | CY28: =L28+T28+AR28+AV28+P28+AZ28+BD28+BH28+BL28+BP28+BT28+BX28+CB28+CF28+CJ28 -> 5894468.9
A29: 44943 | B29: 1000 | C29: =D29/B29 -> 1755.88 | D29: 1755880 | F29: 6th Redemption | H29: 44530 | I29: -8.3821 | J29: -17771.88 | K29: -192185.46 | L29: =L28+J29+K29 -> 2678563.7 | M29: -11.9075 | N29: -9011.48 | O29: -97448 | P29: =P28+N29+O29 -> 1358205.3 | Q29: -0.3874 | R29: -320.6 | S29: -3466.8 | T29: =T28+R29+S29 -> 48320.14 | AM29: -176.68 | AN29: =AN28+AL29+AM29 -> 101034.84 | AR29: =AR28+AP29+AQ29 -> 0 | AU29: -475.49 | AV29: =AV28+AT29+AU29 -> 244218.02 | AY29: -540.81 | AZ29: =AZ28+AX29+AY29 -> 314111.98 | BC29: -203.51 | BD29: =BD28+BB29+BC29 -> 117085.14 | BG29: -288.23 | BH29: =BH28+BF29+BG29 -> 140480.95 | BK29: -144.46 | BL29: =BL28+BJ29+BK29 -> 73294.01 | BO29: -243.22 | BP29: =BP28+BN29+BO29 -> 47088.07 | BS29: =-101.14-97.4 -> -198.54 | BT29: =BT28+BR29+BS29 -> 103159.81 | BW29: -594.53 | BX29: =BX28+BV29+BW29 -> 273235.54 | CA29: -20.92 | CB29: =CB28+BZ29+CA29 -> 10919.18 | CE29: -157.73 | CF29: =CF28+CD29+CE29 -> 81281.35 | CI29: -141.38 | CJ29: =CJ28+CH29+CI29 -> 81292.72 | CK29: 27.104 | CL29: 27103.96 | CM29: 0.04 | CN29: =CN28+CL29+CM29 -> 27104 | CW29: =J29+R29+AP29+AT29+N29+AX29+BB29+BF29+BJ29+BN29+BR29+BV29+BZ29+CD29+CH29+CL29+CP29+CT29 -> 0 | CX29: =K29+S29+AQ29+AU29+O29+AY29+BC29+BG29+BK29+BO29+BS29+BW29+CA29+CE29+CI29+CM29 -> -296109.04 | CY29: =L29+T29+AR29+AV29+P29+AZ29+BD29+BH29+BL29+BP29+BT29+BX29+CB29+CF29+CJ29+CN29 -> 5598359.8
A30: 44957 | E30: 3270164.8 | F30: NAV | H30: 44561 | K30: -124921.05 | L30: =L29+J30+K30 -> 2553642.6 | O30: -63352.64 | P30: =P29+N30+O30 -> 1294852.6 | S30: -2253.61 | T30: =T29+R30+S30 -> 46066.53 | U30: 75.0253 | V30: 75025.3 | W30: 0 | X30: =X29+V30+W30 -> 75025.3 | AM30: -175.65 | AN30: =AN29+AL30+AM30 -> 100859.19 | AR30: =AR29+AP30+AQ30 -> 0 | AU30: -428.18 | AV30: =AV29+AT30+AU30 -> 243789.84 | AY30: -540.81 | AZ30: =AZ29+AX30+AY30 -> 313571.17 | BC30: -203.51 | BD30: =BD29+BB30+BC30 -> 116881.63 | BG30: -244.22 | BH30: =BH29+BF30+BG30 -> 140236.73 | BI30: -74.0815 | BJ30: -75025.3 | BK30: 1731.29 | BL30: =BL29+BJ30+BK30 -> 6.3664629e-12 | BO30: -84.1 | BP30: =BP29+BN30+BO30 -> 47003.97 | BS30: =-86.55-97.95 -> -184.5 | BT30: =BT29+BR30+BS30 -> 102975.31 | BW30: -467.92 | BX30: =BX29+BV30+BW30 -> 272767.62 | CA30: -20.92 | CB30: =CB29+BZ30+CA30 -> 10898.26 | CE30: -141.39 | CF30: =CF29+CD30+CE30 -> 81139.96 | CI30: -140.57 | CJ30: =CJ29+CH30+CI30 -> 81152.15 | CM30: -55.29 | CN30: =CN29+CL30+CM30 -> 27048.71 | CW30: =J30+R30+AP30+AT30+N30+AX30+BB30+BF30+BJ30+BN30+BR30+BV30+BZ30+CD30+CH30+CL30+CP30+CT30 -> -75025.3 | CX30: =K30+S30+AQ30+AU30+O30+AY30+BC30+BG30+BK30+BO30+BS30+BW30+CA30+CE30+CI30+CM30+W30+CQ30+CU30 -> -191307.42 | CY30: =L30+T30+AR30+AV30+P30+AZ30+BD30+BH30+BL30+BP30+BT30+BX30+CB30+CF30+CJ30+CN30+X30+CR30+CV30 -> 5407052.4
A31: 44985 | E31: 3129594 | F31: NAV | H31: 44592 | I31: -9.7481 | J31: -18389.08 | K31: -170439.66 | L31: =L30+J31+K31 -> 2364813.9 | M31: -13.8479 | N31: -9324.39 | O31: -86414.39 | P31: =P30+N31+O31 -> 1199113.9 | Q31: -0.4505 | R31: -331.73 | S31: -3074.75 | T31: =T30+R31+S31 -> 42660.05 | U31: -0.5786 | V31: -540.27 | W31: -5006.9 | X31: =X30+V31+W31 -> 69478.13 | AM31: -176.68 | AN31: =AN30+AL31+AM31 -> 100682.51 | AR31: =AR30+AP31+AQ31 -> 0 | AU31: -430.68 | AV31: =AV30+AT31+AU31 -> 243359.16 | AY31: -537.61 | AZ31: =AZ30+AX31+AY31 -> 313033.56 | BC31: -204.7 | BD31: =BD30+BB31+BC31 -> 116676.93 | BG31: -244.21 | BH31: =BH30+BF31+BG31 -> 139992.52 | BL31: =BL30+BJ31+BK31 -> 6.3664629e-12 | BO31: -86.01 | BP31: =BP30+BN31+BO31 -> 46917.96 | BS31: =-87.53-97.4 -> -184.93 | BT31: =BT30+BR31+BS31 -> 102790.38 | BW31: -467.92 | BX31: =BX30+BV31+BW31 -> 272299.7 | CA31: -20.81 | CB31: =CB30+BZ31+CA31 -> 10877.45 | CE31: -142.21 | CF31: =CF30+CD31+CE31 -> 80997.75 | CI31: -140.56 | CJ31: =CJ30+CH31+CI31 -> 81011.59 | CM31: -48.25 | CN31: =CN30+CL31+CM31 -> 27000.46 | CO31: 20.5063 | CP31: 20506.24 | CQ31: 0.06 | CR31: =CR30+CP31+CQ31 -> 20506.3 | CS31: 8.0793 | CT31: 8079.23 | CU31: 0.07 | CV31: =CV30+CT31+CU31 -> 8079.3 | CW31: =J31+R31+AP31+AT31+N31+AX31+BB31+BF31+BJ31+BN31+BR31+BV31+BZ31+CD31+CH31+CL31+CP31+CT31 -> 540.27 | CX31: =K31+S31+AQ31+AU31+O31+AY31+BC31+BG31+BK31+BO31+BS31+BW31+CA31+CE31+CI31+CM31+W31+CQ31+CU31 -> -267443.46 | CY31: =L31+T31+AR31+AV31+P31+AZ31+BD31+BH31+BL31+BP31+BT31+BX31+CB31+CF31+CJ31+CN31+X31+CR31+CV31 -> 5139609
A32: 45016 | E32: 3137611.8 | F32: NAV | H32: 44620 | K32: -83014.2 | L32: =L31+J32+K32 -> 2281799.7 | O32: -42099.17 | P32: =P31+N32+O32 -> 1157014.7 | S32: -1497.2 | T32: =T31+R32+S32 -> 41162.85 | W32: -2438.88 | X32: =X31+V32+W32 -> 67039.25 | AM32: -219.04 | AN32: =AN31+AL32+AM32 -> 100463.47 | AR32: =AR31+AP32+AQ32 -> 0 | AU32: -490.42 | AV32: =AV31+AT32+AU32 -> 242868.74 | AY32: -537.61 | AZ32: =AZ31+AX32+AY32 -> 312495.95 | BC32: -227.18 | BD32: =BD31+BB32+BC32 -> 116449.75 | BG32: -244.22 | BH32: =BH31+BF32+BG32 -> 139748.3 | BL32: =BL31+BJ32+BK32 -> 6.3664629e-12 | BO32: -85.54 | BP32: =BP31+BN32+BO32 -> 46832.42 | BS32: =-108.92-119.1 -> -228.02 | BT32: =BT31+BR32+BS32 -> 102562.36 | BW32: -467.92 | BX32: =BX31+BV32+BW32 -> 271831.78 | CA32: -20.81 | CB32: =CB31+BZ32+CA32 -> 10856.64 | CE32: -141.39 | CF32: =CF31+CD32+CE32 -> 80856.36 | CI32: -145.47 | CJ32: =CJ31+CH32+CI32 -> 80866.12 | CM32: -79.95 | CN32: =CN31+CL32+CM32 -> 26920.51 | CQ32: -43.68 | CR32: =CR31+CP32+CQ32 -> 20462.62 | CU32: -22.46 | CV32: =CV31+CT32+CU32 -> 8056.84 | CW32: =J32+R32+AP32+AT32+N32+AX32+BB32+BF32+BJ32+BN32+BR32+BV32+BZ32+CD32+CH32+CL32+CP32+CT32 -> 0 | CX32: =K32+S32+AQ32+AU32+O32+AY32+BC32+BG32+BK32+BO32+BS32+BW32+CA32+CE32+CI32+CM32+W32+CQ32+CU32 -> -131784.12 | CY32: =L32+T32+AR32+AV32+P32+AZ32+BD32+BH32+BL32+BP32+BT32+BX32+CB32+CF32+CJ32+CN32+X32+CR32+CV32 -> 5007824.8
A33: 45046 | E33: 3054438.3 | F33: NAV | H33: 44651 | K33: -251800.52 | L33: =L32+J33+K33 -> 2029999.1 | O33: -127686.55 | P33: =P32+N33+O33 -> 1029328.1 | S33: -4542.61 | T33: =T32+R33+S33 -> 36620.24 | W33: -7398.51 | X33: =X32+V33+W33 -> 59640.74 | Y33: 55.4525 | Z33: 55452.57 | AA33: -0.07 | AB33: =AB32+Z33+AA33 -> 55452.5 | AF33: =AF32+AD33+AE33 -> 0 | AJ33: =AJ32+AH33+AI33 -> 0 | AM33: -308.93 | AN33: =AN32+AL33+AM33 -> 100154.54 | AR33: =AR32+AP33+AQ33 -> 0 | AU33: -428.19 | AV33: =AV32+AT33+AU33 -> 242440.55 | AY33: -534.41 | AZ33: =AZ32+AX33+AY33 -> 311961.54 | BC33: -203.51 | BD33: =BD32+BB33+BC33 -> 116246.24 | BG33: -244.22 | BH33: =BH32+BF33+BG33 -> 139504.08 | BL33: =BL32+BJ33+BK33 -> 6.3664629e-12 | BO33: -85.53 | BP33: =BP32+BN33+BO33 -> 46746.89 | BQ33: -55.6546 | BR33: -55452.57 | BS33: =-87.04+697.35 -> 610.31 | BT33: =BT32+BR33+BS33 -> 47720.1 | BW33: -465.17 | BX33: =BX32+BV33+BW33 -> 271366.61 | CA33: -21.58 | CB33: =CB32+BZ33+CA33 -> 10835.06 | CE33: -140.57 | CF33: =CF32+CD33+CE33 -> 80715.79 | CI33: -139.75 | CJ33: =CJ32+CH33+CI33 -> 80726.37 | CM33: -54.75 | CN33: =CN32+CL33+CM33 -> 26865.76 | CQ33: -38.76 | CR33: =CR32+CP33+CQ33 -> 20423.86 | CU33: -15.84 | CV33: =CV32+CT33+CU33 -> 8041 | CW33: =J33+R33+AP33+AT33+N33+AX33+BB33+BF33+BJ33+BN33+BR33+BV33+BZ33+CD33+CH33+CL33+CP33+CT33+V33+Z33 -> 0 | CX33: =K33+S33+AQ33+AU33+O33+AY33+BC33+BG33+BK33+BO33+BS33+BW33+CA33+CE33+CI33+CM33+CQ33+CU33+W33+AA33 -> -393190.23 | CY33: =L33+T33+AR33+AV33+P33+AZ33+BD33+BH33+BL33+BP33+BT33+BX33+CB33+CF33+CJ33+CN33+CR33+CV33+X33+AB33 -> 4614634.6
A34: 45077 | E34: 2845826.9 | F34: NAV | H34: 44681 | K34: -44114.61 | L34: =L33+J34+K34 -> 1985884.5 | O34: -22367.41 | P34: =P33+N34+O34 -> 1006960.7 | S34: -795.84 | T34: =T33+R34+S34 -> 35824.4 | W34: -1295.37 | X34: =X33+V34+W34 -> 58345.37 | AA34: -1204.98 | AB34: =AB33+Z34+AA34 -> 54247.52 | AF34: =AF33+AD34+AE34 -> 0 | AJ34: =AJ33+AH34+AI34 -> 0 | AM34: -175.65 | AN34: =AN33+AL34+AM34 -> 99978.89 | AR34: =AR33+AP34+AQ34 -> 0 | AU34: -153031.77 | AV34: =AV33+AT34+AU34 -> 89408.78 | AY34: -537.61 | AZ34: =AZ33+AX34+AY34 -> 311423.93 | BC34: -204.7 | BD34: =BD33+BB34+BC34 -> 116041.54 | BG34: -242.79 | BH34: =BH33+BF34+BG34 -> 139261.29 | BL34: =BL33+BJ34+BK34 -> 6.3664629e-12 | BO34: -85.53 | BP34: =BP33+BN34+BO34 -> 46661.36 | BS34: -87.04 | BT34: =BT33+BR34+BS34 -> 47633.06 | BW34: -465.17 | BX34: =BX33+BV34+BW34 -> 270901.44 | CA34: -20.7 | CB34: =CB33+BZ34+CA34 -> 10814.36 | CE34: -141.4 | CF34: =CF33+CD34+CE34 -> 80574.39 | CI34: -140.56 | CJ34: =CJ33+CH34+CI34 -> 80585.81 | CM34: -48.25 | CN34: =CN33+CL34+CM34 -> 26817.51 | CQ34: -37.11 | CR34: =CR33+CP34+CQ34 -> 20386.75 | CU34: -15.83 | CV34: =CV33+CT34+CU34 -> 8025.17 | CW34: =J34+R34+AP34+AT34+N34+AX34+BB34+BF34+BJ34+BN34+BR34+BV34+BZ34+CD34+CH34+CL34+CP34+CT34+V34+Z34 -> 0 | CX34: =K34+S34+AQ34+AU34+O34+AY34+BC34+BG34+BK34+BO34+BS34+BW34+CA34+CE34+CI34+CM34+CQ34+CU34+W34+AA34 -> -224836.67 | CY34: =L34+T34+AR34+AV34+P34+AZ34+BD34+BH34+BL34+BP34+BT34+BX34+CB34+CF34+CJ34+CN34+CR34+CV34+X34+AB34 -> 4389797.9
A35: 45107 | E35: 2882835 | F35: NAV | H35: 44712 | K35: 16936.3 | L35: =L34+J35+K35 -> 2002820.8 | O35: 8601.48 | P35: =P34+N35+O35 -> 1015562.2 | S35: 305.47 | T35: =T34+R35+S35 -> 36129.87 | W35: 497.3 | X35: =X34+V35+W35 -> 58842.67 | AA35: 462.47 | AB35: =AB34+Z35+AA35 -> 54709.99 | AF35: =AF34+AD35+AE35 -> 0 | AJ35: =AJ34+AH35+AI35 -> 0 | AM35: -264.51 | AN35: =AN34+AL35+AM35 -> 99714.38 | AO35: 140.3503 | AP35: 140350.32 | AQ35: -0.02 | AR35: =AR34+AP35+AQ35 -> 140350.3 | AU35: -169.29 | AV35: =AV34+AT35+AU35 -> 89239.49 | AY35: -534.42 | AZ35: =AZ34+AX35+AY35 -> 310889.51 | BC35: -203.51 | BD35: =BD34+BB35+BC35 -> 115838.03 | BE35: -141.986 | BF35: -140350.32 | BG35: 1089.03 | BH35: =BH34+BF35+BG35 -> 0 | BL35: =BL34+BJ35+BK35 -> 6.3664629e-12 | BO35: -85.06 | BP35: =BP34+BN35+BO35 -> 46576.3 | BS35: -86.56 | BT35: =BT34+BR35+BS35 -> 47546.5 | BW35: -467.92 | BX35: =BX34+BV35+BW35 -> 270433.52 | CA35: -21.24 | CB35: =CB34+BZ35+CA35 -> 10793.12 | CE35: -141.39 | CF35: =CF34+CD35+CE35 -> 80433 | CI35: -139.75 | CJ35: =CJ34+CH35+CI35 -> 80446.06 | CM35: -48.24 | CN35: =CN34+CL35+CM35 -> 26769.27 | CQ35: -37.32 | CR35: =CR34+CP35+CQ35 -> 20349.43 | CU35: -15.92 | CV35: =CV34+CT35+CU35 -> 8009.25 | CW35: =J35+R35+AP35+AT35+N35+AX35+BB35+BF35+BJ35+BN35+BR35+BV35+BZ35+CD35+CH35+CL35+CP35+CT35+V35+Z35+AL35 -> 0 | CX35: =K35+S35+AQ35+AU35+O35+AY35+BC35+BG35+BK35+BO35+BS35+BW35+CA35+CE35+CI35+CM35+CQ35+CU35+W35+AA35+AM35 -> 25676.9 | CY35: =L35+T35+AR35+AV35+P35+AZ35+BD35+BH35+BL35+BP35+BT35+BX35+CB35+CF35+CJ35+CN35+CR35+CV35+X35+AB35+AN35 -> 4515453.7
A36: 45138 | B36: =253.6121+140.6488 -> 394.2609 | C36: =D36/B36 -> 1234.6861 | D36: 486788.47 | F36: 7th Redemption | H36: 44742 | K36: 260262.4 | L36: =L35+J36+K36 -> 2263083.2 | O36: 131960.58 | P36: =P35+N36+O36 -> 1147522.8 | S36: 4695.05 | T36: =T35+R36+S36 -> 40824.92 | W36: 7646.42 | X36: =X35+V36+W36 -> 66489.09 | AA36: 5836.38 | AB36: =AB35+Z36+AA36 -> 60546.37 | AF36: =AF35+AD36+AE36 -> 0 | AJ36: =AJ35+AH36+AI36 -> 0 | AM36: -202.51 | AN36: =AN35+AL36+AM36 -> 99511.87 | AQ36: 14590.82 | AR36: =AR35+AP36+AQ36 -> 154941.12 | AU36: -226.54 | AV36: =AV35+AT36+AU36 -> 89012.95 | AY36: -556.81 | AZ36: =AZ35+AX36+AY36 -> 310332.7 | BC36: -225.99 | BD36: =BD35+BB36+BC36 -> 115612.04 | BH36: =BH35+BF36+BG36 -> 0 | BL36: =BL35+BJ36+BK36 -> 6.3664629e-12 | BO36: -107.51 | BP36: =BP35+BN36+BO36 -> 46468.79 | BS36: -108.92 | BT36: =BT35+BR36+BS36 -> 47437.58 | BW36: -478.93 | BX36: =BX35+BV36+BW36 -> 269954.59 | CA36: -38.65 | CB36: =CB35+BZ36+CA36 -> 10754.47 | CE36: -153.64 | CF36: =CF35+CD36+CE36 -> 80279.36 | CI36: -152.82 | CJ36: =CJ35+CH36+CI36 -> 80293.24 | CM36: -47.98 | CN36: =CN35+CL36+CM36 -> 26721.29 | CQ36: -36.91 | CR36: =CR35+CP36+CQ36 -> 20312.52 | CU36: -15.83 | CV36: =CV35+CT36+CU36 -> 7993.42 | CW36: =J36+R36+AP36+AT36+N36+AX36+BB36+BF36+BJ36+BN36+BR36+BV36+BZ36+CD36+CH36+CL36+CP36+CT36+V36+Z36+AL36 -> 0 | CX36: =K36+S36+AQ36+AU36+O36+AY36+BC36+BG36+BK36+BO36+BS36+BW36+CA36+CE36+CI36+CM36+CQ36+CU36+W36+AA36+AM36 -> 422638.61 | CY36: =L36+T36+AR36+AV36+P36+AZ36+BD36+BH36+BL36+BP36+BT36+BX36+CB36+CF36+CJ36+CN36+CR36+CV36+X36+AB36+AN36 -> 4938092.3
A37: 45138 | E37: 2480922.7 | F37: NAV | H37: 44773 | K37: -144779.66 | L37: =L36+J37+K37 -> 2118303.6 | O37: -73406.41 | P37: =P36+N37+O37 -> 1074116.4 | S37: -2611.84 | T37: =T36+R37+S37 -> 38213.08 | W37: -4253.14 | X37: =X36+V37+W37 -> 62235.95 | AA37: -3164.12 | AB37: =AB36+Z37+AA37 -> 57382.25 | AF37: =AF36+AD37+AE37 -> 0 | AJ37: =AJ36+AH37+AI37 -> 0 | AM37: -172.55 | AN37: =AN36+AL37+AM37 -> 99339.32 | AQ37: -8116.46 | AR37: =AR36+AP37+AQ37 -> 146824.66 | AU37: -166.79 | AV37: =AV36+AT37+AU37 -> 88846.16 | AY37: -531.21 | AZ37: =AZ36+AX37+AY37 -> 309801.49 | BC37: -202.33 | BD37: =BD36+BB37+BC37 -> 115409.71 | BO37: -85.06 | BP37: =BP36+BN37+BO37 -> 46383.73 | BS37: -86.07 | BT37: =BT36+BR37+BS37 -> 47351.51 | BW37: -462.42 | BX37: =BX36+BV37+BW37 -> 269492.17 | CA37: -20.59 | CB37: =CB36+BZ37+CA37 -> 10733.88 | CE37: -139.76 | CF37: =CF36+CD37+CE37 -> 80139.6 | CI37: -138.93 | CJ37: =CJ36+CH37+CI37 -> 80154.31 | CM37: -47.7 | CN37: =CN36+CL37+CM37 -> 26673.59 | CQ37: -36.71 | CR37: =CR36+CP37+CQ37 -> 20275.81 | CU37: -15.76 | CV37: =CV36+CT37+CU37 -> 7977.66 | CW37: =J37+R37+AP37+AT37+N37+AX37+BB37+BF37+BJ37+BN37+BR37+BV37+BZ37+CD37+CH37+CL37+CP37+CT37+V37+Z37+AL37 -> 0 | CX37: =K37+S37+AQ37+AU37+O37+AY37+BC37+BG37+BK37+BO37+BS37+BW37+CA37+CE37+CI37+CM37+CQ37+CU37+W37+AA37+AM37 -> -238437.51 | CY37: =L37+T37+AR37+AV37+P37+AZ37+BD37+BH37+BL37+BP37+BT37+BX37+CB37+CF37+CJ37+CN37+CR37+CV37+X37+AB37+AN37 -> 4699654.8
A38: 45169 | E38: 2392446.5 | F38: NAV | H38: 44804 | K38: -3322.07 | L38: =L37+J38+K38 -> 2114981.5 | O38: -1691.8 | P38: =P37+N38+O38 -> 1072424.6 | S38: -59.7 | T38: =T37+R38+S38 -> 38153.38 | W38: -98.27 | X38: =X37+V38+W38 -> 62137.68 | AA38: -72.65 | AB38: =AB37+Z38+AA38 -> 57309.6 | AF38: =AF37+AD38+AE38 -> 0 | AJ38: =AJ37+AH38+AI38 -> 0 | AM38: -171.51 | AN38: =AN37+AL38+AM38 -> 99167.81 | AQ38: -186.67 | AR38: =AR37+AP38+AQ38 -> 146637.99 | AU38: -166.79 | AV38: =AV37+AT38+AU38 -> 88679.37 | AY38: -531.21 | AZ38: =AZ37+AX38+AY38 -> 309270.28 | BC38: -202.33 | BD38: =BD37+BB38+BC38 -> 115207.38 | BO38: -84.57 | BP38: =BP37+BN38+BO38 -> 46299.16 | BS38: -86.55 | BT38: =BT37+BR38+BS38 -> 47264.96 | BW38: -462.41 | BX38: =BX37+BV38+BW38 -> 269029.76 | CA38: -20.59 | CB38: =CB37+BZ38+CA38 -> 10713.29 | CE38: -140.57 | CF38: =CF37+CD38+CE38 -> 79999.03 | CI38: -138.93 | CJ38: =CJ37+CH38+CI38 -> 80015.38 | CM38: -47.7 | CN38: =CN37+CL38+CM38 -> 26625.89 | CQ38: -36.71 | CR38: =CR37+CP38+CQ38 -> 20239.1 | CU38: -15.75 | CV38: =CV37+CT38+CU38 -> 7961.91 | CW38: =J38+R38+AP38+AT38+N38+AX38+BB38+BF38+BJ38+BN38+BR38+BV38+BZ38+CD38+CH38+CL38+CP38+CT38+V38+Z38+AL38 -> 0 | CX38: =K38+S38+AQ38+AU38+O38+AY38+BC38+BG38+BK38+BO38+BS38+BW38+CA38+CE38+CI38+CM38+CQ38+CU38+W38+AA38+AM38 -> -7536.78 | CY38: =L38+T38+AR38+AV38+P38+AZ38+BD38+BH38+BL38+BP38+BT38+BX38+CB38+CF38+CJ38+CN38+CR38+CV38+X38+AB38+AN38 -> 4692118
A39: 45199 | E39: 2363254.8 | F39: NAV | H39: 44834 | K39: -227618.35 | L39: =L38+J39+K39 -> 1887363.2 | O39: -115416.53 | P39: =P38+N39+O39 -> 957008.04 | S39: -4106.14 | T39: =T38+R39+S39 -> 34047.24 | W39: -6687.54 | X39: =X38+V39+W39 -> 55450.14 | AA39: -5753.75 | AB39: =AB38+Z39+AA39 -> 51555.85 | AF39: =AF38+AD39+AE39 -> 0 | AJ39: =AJ38+AH39+AI39 -> 0 | AM39: -180.82 | AN39: =AN38+AL39+AM39 -> 98986.99 | AQ39: -14378.88 | AR39: =AR38+AP39+AQ39 -> 132259.11 | AU39: -169.29 | AV39: =AV38+AT39+AU39 -> 88510.08 | AY39: -531.21 | AZ39: =AZ38+AX39+AY39 -> 308739.07 | BC39: -202.33 | BD39: =BD38+BB39+BC39 -> 115005.05 | BO39: -84.58 | BP39: =BP38+BN39+BO39 -> 46214.58 | BS39: -86.07 | BT39: =BT38+BR39+BS39 -> 47178.89 | BW39: -462.42 | BX39: =BX38+BV39+BW39 -> 268567.34 | CA39: -26.2 | CB39: =CB38+BZ39+CA39 -> 10687.09 | CE39: -139.76 | CF39: =CF38+CD39+CE39 -> 79859.27 | CI39: -141.38 | CJ39: =CJ38+CH39+CI39 -> 79874 | CM39: -52.04 | CN39: =CN38+CL39+CM39 -> 26573.85 | CQ39: -41.42 | CR39: =CR38+CP39+CQ39 -> 20197.68 | CU39: -15.76 | CV39: =CV38+CT39+CU39 -> 7946.15 | CW39: =J39+R39+AP39+AT39+N39+AX39+BB39+BF39+BJ39+BN39+BR39+BV39+BZ39+CD39+CH39+CL39+CP39+CT39+V39+Z39+AL39 -> 0 | CX39: =K39+S39+AQ39+AU39+O39+AY39+BC39+BG39+BK39+BO39+BS39+BW39+CA39+CE39+CI39+CM39+CQ39+CU39+W39+AA39+AM39 -> -376094.47 | CY39: =L39+T39+AR39+AV39+P39+AZ39+BD39+BH39+BL39+BP39+BT39+BX39+CB39+CF39+CJ39+CN39+CR39+CV39+X39+AB39+AN39 -> 4316023.6
A40: 45200 | B40: 851.1664 | C40: =D40/B40 -> 561.08002 | D40: 477572.46 | F40: 8th Redemption | H40: 44865 | K40: -229110.15 | L40: =L39+J40+K40 -> 1658253 | O40: -116164.49 | P40: =P39+N40+O40 -> 840843.55 | S40: -4132.81 | T40: =T39+R40+S40 -> 29914.43 | W40: -6730.73 | X40: =X39+V40+W40 -> 48719.41 | AA40: -6258.37 | AB40: =AB39+Z40+AA40 -> 45297.48 | AF40: =AF39+AD40+AE40 -> 0 | AJ40: =AJ39+AH40+AI40 -> 0 | AM40: -171.51 | AN40: =AN39+AL40+AM40 -> 98815.48 | AQ40: -16054.68 | AR40: =AR39+AP40+AQ40 -> 116204.43 | AU40: -164.3 | AV40: =AV39+AT40+AU40 -> 88345.78 | AY40: -502.41 | AZ40: =AZ39+AX40+AY40 -> 308236.66 | BC40: -201.15 | BD40: =BD39+BB40+BC40 -> 114803.9 | BO40: -84.58 | BP40: =BP39+BN40+BO40 -> 46130 | BS40: -86.07 | BT40: =BT39+BR40+BS40 -> 47092.82 | BW40: -459.66 | BX40: =BX39+BV40+BW40 -> 268107.68 | CA40: -20.48 | CB40: =CB39+BZ40+CA40 -> 10666.61 | CE40: -138.94 | CF40: =CF39+CD40+CE40 -> 79720.33 | CI40: -138.11 | CJ40: =CJ39+CH40+CI40 -> 79735.89 | CM40: -47.44 | CN40: =CN39+CL40+CM40 -> 26526.41 | CQ40: -36.5 | CR40: =CR39+CP40+CQ40 -> 20161.18 | CU40: -15.67 | CV40: =CV39+CT40+CU40 -> 7930.48 | CW40: =J40+R40+AP40+AT40+N40+AX40+BB40+BF40+BJ40+BN40+BR40+BV40+BZ40+CD40+CH40+CL40+CP40+CT40+V40+Z40+AL40 -> 0 | CX40: =K40+S40+AQ40+AU40+O40+AY40+BC40+BG40+BK40+BO40+BS40+BW40+CA40+CE40+CI40+CM40+CQ40+CU40+W40+AA40+AM40 -> -380518.05 | CY40: =L40+T40+AR40+AV40+P40+AZ40+BD40+BH40+BL40+BP40+BT40+BX40+CB40+CF40+CJ40+CN40+CR40+CV40+X40+AB40+AN40+0.01 -> 3935505.5
A41: 45230 | E41: 1878008.5 | F41: NAV | H41: 44895 | K41: 470066.93 | L41: =L40+J41+K41 -> 2128319.9 | O41: 238348.23 | P41: =P40+N41+O41 -> 1079191.8 | S41: 8479.5 | T41: =T40+R41+S41 -> 38393.93 | W41: 13810.61 | X41: =X40+V41+W41 -> 62530.02 | AA41: 12303.25 | AB41: =AB40+Z41+AA41 -> 57600.73 | AF41: =AF40+AD41+AE41 -> 0 | AJ41: =AJ40+AH41+AI41 -> 0 | AM41: -176.68 | AN41: =AN40+AL41+AM41 -> 98638.8 | AQ41: 31181.63 | AR41: =AR40+AP41+AQ41 -> 147386.06 | AU41: -169.28 | AV41: =AV40+AT41+AU41 -> 88176.5 | AY41: -534.41 | AZ41: =AZ40+AX41+AY41 -> 307702.25 | BC41: -202.33 | BD41: =BD40+BB41+BC41 -> 114601.57 | BO41: -84.57 | BP41: =BP40+BN41+BO41 -> 46045.43 | BS41: -86.07 | BT41: =BT40+BR41+BS41 -> 47006.75 | BW41: -465.17 | BX41: =BX40+BV41+BW41 -> 267642.51 | CA41: -20.59 | CB41: =CB40+BZ41+CA41 -> 10646.02 | CE41: -140.57 | CF41: =CF40+CD41+CE41 -> 79579.76 | CI41: -138.93 | CJ41: =CJ40+CH41+CI41 -> 79596.96 | CM41: -47.7 | CN41: =CN40+CL41+CM41 -> 26478.71 | CQ41: -37.94 | CR41: =CR40+CP41+CQ41 -> 20123.24 | CU41: -16.16 | CV41: =CV40+CT41+CU41 -> 7914.32 | CW41: =J41+R41+AP41+AT41+N41+AX41+BB41+BF41+BJ41+BN41+BR41+BV41+BZ41+CD41+CH41+CL41+CP41+CT41+V41+Z41+AL41 -> 0 | CX41: =K41+S41+AQ41+AU41+O41+AY41+BC41+BG41+BK41+BO41+BS41+BW41+CA41+CE41+CI41+CM41+CQ41+CU41+W41+AA41+AM41 -> 772069.75 | CY41: =L41+T41+AR41+AV41+P41+AZ41+BD41+BH41+BL41+BP41+BT41+BX41+CB41+CF41+CJ41+CN41+CR41+CV41+X41+AB41+AN41-0.02 -> 4707575.3
A42: 45260 | E42: 1941163.8 | F42: NAV | H42: 45291 | K42: 72872.47 | L42: =L41+J42+K42 -> 2201192.4 | O42: 36952.52 | P42: =P41+N42+O42 -> 1116144.3 | S42: 1314.61 | T42: =T41+R42+S42 -> 39708.54 | W42: 2141.08 | X42: =X41+V42+W42 -> 64671.1 | AA42: 1592.6 | AB42: =AB41+Z42+AA42 -> 59193.33 | AF42: =AF41+AD42+AE42 -> 0 | AJ42: =AJ41+AH42+AI42 -> 0 | AM42: -174.62 | AN42: =AN41+AL42+AM42 -> 98464.18 | AQ42: 4085.6 | AR42: =AR41+AP42+AQ42 -> 151471.66 | AU42: -166.8 | AV42: =AV41+AT42+AU42 -> 88009.7 | AY42: -528.01 | AZ42: =AZ41+AX42+AY42 -> 307174.24 | BC42: -202.33 | BD42: =BD41+BB42+BC42 -> 114399.24 | BO42: -84.1 | BP42: =BP41+BN42+BO42 -> 45961.33 | BS42: -86.06 | BT42: =BT41+BR42+BS42 -> 46920.69 | BW42: -459.66 | BX42: =BX41+BV42+BW42 -> 267182.85 | CA42: -20.37 | CB42: =CB41+BZ42+CA42 -> 10625.65 | CE42: -138.94 | CF42: =CF41+CD42+CE42 -> 79440.82 | CI42: -138.12 | CJ42: =CJ41+CH42+CI42 -> 79458.84 | CM42: -47.43 | CN42: =CN41+CL42+CM42 -> 26431.28 | CQ42: -36.5 | CR42: =CR41+CP42+CQ42 -> 20086.74 | CU42: -15.59 | CV42: =CV41+CT42+CU42 -> 7898.73 | CW42: =J42+R42+AP42+AT42+N42+AX42+BB42+BF42+BJ42+BN42+BR42+BV42+BZ42+CD42+CH42+CL42+CP42+CT42+V42+Z42+AL42 -> 0 | CX42: =K42+S42+AQ42+AU42+O42+AY42+BC42+BG42+BK42+BO42+BS42+BW42+CA42+CE42+CI42+CM42+CQ42+CU42+W42+AA42+AM42 -> 116860.35 | CY42: =L42+T42+AR42+AV42+P42+AZ42+BD42+BH42+BL42+BP42+BT42+BX42+CB42+CF42+CJ42+CN42+CR42+CV42+X42+AB42+AN42-0.02 -> 4824435.6
A43: 45291 | E43: =CY54 -> 1968470.9 | F43: NAV | H43: 44957 | I43: -1000000 | J43: -1755880 | K43: 48787.36 | L43: =L42+J43+K43 -> 494099.77 | O43: 122272.78 | P43: =P42+N43+O43 -> 1238417.1 | S43: 4350.17 | T43: =T42+R43+S43 -> 44058.71 | W43: 7085.1 | X43: =X42+V43+W43 -> 71756.2 | Y43: 141.8991 | Z43: 151471.66 | AA43: 18464.16 | AB43: =AB42+Z43+AA43 -> 229129.15 | AF43: =AF42+AD43+AE43 -> 0 | AJ43: =AJ42+AH43+AI43 -> 0 | AM43: -174.61 | AN43: =AN42+AL43+AM43 -> 98289.57 | AU43: 2574.1 | AV43: =AV42+AT43+AU43 -> 90583.8 | AY43: -528.01 | AZ43: =AZ42+AX43+AY43 -> 306646.23 | BC43: -198.78 | BD43: =BD42+BB43+BC43 -> 114200.46 | BO43: -82.67 | BP43: =BP42+BN43+BO43 -> 45878.66 | BS43: -83.64 | BT43: =BT42+BR43+BS43 -> 46837.05 | BW43: -459.67 | BX43: =BX42+BV43+BW43 -> 266723.18 | CA43: -20.47 | CB43: =CB42+BZ43+CA43 -> 10605.18 | CE43: -138.94 | CF43: =CF42+CD43+CE43 -> 79301.88 | CI43: -138.11 | CJ43: =CJ42+CH43+CI43 -> 79320.73 | CM43: -47.43 | CN43: =CN42+CL43+CM43 -> 26383.85 | CQ43: -36.5 | CR43: =CR42+CP43+CQ43 -> 20050.24 | CU43: -15.68 | CV43: =CV42+CT43+CU43 -> 7883.05 | CW43: =J43+R43+AP43+AT43+N43+AX43+BB43+BF43+BJ43+BN43+BR43+BV43+BZ43+CD43+CH43+CL43+CP43+CT43+V43+Z43+AL43 -> -1604408.3 | CX43: =K43+S43+AQ43+AU43+O43+AY43+BC43+BG43+BK43+BO43+BS43+BW43+CA43+CE43+CI43+CM43+CQ43+CU43+W43+AA43+AM43 -> 201609.16 | CY43: =L43+T43+AR43+AV43+P43+AZ43+BD43+BH43+BL43+BP43+BT43+BX43+CB43+CF43+CJ43+CN43+CR43+CV43+X43+AB43+AN43 -> 3270164.8
A44: 45310 | B44: =56.5543+789.0292 -> 845.5835 | C44: =D44/B44 -> 603.4822 | D44: 510294.59 | F44: 9th Redemption | H44: 44985 | K44: -34978.18 | L44: =L43+J44+K44 -> 459121.59 | O44: -87670.97 | P44: =P43+N44+O44 -> 1150746.1 | S44: -3119.02 | T44: =T43+R44+S44 -> 40939.69 | W44: -5080.25 | X44: =X43+V44+W44 -> 66675.95 | AA44: -13238.34 | AB44: =AB43+Z44+AA44 -> 215890.81 | AF44: =AF43+AD44+AE44 -> 0 | AJ44: =AJ43+AH44+AI44 -> 0 | AM44: -169.45 | AN44: =AN43+AL44+AM44 -> 98120.12 | AU44: 5449.42 | AV44: =AV43+AT44+AU44 -> 96033.22 | AY44: -528.01 | AZ44: =AZ43+AX44+AY44 -> 306118.22 | BC44: -198.78 | BD44: =BD43+BB44+BC44 -> 114001.68 | BO44: -82.19 | BP44: =BP43+BN44+BO44 -> 45796.47 | BS44: -83.64 | BT44: =BT43+BR44+BS44 -> 46753.41 | BW44: -456.91 | BX44: =BX43+BV44+BW44 -> 266266.27 | CA44: -20.26 | CB44: =CB43+BZ44+CA44 -> 10584.92 | CE44: -137.3 | CF44: =CF43+CD44+CE44 -> 79164.58 | CI44: -137.29 | CJ44: =CJ43+CH44+CI44 -> 79183.44 | CM44: -47.16 | CN44: =CN43+CL44+CM44 -> 26336.69 | CQ44: -56.8 | CR44: =CR43+CP44+CQ44 -> 19993.44 | CU44: -15.59 | CV44: =CV43+CT44+CU44 -> 7867.46 | CW44: =J44+R44+AP44+AT44+N44+AX44+BB44+BF44+BJ44+BN44+BR44+BV44+BZ44+CD44+CH44+CL44+CP44+CT44+V44+Z44+AL44 -> 0 | CX44: =K44+S44+AQ44+AU44+O44+AY44+BC44+BG44+BK44+BO44+BS44+BW44+CA44+CE44+CI44+CM44+CQ44+CU44+W44+AA44+AM44 -> -140570.72 | CY44: =L44+T44+AR44+AV44+P44+AZ44+BD44+BH44+BL44+BP44+BT44+BX44+CB44+CF44+CJ44+CN44+CR44+CV44+X44+AB44+AN44 -> 3129594.1
A45: 45351 | E45: 1369830.3 | F45: NAV | H45: 45016 | K45: 2883.57 | L45: =L44+J45+K45 -> 462005.16 | O45: 7230.23 | P45: =P44+N45+O45 -> 1157976.3 | S45: 257.36 | T45: =T44+R45+S45 -> 41197.05 | W45: 419.14 | X45: =X44+V45+W45 -> 67095.09 | AA45: 1091.35 | AB45: =AB44+Z45+AA45 -> 216982.16 | AF45: =AF44+AD45+AE45 -> 0 | AJ45: =AJ44+AH45+AI45 -> 0 | AM45: -182.88 | AN45: =AN44+AL45+AM45 -> 97937.24 | AU45: -1862.12 | AV45: =AV44+AT45+AU45 -> 94171.1 | AY45: -556.81 | AZ45: =AZ44+AX45+AY45 -> 305561.41 | BC45: -212.98 | BD45: =BD44+BB45+BC45 -> 113788.7 | BO45: -85.53 | BP45: =BP44+BN45+BO45 -> 45710.94 | BS45: -95.79 | BT45: =BT44+BR45+BS45 -> 46657.62 | BW45: -456.91 | BX45: =BX44+BV45+BW45 -> 265809.36 | CA45: -25.99 | CB45: =CB44+BZ45+CA45 -> 10558.93 | CE45: -137.3 | CF45: =CF44+CD45+CE45 -> 79027.28 | CI45: -137.3 | CJ45: =CJ44+CH45+CI45 -> 79046.14 | CM45: -52.86 | CN45: =CN44+CL45+CM45 -> 26283.83 | CQ45: -41.84 | CR45: =CR44+CP45+CQ45 -> 19951.6 | CU45: -15.59 | CV45: =CV44+CT45+CU45 -> 7851.87 | CW45: =J45+R45+AP45+AT45+N45+AX45+BB45+BF45+BJ45+BN45+BR45+BV45+BZ45+CD45+CH45+CL45+CP45+CT45+V45+Z45+AL45 -> 0 | CX45: =K45+S45+AQ45+AU45+O45+AY45+BC45+BG45+BK45+BO45+BS45+BW45+CA45+CE45+CI45+CM45+CQ45+CU45+W45+AA45+AM45 -> 8017.75 | CY45: =L45+T45+AR45+AV45+P45+AZ45+BD45+BH45+BL45+BP45+BT45+BX45+CB45+CF45+CJ45+CN45+CR45+CV45+X45+AB45+AN45 -> 3137611.8
A46: 45382 | E46: 1416123.6 | F46: NAV | H46: 45046 | K46: -20978.79 | L46: =L45+J46+K46 -> 441026.37 | O46: -52570.53 | P46: =P45+N46+O46 -> 1105405.8 | S46: -1870.49 | T46: =T45+R46+S46 -> 39326.56 | W46: -3047.11 | X46: =X45+V46+W46 -> 64047.98 | AA46: -8346 | AB46: =AB45+Z46+AA46 -> 208636.16 | AF46: =AF45+AD46+AE46 -> 0 | AJ46: =AJ45+AH46+AI46 -> 0 | AM46: -170.49 | AN46: =AN45+AL46+AM46 -> 97766.75 | AU46: 5549 | AV46: =AV45+AT46+AU46 -> 99720.1 | AY46: -524.81 | AZ46: =AZ45+AX46+AY46 -> 305036.6 | BC46: -197.6 | BD46: =BD45+BB46+BC46 -> 113591.1 | BO46: -82.19 | BP46: =BP45+BN46+BO46 -> 45628.75 | BS46: -83.15 | BT46: =BT45+BR46+BS46 -> 46574.47 | BW46: -456.91 | BX46: =BX45+BV46+BW46 -> 265352.45 | CA46: -20.25 | CB46: =CB45+BZ46+CA46 -> 10538.68 | CE46: -138.12 | CF46: =CF45+CD46+CE46 -> 78889.16 | CI46: -137.29 | CJ46: =CJ45+CH46+CI46 -> 78908.85 | CM46: -47.16 | CN46: =CN45+CL46+CM46 -> 26236.67 | CQ46: -36.09 | CR46: =CR45+CP46+CQ46 -> 19915.51 | CU46: -15.51 | CV46: =CV45+CT46+CU46 -> 7836.36 | CW46: =J46+R46+AP46+AT46+N46+AX46+BB46+BF46+BJ46+BN46+BR46+BV46+BZ46+CD46+CH46+CL46+CP46+CT46+V46+Z46+AL46 -> 0 | CX46: =K46+S46+AQ46+AU46+O46+AY46+BC46+BG46+BK46+BO46+BS46+BW46+CA46+CE46+CI46+CM46+CQ46+CU46+W46+AA46+AM46 -> -83173.49 | CY46: =L46+T46+AR46+AV46+P46+AZ46+BD46+BH46+BL46+BP46+BT46+BX46+CB46+CF46+CJ46+CN46+CR46+CV46+X46+AB46+AN46 -> 3054438.3
A47: 45401 | B47: 524.1022 | C47: =D47/B47 -> 902.99661 | D47: 473262.51 | E47: =E46-D47-1670.87 -> 941190.25 | F47: 10th Redemption | H47: 45077 | K47: -42791.97 | L47: =L46+J47+K47 -> 398234.4 | O47: -107260.27 | P47: =P46+N47+O47 -> 998145.54 | S47: -3815.74 | T47: =T46+R47+S47 -> 35510.82 | W47: -6214.06 | X47: =X46+V47+W47 -> 57833.92 | AA47: -20242.35 | AB47: =AB46+Z47+AA47 -> 188393.81 | AC47: 212.2819 | AD47: 212281.98 | AE47: -20597.79 | AF47: =AF46+AD47+AE47 -> 191684.19 | AJ47: =AJ46+AH47+AI47 -> 0 | AM47: -168.41 | AN47: =AN46+AL47+AM47 -> 97598.34 | AU47: -6134.02 | AV47: =AV46+AT47+AU47 -> 93586.08 | AY47: -524.81 | AZ47: =AZ46+AX47+AY47 -> 304511.79 | BC47: -197.59 | BD47: =BD46+BB47+BC47 -> 113393.51 | BO47: -81.23 | BP47: =BP46+BN47+BO47 -> 45547.52 | BS47: -83.15 | BT47: =BT46+BR47+BS47 -> 46491.32 | BU47: -220.1981 | BV47: -212281.98 | BW47: -92.48 | BX47: =BX46+BV47+BW47 -> 52977.99 | CA47: -20.26 | CB47: =CB46+BZ47+CA47 -> 10518.42 | CE47: -137.31 | CF47: =CF46+CD47+CE47 -> 78751.85 | CI47: -136.48 | CJ47: =CJ46+CH47+CI47 -> 78772.37 | CM47: -54.48 | CN47: =CN46+CL47+CM47 -> 26182.19 | CQ47: -43.47 | CR47: =CR46+CP47+CQ47 -> 19872.04 | CU47: -15.52 | CV47: =CV46+CT47+CU47 -> 7820.84 | CW47: =J47+R47+AP47+AT47+N47+AX47+BB47+BF47+BJ47+BN47+BR47+BV47+BZ47+CD47+CH47+CL47+CP47+CT47+V47+Z47+AL47 -> -212281.98 | CX47: =K47+S47+AQ47+AU47+O47+AY47+BC47+BG47+BK47+BO47+BS47+BW47+CA47+CE47+CI47+CM47+CQ47+CU47+W47+AA47+AM47+AE47 -> -208611.39 | CY47: =L47+T47+AR47+AV47+P47+AZ47+BD47+BH47+BL47+BP47+BT47+BX47+CB47+CF47+CJ47+CN47+CR47+CV47+X47+AB47+AN47+AF47 -> 2845826.9
A48: 45443 | E48: 94190.26 | F48: NAV | H48: 45107 | K48: 8115.59 | L48: =L47+J48+K48 -> 406349.99 | O48: 20337.25 | P48: =P47+N48+O48 -> 1018482.8 | S48: 723.39 | T48: =T47+R48+S48 -> 36234.21 | W48: 1178.49 | X48: =X47+V48+W48 -> 59012.41 | AA48: 3838.49 | AB48: =AB47+Z48+AA48 -> 192232.3 | AE48: 3905.98 | AF48: =AF47+AD48+AE48 -> 195590.17 | AG48: 38.6126 | AH48: 38612.63 | AI48: 639.39 | AJ48: =AJ47+AH48+AI48 -> 39252.02 | AM48: -169.45 | AN48: =AN47+AL48+AM48 -> 97428.89 | AS48: -102.7123 | AT48: -38612.63 | AU48: -105.29 | AV48: =AV47+AT48+AU48 -> 54868.16 | AY48: -524.82 | AZ48: =AZ47+AX48+AY48 -> 303986.97 | BC48: -197.6 | BD48: =BD47+BB48+BC48 -> 113195.91 | BO48: -81.71 | BP48: =BP47+BN48+BO48 -> 45465.81 | BS48: -83.15 | BT48: =BT47+BR48+BS48 -> 46408.17 | BW48: -93.04 | BX48: =BX47+BV48+BW48 -> 52884.95 | CA48: -20.59 | CB48: =CB47+BZ48+CA48 -> 10497.83 | CE48: -196.15 | CF48: =CF47+CD48+CE48 -> 78555.7 | CI48: -160.18 | CJ48: =CJ47+CH48+CI48 -> 78612.19 | CM48: -46.89 | CN48: =CN47+CL48+CM48 -> 26135.3 | CQ48: -36.09 | CR48: =CR47+CP48+CQ48 -> 19835.95 | CU48: -15.51 | CV48: =CV47+CT48+CU48 -> 7805.33 | CW48: =J48+R48+AP48+AT48+N48+AX48+BB48+BF48+BJ48+BN48+BR48+BV48+BZ48+CD48+CH48+CL48+CP48+CT48+V48+Z48+AL48 -> -38612.63 | CX48: =K48+S48+AQ48+AU48+O48+AY48+BC48+BG48+BK48+BO48+BS48+BW48+CA48+CE48+CI48+CM48+CQ48+CU48+W48+AA48+AM48+AE48+AI48 -> 37008.11 | CY48: =L48+T48+AR48+AV48+P48+AZ48+BD48+BH48+BL48+BP48+BT48+BX48+CB48+CF48+CJ48+CN48+CR48+CV48+X48+AB48+AN48+AF48+AJ48 -> 2882835.1
A49: 45473 | E49: 937791.7 | F49: NAV | H49: 45138 | I49: -253.6121 | J49: -406349.99 | K49: 0 | L49: =L48+J49+K49 -> 1.7462298e-10 | M49: -140.6488 | N49: -80438.48 | O49: 56029.11 | P49: =P48+N49+O49 -> 994073.42 | S49: 2164.36 | T49: =T48+R49+S49 -> 38398.57 | W49: 3525.05 | X49: =X48+V49+W49 -> 62537.46 | AA49: 11481.92 | AB49: =AB48+Z49+AA49 -> 203714.22 | AE49: 11684 | AF49: =AF48+AD49+AE49 -> 207274.17 | AI49: 1883.53 | AJ49: =AJ48+AH49+AI49 -> 41135.55 | AM49: -193.21 | AN49: =AN48+AL49+AM49 -> 97235.68 | AU49: -157.93 | AV49: =AV48+AT49+AU49 -> 54710.23 | AY49: -566.41 | AZ49: =AZ48+AX49+AY49 -> 303420.56 | BC49: -227.18 | BD49: =BD48+BB49+BC49 -> 112968.73 | BO49: -110.86 | BP49: =BP48+BN49+BO49 -> 45354.95 | BS49: -89.47 | BT49: =BT48+BR49+BS49 -> 46318.7 | BW49: -105.14 | BX49: =BX48+BV49+BW49 -> 52779.81 | CA49: -32.81 | CB49: =CB48+BZ49+CA49 -> 10465.02 | CE49: -137.3 | CF49: =CF48+CD49+CE49 -> 78418.4 | CI49: -149.55 | CJ49: =CJ48+CH49+CI49 -> 78462.64 | CM49: -57.73 | CN49: =CN48+CL49+CM49 -> 26077.57 | CQ49: -47.78 | CR49: =CR48+CP49+CQ49 -> 19788.17 | CU49: -16.48 | CV49: =CV48+CT49+CU49 -> 7788.85 | CW49: =J49+R49+AP49+AT49+N49+AX49+BB49+BF49+BJ49+BN49+BR49+BV49+BZ49+CD49+CH49+CL49+CP49+CT49+V49+Z49+AL49 -> -486788.47 | CX49: =K49+S49+AQ49+AU49+O49+AY49+BC49+BG49+BK49+BO49+BS49+BW49+CA49+CE49+CI49+CM49+CQ49+CU49+W49+AA49+AM49+AE49+AI49 -> 84876.12 | CY49: =L49+T49+AR49+AV49+P49+AZ49+BD49+BH49+BL49+BP49+BT49+BX49+CB49+CF49+CJ49+CN49+CR49+CV49+X49+AB49+AN49+AF49+AJ49 -> 2480922.7
A50: 45504 | E50: 936123.6 | F50: NAV | H50: 45169 | L50: =L49+J50+K50 -> 1.7462298e-10 | O50: -56012.69 | P50: =P49+N50+O50 -> 938060.73 | S50: -2163.78 | T50: =T49+R50+S50 -> 36234.79 | W50: -3524.31 | X50: =X49+V50+W50 -> 59013.15 | AA50: -11479.95 | AB50: =AB49+Z50+AA50 -> 192234.27 | AE50: -11679.75 | AF50: =AF49+AD50+AE50 -> 195594.42 | AI50: -1882.75 | AJ50: =AJ49+AH50+AI50 -> 39252.8 | AM50: -169.45 | AN50: =AN49+AL50+AM50 -> 97066.23 | AU50: -128.69 | AV50: =AV49+AT50+AU50 -> 54581.54 | AY50: -521.61 | AZ50: =AZ49+AX50+AY50 -> 302898.95 | BC50: -205.88 | BD50: =BD49+BB50+BC50 -> 112762.85 | BO50: -90.31 | BP50: =BP49+BN50+BO50 -> 45264.64 | BS50: -95.31 | BT50: =BT49+BR50+BS50 -> 46223.39 | BW50: -97.99 | BX50: =BX49+BV50+BW50 -> 52681.82 | CA50: -20.37 | CB50: =CB49+BZ50+CA50 -> 10444.65 | CE50: -156.92 | CF50: =CF49+CD50+CE50 -> 78261.48 | CI50: -136.48 | CJ50: =CJ49+CH50+CI50 -> 78326.16 | CM50: -46.62 | CN50: =CN49+CL50+CM50 -> 26030.95 | CQ50: -35.68 | CR50: =CR49+CP50+CQ50 -> 19752.49 | CU50: -27.71 | CV50: =CV49+CT50+CU50 -> 7761.14 | CW50: =J50+R50+AP50+AT50+N50+AX50+BB50+BF50+BJ50+BN50+BR50+BV50+BZ50+CD50+CH50+CL50+CP50+CT50+V50+Z50+AL50 -> 0 | CX50: =K50+S50+AQ50+AU50+O50+AY50+BC50+BG50+BK50+BO50+BS50+BW50+CA50+CE50+CI50+CM50+CQ50+CU50+W50+AA50+AM50+AE50+AI50 -> -88476.25 | CY50: =L50+T50+AR50+AV50+P50+AZ50+BD50+BH50+BL50+BP50+BT50+BX50+CB50+CF50+CJ50+CN50+CR50+CV50+X50+AB50+AN50+AF50+AJ50 -> 2392446.5
